Workbook

Sheet Cover
A1: Power Demand Model
A3: Model version: | B3: ef58fe6 (2026-07-07 15:25) [dirty] + cooling split and climate adjustment (2026-10-23)
A4: Scenario: | B4: FEL 2026 | Base FEL | Base
A6: Scenario Parameters
A7: Parameter | B7: Preset | C7: Scaling
A8: BEV share of vehicle sales | B8: base_fel | C8: 1
A9: Buildings scenario | B9: base_fel
A10: Industry scenario | B10: base_fel | C10: 1
A11: Industry electrification — Iron & Steel | B11: base_fel | C11: 1
A12: Industry electrification — Chemicals | B12: base_fel | C12: 1
A13: Industry electrification — Other | B13: base_fel | C13: 1
A14: Data center scenario | B14: base_fel
A15: DC BTM/FTM sensitivity | B15: base_fel
A16: Hydrogen scenario | B16: base_fel
A17: Energy efficiency improvements | B17: base_fel | C17: 1
A18: GDP growth | B18: base_fel | C18: 1
A19: Power prices | B19: base_fel | C19: 1
A20: Transport scenario | B20: base_fel
A21: US transport BEV scenario | B21: base_fel
A22: Cooling split (own sector) | B22: pdm_2026-09-23
A23: Physical climate pathway (cooling/heating, NA) | B23: ssp245 + COP
A24: AC adoption from warmer summers | B24: mcneil_gap_closure
A26: Geographies: | B26: US, DE, FR, IT, ES, UK, PL, CA, US_R_CALIFORNIA, US_R_ERCOT, US_R_PJM, US_R_WECC, US_R_SPP, US_R_MISO, US_R_SERC, US_R_NYISO, US_R_ISONE
A27: Years: | B27: 2024-2040
A29: Generated by Python Power Demand Model v1.0
A30: Cooling split out of buildings for US and Canada only; Europe unchanged vs v260707_v2.

Sheet Dashboard
A1: Dashboard
A2: Scenario: FEL 2026 | Base FEL | Base
A5: Geography | B5: 2024 | C5: 2025 | D5: 2026 | E5: 2027 | F5: 2028 | G5: 2029 | H5: 2030 | I5: 2031 | J5: 2032 | K5: 2033 | L5: 2034 | M5: 2035 | N5: 2036 | O5: 2037 | P5: 2038 | Q5: 2039 | R5: 2040
A6: EU28 | B6: =SUMIFS(_Data_Sectoral!$F$2:$F$20000,_Data_Sectoral!$A$2:$A$20000,"EU28",_Data_Sectoral!$D$2:$D$20000,"TOTAL",_Data_Sectoral!$E$2:$E$20000,2024) -> 2757.9599 | C6: =SUMIFS(_Data_Sectoral!$F$2:$F$20000,_Data_Sectoral!$A$2:$A$20000,"EU28",_Data_Sectoral!$D$2:$D$20000,"TOTAL",_Data_Sectoral!$E$2:$E$20000,2025) -> 2799.6018 | D6: =SUMIFS(_Data_Sectoral!$F$2:$F$20000,_Data_Sectoral!$A$2:$A$20000,"EU28",_Data_Sectoral!$D$2:$D$20000,"TOTAL",_Data_Sectoral!$E$2:$E$20000,2026) -> 2853.0276 | E6: =SUMIFS(_Data_Sectoral!$F$2:$F$20000,_Data_Sectoral!$A$2:$A$20000,"EU28",_Data_Sectoral!$D$2:$D$20000,"TOTAL",_Data_Sectoral!$E$2:$E$20000,2027) -> 2917.1644 | F6: =SUMIFS(_Data_Sectoral!$F$2:$F$20000,_Data_Sectoral!$A$2:$A$20000,"EU28",_Data_Sectoral!$D$2:$D$20000,"TOTAL",_Data_Sectoral!$E$2:$E$20000,2028) -> 2984.5584 | G6: =SUMIFS(_Data_Sectoral!$F$2:$F$20000,_Data_Sectoral!$A$2:$A$20000,"EU28",_Data_Sectoral!$D$2:$D$20000,"TOTAL",_Data_Sectoral!$E$2:$E$20000,2029) -> 3066.2688 | H6: =SUMIFS(_Data_Sectoral!$F$2:$F$20000,_Data_Sectoral!$A$2:$A$20000,"EU28",_Data_Sectoral!$D$2:$D$20000,"TOTAL",_Data_Sectoral!$E$2:$E$20000,2030) -> 3142.9569 | I6: =SUMIFS(_Data_Sectoral!$F$2:$F$20000,_Data_Sectoral!$A$2:$A$20000,"EU28",_Data_Sectoral!$D$2:$D$20000,"TOTAL",_Data_Sectoral!$E$2:$E$20000,2031) -> 3220.6043 | J6: =SUMIFS(_Data_Sectoral!$F$2:$F$20000,_Data_Sectoral!$A$2:$A$20000,"EU28",_Data_Sectoral!$D$2:$D$20000,"TOTAL",_Data_Sectoral!$E$2:$E$20000,2032) -> 3314.8918 | K6: =SUMIFS(_Data_Sectoral!$F$2:$F$20000,_Data_Sectoral!$A$2:$A$20000,"EU28",_Data_Sectoral!$D$2:$D$20000,"TOTAL",_Data_Sectoral!$E$2:$E$20000,2033) -> 3415.3326 | L6: =SUMIFS(_Data_Sectoral!$F$2:$F$20000,_Data_Sectoral!$A$2:$A$20000,"EU28",_Data_Sectoral!$D$2:$D$20000,"TOTAL",_Data_Sectoral!$E$2:$E$20000,2034) -> 3520.4642 | M6: =SUMIFS(_Data_Sectoral!$F$2:$F$20000,_Data_Sectoral!$A$2:$A$20000,"EU28",_Data_Sectoral!$D$2:$D$20000,"TOTAL",_Data_Sectoral!$E$2:$E$20000,2035) -> 3626.9258 | N6: =SUMIFS(_Data_Sectoral!$F$2:$F$20000,_Data_Sectoral!$A$2:$A$20000,"EU28",_Data_Sectoral!$D$2:$D$20000,"TOTAL",_Data_Sectoral!$E$2:$E$20000,2036) -> 3724.5284 | O6: =SUMIFS(_Data_Sectoral!$F$2:$F$20000,_Data_Sectoral!$A$2:$A$20000,"EU28",_Data_Sectoral!$D$2:$D$20000,"TOTAL",_Data_Sectoral!$E$2:$E$20000,2037) -> 3813.6523 | P6: =SUMIFS(_Data_Sectoral!$F$2:$F$20000,_Data_Sectoral!$A$2:$A$20000,"EU28",_Data_Sectoral!$D$2:$D$20000,"TOTAL",_Data_Sectoral!$E$2:$E$20000,2038) -> 3901.5097 | Q6: =SUMIFS(_Data_Sectoral!$F$2:$F$20000,_Data_Sectoral!$A$2:$A$20000,"EU28",_Data_Sectoral!$D$2:$D$20000,"TOTAL",_Data_Sectoral!$E$2:$E$20000,2039) -> 3987.5668 | R6: =SUMIFS(_Data_Sectoral!$F$2:$F$20000,_Data_Sectoral!$A$2:$A$20000,"EU28",_Data_Sectoral!$D$2:$D$20000,"TOTAL",_Data_Sectoral!$E$2:$E$20000,2040) -> 4069.837
A7: United States | B7: =SUMIFS(_Data_Sectoral!$F$2:$F$20000,_Data_Sectoral!$A$2:$A$20000,"US",_Data_Sectoral!$D$2:$D$20000,"TOTAL",_Data_Sectoral!$E$2:$E$20000,2024) -> 4155.0351 | C7: =SUMIFS(_Data_Sectoral!$F$2:$F$20000,_Data_Sectoral!$A$2:$A$20000,"US",_Data_Sectoral!$D$2:$D$20000,"TOTAL",_Data_Sectoral!$E$2:$E$20000,2025) -> 4209.9341 | D7: =SUMIFS(_Data_Sectoral!$F$2:$F$20000,_Data_Sectoral!$A$2:$A$20000,"US",_Data_Sectoral!$D$2:$D$20000,"TOTAL",_Data_Sectoral!$E$2:$E$20000,2026) -> 4300.1163 | E7: =SUMIFS(_Data_Sectoral!$F$2:$F$20000,_Data_Sectoral!$A$2:$A$20000,"US",_Data_Sectoral!$D$2:$D$20000,"TOTAL",_Data_Sectoral!$E$2:$E$20000,2027) -> 4466.5673 | F7: =SUMIFS(_Data_Sectoral!$F$2:$F$20000,_Data_Sectoral!$A$2:$A$20000,"US",_Data_Sectoral!$D$2:$D$20000,"TOTAL",_Data_Sectoral!$E$2:$E$20000,2028) -> 4661.3521 | G7: =SUMIFS(_Data_Sectoral!$F$2:$F$20000,_Data_Sectoral!$A$2:$A$20000,"US",_Data_Sectoral!$D$2:$D$20000,"TOTAL",_Data_Sectoral!$E$2:$E$20000,2029) -> 4874.7992 | H7: =SUMIFS(_Data_Sectoral!$F$2:$F$20000,_Data_Sectoral!$A$2:$A$20000,"US",_Data_Sectoral!$D$2:$D$20000,"TOTAL",_Data_Sectoral!$E$2:$E$20000,2030) -> 5112.4056 | I7: =SUMIFS(_Data_Sectoral!$F$2:$F$20000,_Data_Sectoral!$A$2:$A$20000,"US",_Data_Sectoral!$D$2:$D$20000,"TOTAL",_Data_Sectoral!$E$2:$E$20000,2031) -> 5392.5459 | J7: =SUMIFS(_Data_Sectoral!$F$2:$F$20000,_Data_Sectoral!$A$2:$A$20000,"US",_Data_Sectoral!$D$2:$D$20000,"TOTAL",_Data_Sectoral!$E$2:$E$20000,2032) -> 5684.3229 | K7: =SUMIFS(_Data_Sectoral!$F$2:$F$20000,_Data_Sectoral!$A$2:$A$20000,"US",_Data_Sectoral!$D$2:$D$20000,"TOTAL",_Data_Sectoral!$E$2:$E$20000,2033) -> 5941.2239 | L7: =SUMIFS(_Data_Sectoral!$F$2:$F$20000,_Data_Sectoral!$A$2:$A$20000,"US",_Data_Sectoral!$D$2:$D$20000,"TOTAL",_Data_Sectoral!$E$2:$E$20000,2034) -> 6219.8223 | M7: =SUMIFS(_Data_Sectoral!$F$2:$F$20000,_Data_Sectoral!$A$2:$A$20000,"US",_Data_Sectoral!$D$2:$D$20000,"TOTAL",_Data_Sectoral!$E$2:$E$20000,2035) -> 6483.1681 | N7: =SUMIFS(_Data_Sectoral!$F$2:$F$20000,_Data_Sectoral!$A$2:$A$20000,"US",_Data_Sectoral!$D$2:$D$20000,"TOTAL",_Data_Sectoral!$E$2:$E$20000,2036) -> 6743.1581 | O7: =SUMIFS(_Data_Sectoral!$F$2:$F$20000,_Data_Sectoral!$A$2:$A$20000,"US",_Data_Sectoral!$D$2:$D$20000,"TOTAL",_Data_Sectoral!$E$2:$E$20000,2037) -> 7007.522 | P7: =SUMIFS(_Data_Sectoral!$F$2:$F$20000,_Data_Sectoral!$A$2:$A$20000,"US",_Data_Sectoral!$D$2:$D$20000,"TOTAL",_Data_Sectoral!$E$2:$E$20000,2038) -> 7255.4984 | Q7: =SUMIFS(_Data_Sectoral!$F$2:$F$20000,_Data_Sectoral!$A$2:$A$20000,"US",_Data_Sectoral!$D$2:$D$20000,"TOTAL",_Data_Sectoral!$E$2:$E$20000,2039) -> 7500.2592 | R7: =SUMIFS(_Data_Sectoral!$F$2:$F$20000,_Data_Sectoral!$A$2:$A$20000,"US",_Data_Sectoral!$D$2:$D$20000,"TOTAL",_Data_Sectoral!$E$2:$E$20000,2040) -> 7719.4272
A9: All Modeled | B9: =SUM(B6:B7) -> 6912.995 | C9: =SUM(C6:C7) -> 7009.5359 | D9: =SUM(D6:D7) -> 7153.1439 | E9: =SUM(E6:E7) -> 7383.7316 | F9: =SUM(F6:F7) -> 7645.9105 | G9: =SUM(G6:G7) -> 7941.0679 | H9: =SUM(H6:H7) -> 8255.3625 | I9: =SUM(I6:I7) -> 8613.1502 | ... R9: =SUM(R6:R7) -> 11789.264
A12: Germany
A13: Sector | B13: 2024 | C13: 2025 | D13: 2026 | E13: 2027 | F13: 2028 | G13: 2029 | H13: 2030 | I13: 2031 | J13: 2032 | K13: 2033 | L13: 2034 | M13: 2035 | N13: 2036 | O13: 2037 | P13: 2038 | Q13: 2039 | R13: 2040
A14: Transport | B14: =SUMIFS(_Data_Sectoral!$F$2:$F$20000,_Data_Sectoral!$A$2:$A$20000,"DE",_Data_Sectoral!$C$2:$C$20000,"transport",_Data_Sectoral!$D$2:$D$20000,"TOTAL",_Data_Sectoral!$E$2:$E$20000,2024) -> 19.997696 | C14: =SUMIFS(_Data_Sectoral!$F$2:$F$20000,_Data_Sectoral!$A$2:$A$20000,"DE",_Data_Sectoral!$C$2:$C$20000,"transport",_Data_Sectoral!$D$2:$D$20000,"TOTAL",_Data_Sectoral!$E$2:$E$20000,2025) -> 21.931835 | D14: =SUMIFS(_Data_Sectoral!$F$2:$F$20000,_Data_Sectoral!$A$2:$A$20000,"DE",_Data_Sectoral!$C$2:$C$20000,"transport",_Data_Sectoral!$D$2:$D$20000,"TOTAL",_Data_Sectoral!$E$2:$E$20000,2026) -> 24.37738 | E14: =SUMIFS(_Data_Sectoral!$F$2:$F$20000,_Data_Sectoral!$A$2:$A$20000,"DE",_Data_Sectoral!$C$2:$C$20000,"transport",_Data_Sectoral!$D$2:$D$20000,"TOTAL",_Data_Sectoral!$E$2:$E$20000,2027) -> 27.716301 | F14: =SUMIFS(_Data_Sectoral!$F$2:$F$20000,_Data_Sectoral!$A$2:$A$20000,"DE",_Data_Sectoral!$C$2:$C$20000,"transport",_Data_Sectoral!$D$2:$D$20000,"TOTAL",_Data_Sectoral!$E$2:$E$20000,2028) -> 31.834037 | G14: =SUMIFS(_Data_Sectoral!$F$2:$F$20000,_Data_Sectoral!$A$2:$A$20000,"DE",_Data_Sectoral!$C$2:$C$20000,"transport",_Data_Sectoral!$D$2:$D$20000,"TOTAL",_Data_Sectoral!$E$2:$E$20000,2029) -> 36.865139 | H14: =SUMIFS(_Data_Sectoral!$F$2:$F$20000,_Data_Sectoral!$A$2:$A$20000,"DE",_Data_Sectoral!$C$2:$C$20000,"transport",_Data_Sectoral!$D$2:$D$20000,"TOTAL",_Data_Sectoral!$E$2:$E$20000,2030) -> 42.684968 | I14: =SUMIFS(_Data_Sectoral!$F$2:$F$20000,_Data_Sectoral!$A$2:$A$20000,"DE",_Data_Sectoral!$C$2:$C$20000,"transport",_Data_Sectoral!$D$2:$D$20000,"TOTAL",_Data_Sectoral!$E$2:$E$20000,2031) -> 48.93417 | J14: =SUMIFS(_Data_Sectoral!$F$2:$F$20000,_Data_Sectoral!$A$2:$A$20000,"DE",_Data_Sectoral!$C$2:$C$20000,"transport",_Data_Sectoral!$D$2:$D$20000,"TOTAL",_Data_Sectoral!$E$2:$E$20000,2032) -> 55.832518 | K14: =SUMIFS(_Data_Sectoral!$F$2:$F$20000,_Data_Sectoral!$A$2:$A$20000,"DE",_Data_Sectoral!$C$2:$C$20000,"transport",_Data_Sectoral!$D$2:$D$20000,"TOTAL",_Data_Sectoral!$E$2:$E$20000,2033) -> 63.240901 | L14: =SUMIFS(_Data_Sectoral!$F$2:$F$20000,_Data_Sectoral!$A$2:$A$20000,"DE",_Data_Sectoral!$C$2:$C$20000,"transport",_Data_Sectoral!$D$2:$D$20000,"TOTAL",_Data_Sectoral!$E$2:$E$20000,2034) -> 70.531404 | M14: =SUMIFS(_Data_Sectoral!$F$2:$F$20000,_Data_Sectoral!$A$2:$A$20000,"DE",_Data_Sectoral!$C$2:$C$20000,"transport",_Data_Sectoral!$D$2:$D$20000,"TOTAL",_Data_Sectoral!$E$2:$E$20000,2035) -> 77.872913 | N14: =SUMIFS(_Data_Sectoral!$F$2:$F$20000,_Data_Sectoral!$A$2:$A$20000,"DE",_Data_Sectoral!$C$2:$C$20000,"transport",_Data_Sectoral!$D$2:$D$20000,"TOTAL",_Data_Sectoral!$E$2:$E$20000,2036) -> 85.067542 | O14: =SUMIFS(_Data_Sectoral!$F$2:$F$20000,_Data_Sectoral!$A$2:$A$20000,"DE",_Data_Sectoral!$C$2:$C$20000,"transport",_Data_Sectoral!$D$2:$D$20000,"TOTAL",_Data_Sectoral!$E$2:$E$20000,2037) -> 91.891028 | P14: =SUMIFS(_Data_Sectoral!$F$2:$F$20000,_Data_Sectoral!$A$2:$A$20000,"DE",_Data_Sectoral!$C$2:$C$20000,"transport",_Data_Sectoral!$D$2:$D$20000,"TOTAL",_Data_Sectoral!$E$2:$E$20000,2038) -> 98.584437 | Q14: =SUMIFS(_Data_Sectoral!$F$2:$F$20000,_Data_Sectoral!$A$2:$A$20000,"DE",_Data_Sectoral!$C$2:$C$20000,"transport",_Data_Sectoral!$D$2:$D$20000,"TOTAL",_Data_Sectoral!$E$2:$E$20000,2039) -> 105.42056 | R14: =SUMIFS(_Data_Sectoral!$F$2:$F$20000,_Data_Sectoral!$A$2:$A$20000,"DE",_Data_Sectoral!$C$2:$C$20000,"transport",_Data_Sectoral!$D$2:$D$20000,"TOTAL",_Data_Sectoral!$E$2:$E$20000,2040) -> 110.96325
A15: Buildings | B15: =SUMIFS(_Data_Sectoral!$F$2:$F$20000,_Data_Sectoral!$A$2:$A$20000,"DE",_Data_Sectoral!$C$2:$C$20000,"buildings",_Data_Sectoral!$D$2:$D$20000,"TOTAL",_Data_Sectoral!$E$2:$E$20000,2024) -> 253.28661 | C15: =SUMIFS(_Data_Sectoral!$F$2:$F$20000,_Data_Sectoral!$A$2:$A$20000,"DE",_Data_Sectoral!$C$2:$C$20000,"buildings",_Data_Sectoral!$D$2:$D$20000,"TOTAL",_Data_Sectoral!$E$2:$E$20000,2025) -> 254.89252 | D15: =SUMIFS(_Data_Sectoral!$F$2:$F$20000,_Data_Sectoral!$A$2:$A$20000,"DE",_Data_Sectoral!$C$2:$C$20000,"buildings",_Data_Sectoral!$D$2:$D$20000,"TOTAL",_Data_Sectoral!$E$2:$E$20000,2026) -> 256.72996 | E15: =SUMIFS(_Data_Sectoral!$F$2:$F$20000,_Data_Sectoral!$A$2:$A$20000,"DE",_Data_Sectoral!$C$2:$C$20000,"buildings",_Data_Sectoral!$D$2:$D$20000,"TOTAL",_Data_Sectoral!$E$2:$E$20000,2027) -> 258.35599 | F15: =SUMIFS(_Data_Sectoral!$F$2:$F$20000,_Data_Sectoral!$A$2:$A$20000,"DE",_Data_Sectoral!$C$2:$C$20000,"buildings",_Data_Sectoral!$D$2:$D$20000,"TOTAL",_Data_Sectoral!$E$2:$E$20000,2028) -> 260.13162 | G15: =SUMIFS(_Data_Sectoral!$F$2:$F$20000,_Data_Sectoral!$A$2:$A$20000,"DE",_Data_Sectoral!$C$2:$C$20000,"buildings",_Data_Sectoral!$D$2:$D$20000,"TOTAL",_Data_Sectoral!$E$2:$E$20000,2029) -> 261.96654 | H15: =SUMIFS(_Data_Sectoral!$F$2:$F$20000,_Data_Sectoral!$A$2:$A$20000,"DE",_Data_Sectoral!$C$2:$C$20000,"buildings",_Data_Sectoral!$D$2:$D$20000,"TOTAL",_Data_Sectoral!$E$2:$E$20000,2030) -> 267.74692 | I15: =SUMIFS(_Data_Sectoral!$F$2:$F$20000,_Data_Sectoral!$A$2:$A$20000,"DE",_Data_Sectoral!$C$2:$C$20000,"buildings",_Data_Sectoral!$D$2:$D$20000,"TOTAL",_Data_Sectoral!$E$2:$E$20000,2031) -> 270.50928 | J15: =SUMIFS(_Data_Sectoral!$F$2:$F$20000,_Data_Sectoral!$A$2:$A$20000,"DE",_Data_Sectoral!$C$2:$C$20000,"buildings",_Data_Sectoral!$D$2:$D$20000,"TOTAL",_Data_Sectoral!$E$2:$E$20000,2032) -> 272.71494 | K15: =SUMIFS(_Data_Sectoral!$F$2:$F$20000,_Data_Sectoral!$A$2:$A$20000,"DE",_Data_Sectoral!$C$2:$C$20000,"buildings",_Data_Sectoral!$D$2:$D$20000,"TOTAL",_Data_Sectoral!$E$2:$E$20000,2033) -> 275.54347 | L15: =SUMIFS(_Data_Sectoral!$F$2:$F$20000,_Data_Sectoral!$A$2:$A$20000,"DE",_Data_Sectoral!$C$2:$C$20000,"buildings",_Data_Sectoral!$D$2:$D$20000,"TOTAL",_Data_Sectoral!$E$2:$E$20000,2034) -> 278.72443 | M15: =SUMIFS(_Data_Sectoral!$F$2:$F$20000,_Data_Sectoral!$A$2:$A$20000,"DE",_Data_Sectoral!$C$2:$C$20000,"buildings",_Data_Sectoral!$D$2:$D$20000,"TOTAL",_Data_Sectoral!$E$2:$E$20000,2035) -> 282.26729 | N15: =SUMIFS(_Data_Sectoral!$F$2:$F$20000,_Data_Sectoral!$A$2:$A$20000,"DE",_Data_Sectoral!$C$2:$C$20000,"buildings",_Data_Sectoral!$D$2:$D$20000,"TOTAL",_Data_Sectoral!$E$2:$E$20000,2036) -> 284.98655 | O15: =SUMIFS(_Data_Sectoral!$F$2:$F$20000,_Data_Sectoral!$A$2:$A$20000,"DE",_Data_Sectoral!$C$2:$C$20000,"buildings",_Data_Sectoral!$D$2:$D$20000,"TOTAL",_Data_Sectoral!$E$2:$E$20000,2037) -> 287.55782 | P15: =SUMIFS(_Data_Sectoral!$F$2:$F$20000,_Data_Sectoral!$A$2:$A$20000,"DE",_Data_Sectoral!$C$2:$C$20000,"buildings",_Data_Sectoral!$D$2:$D$20000,"TOTAL",_Data_Sectoral!$E$2:$E$20000,2038) -> 290.17914 | Q15: =SUMIFS(_Data_Sectoral!$F$2:$F$20000,_Data_Sectoral!$A$2:$A$20000,"DE",_Data_Sectoral!$C$2:$C$20000,"buildings",_Data_Sectoral!$D$2:$D$20000,"TOTAL",_Data_Sectoral!$E$2:$E$20000,2039) -> 291.86426 | R15: =SUMIFS(_Data_Sectoral!$F$2:$F$20000,_Data_Sectoral!$A$2:$A$20000,"DE",_Data_Sectoral!$C$2:$C$20000,"buildings",_Data_Sectoral!$D$2:$D$20000,"TOTAL",_Data_Sectoral!$E$2:$E$20000,2040) -> 293.54326
A16: Industry | B16: =SUMIFS(_Data_Sectoral!$F$2:$F$20000,_Data_Sectoral!$A$2:$A$20000,"DE",_Data_Sectoral!$C$2:$C$20000,"industry",_Data_Sectoral!$D$2:$D$20000,"TOTAL",_Data_Sectoral!$E$2:$E$20000,2024) -> 181.89842 | C16: =SUMIFS(_Data_Sectoral!$F$2:$F$20000,_Data_Sectoral!$A$2:$A$20000,"DE",_Data_Sectoral!$C$2:$C$20000,"industry",_Data_Sectoral!$D$2:$D$20000,"TOTAL",_Data_Sectoral!$E$2:$E$20000,2025) -> 183.47596 | D16: =SUMIFS(_Data_Sectoral!$F$2:$F$20000,_Data_Sectoral!$A$2:$A$20000,"DE",_Data_Sectoral!$C$2:$C$20000,"industry",_Data_Sectoral!$D$2:$D$20000,"TOTAL",_Data_Sectoral!$E$2:$E$20000,2026) -> 185.22682 | E16: =SUMIFS(_Data_Sectoral!$F$2:$F$20000,_Data_Sectoral!$A$2:$A$20000,"DE",_Data_Sectoral!$C$2:$C$20000,"industry",_Data_Sectoral!$D$2:$D$20000,"TOTAL",_Data_Sectoral!$E$2:$E$20000,2027) -> 189.37152 | F16: =SUMIFS(_Data_Sectoral!$F$2:$F$20000,_Data_Sectoral!$A$2:$A$20000,"DE",_Data_Sectoral!$C$2:$C$20000,"industry",_Data_Sectoral!$D$2:$D$20000,"TOTAL",_Data_Sectoral!$E$2:$E$20000,2028) -> 192.01958 | G16: =SUMIFS(_Data_Sectoral!$F$2:$F$20000,_Data_Sectoral!$A$2:$A$20000,"DE",_Data_Sectoral!$C$2:$C$20000,"industry",_Data_Sectoral!$D$2:$D$20000,"TOTAL",_Data_Sectoral!$E$2:$E$20000,2029) -> 195.35985 | H16: =SUMIFS(_Data_Sectoral!$F$2:$F$20000,_Data_Sectoral!$A$2:$A$20000,"DE",_Data_Sectoral!$C$2:$C$20000,"industry",_Data_Sectoral!$D$2:$D$20000,"TOTAL",_Data_Sectoral!$E$2:$E$20000,2030) -> 198.88547 | I16: =SUMIFS(_Data_Sectoral!$F$2:$F$20000,_Data_Sectoral!$A$2:$A$20000,"DE",_Data_Sectoral!$C$2:$C$20000,"industry",_Data_Sectoral!$D$2:$D$20000,"TOTAL",_Data_Sectoral!$E$2:$E$20000,2031) -> 203.52721 | J16: =SUMIFS(_Data_Sectoral!$F$2:$F$20000,_Data_Sectoral!$A$2:$A$20000,"DE",_Data_Sectoral!$C$2:$C$20000,"industry",_Data_Sectoral!$D$2:$D$20000,"TOTAL",_Data_Sectoral!$E$2:$E$20000,2032) -> 208.68291 | K16: =SUMIFS(_Data_Sectoral!$F$2:$F$20000,_Data_Sectoral!$A$2:$A$20000,"DE",_Data_Sectoral!$C$2:$C$20000,"industry",_Data_Sectoral!$D$2:$D$20000,"TOTAL",_Data_Sectoral!$E$2:$E$20000,2033) -> 213.63744 | L16: =SUMIFS(_Data_Sectoral!$F$2:$F$20000,_Data_Sectoral!$A$2:$A$20000,"DE",_Data_Sectoral!$C$2:$C$20000,"industry",_Data_Sectoral!$D$2:$D$20000,"TOTAL",_Data_Sectoral!$E$2:$E$20000,2034) -> 218.7088 | M16: =SUMIFS(_Data_Sectoral!$F$2:$F$20000,_Data_Sectoral!$A$2:$A$20000,"DE",_Data_Sectoral!$C$2:$C$20000,"industry",_Data_Sectoral!$D$2:$D$20000,"TOTAL",_Data_Sectoral!$E$2:$E$20000,2035) -> 223.93116 | N16: =SUMIFS(_Data_Sectoral!$F$2:$F$20000,_Data_Sectoral!$A$2:$A$20000,"DE",_Data_Sectoral!$C$2:$C$20000,"industry",_Data_Sectoral!$D$2:$D$20000,"TOTAL",_Data_Sectoral!$E$2:$E$20000,2036) -> 225.73092 | O16: =SUMIFS(_Data_Sectoral!$F$2:$F$20000,_Data_Sectoral!$A$2:$A$20000,"DE",_Data_Sectoral!$C$2:$C$20000,"industry",_Data_Sectoral!$D$2:$D$20000,"TOTAL",_Data_Sectoral!$E$2:$E$20000,2037) -> 227.52973 | P16: =SUMIFS(_Data_Sectoral!$F$2:$F$20000,_Data_Sectoral!$A$2:$A$20000,"DE",_Data_Sectoral!$C$2:$C$20000,"industry",_Data_Sectoral!$D$2:$D$20000,"TOTAL",_Data_Sectoral!$E$2:$E$20000,2038) -> 229.19499 | Q16: =SUMIFS(_Data_Sectoral!$F$2:$F$20000,_Data_Sectoral!$A$2:$A$20000,"DE",_Data_Sectoral!$C$2:$C$20000,"industry",_Data_Sectoral!$D$2:$D$20000,"TOTAL",_Data_Sectoral!$E$2:$E$20000,2039) -> 231.26294 | R16: =SUMIFS(_Data_Sectoral!$F$2:$F$20000,_Data_Sectoral!$A$2:$A$20000,"DE",_Data_Sectoral!$C$2:$C$20000,"industry",_Data_Sectoral!$D$2:$D$20000,"TOTAL",_Data_Sectoral!$E$2:$E$20000,2040) -> 232.33639
A17: Data Centers | B17: =SUMIFS(_Data_Sectoral!$F$2:$F$20000,_Data_Sectoral!$A$2:$A$20000,"DE",_Data_Sectoral!$C$2:$C$20000,"data_centers",_Data_Sectoral!$D$2:$D$20000,"TOTAL",_Data_Sectoral!$E$2:$E$20000,2024) -> 19.99887 | C17: =SUMIFS(_Data_Sectoral!$F$2:$F$20000,_Data_Sectoral!$A$2:$A$20000,"DE",_Data_Sectoral!$C$2:$C$20000,"data_centers",_Data_Sectoral!$D$2:$D$20000,"TOTAL",_Data_Sectoral!$E$2:$E$20000,2025) -> 21.295244 | D17: =SUMIFS(_Data_Sectoral!$F$2:$F$20000,_Data_Sectoral!$A$2:$A$20000,"DE",_Data_Sectoral!$C$2:$C$20000,"data_centers",_Data_Sectoral!$D$2:$D$20000,"TOTAL",_Data_Sectoral!$E$2:$E$20000,2026) -> 24.136782 | E17: =SUMIFS(_Data_Sectoral!$F$2:$F$20000,_Data_Sectoral!$A$2:$A$20000,"DE",_Data_Sectoral!$C$2:$C$20000,"data_centers",_Data_Sectoral!$D$2:$D$20000,"TOTAL",_Data_Sectoral!$E$2:$E$20000,2027) -> 27.201716 | F17: =SUMIFS(_Data_Sectoral!$F$2:$F$20000,_Data_Sectoral!$A$2:$A$20000,"DE",_Data_Sectoral!$C$2:$C$20000,"data_centers",_Data_Sectoral!$D$2:$D$20000,"TOTAL",_Data_Sectoral!$E$2:$E$20000,2028) -> 30.64595 | G17: =SUMIFS(_Data_Sectoral!$F$2:$F$20000,_Data_Sectoral!$A$2:$A$20000,"DE",_Data_Sectoral!$C$2:$C$20000,"data_centers",_Data_Sectoral!$D$2:$D$20000,"TOTAL",_Data_Sectoral!$E$2:$E$20000,2029) -> 33.833232 | H17: =SUMIFS(_Data_Sectoral!$F$2:$F$20000,_Data_Sectoral!$A$2:$A$20000,"DE",_Data_Sectoral!$C$2:$C$20000,"data_centers",_Data_Sectoral!$D$2:$D$20000,"TOTAL",_Data_Sectoral!$E$2:$E$20000,2030) -> 36.20331 | I17: =SUMIFS(_Data_Sectoral!$F$2:$F$20000,_Data_Sectoral!$A$2:$A$20000,"DE",_Data_Sectoral!$C$2:$C$20000,"data_centers",_Data_Sectoral!$D$2:$D$20000,"TOTAL",_Data_Sectoral!$E$2:$E$20000,2031) -> 38.589344 | J17: =SUMIFS(_Data_Sectoral!$F$2:$F$20000,_Data_Sectoral!$A$2:$A$20000,"DE",_Data_Sectoral!$C$2:$C$20000,"data_centers",_Data_Sectoral!$D$2:$D$20000,"TOTAL",_Data_Sectoral!$E$2:$E$20000,2032) -> 42.202804 | K17: =SUMIFS(_Data_Sectoral!$F$2:$F$20000,_Data_Sectoral!$A$2:$A$20000,"DE",_Data_Sectoral!$C$2:$C$20000,"data_centers",_Data_Sectoral!$D$2:$D$20000,"TOTAL",_Data_Sectoral!$E$2:$E$20000,2033) -> 45.802842 | L17: =SUMIFS(_Data_Sectoral!$F$2:$F$20000,_Data_Sectoral!$A$2:$A$20000,"DE",_Data_Sectoral!$C$2:$C$20000,"data_centers",_Data_Sectoral!$D$2:$D$20000,"TOTAL",_Data_Sectoral!$E$2:$E$20000,2034) -> 49.294674 | M17: =SUMIFS(_Data_Sectoral!$F$2:$F$20000,_Data_Sectoral!$A$2:$A$20000,"DE",_Data_Sectoral!$C$2:$C$20000,"data_centers",_Data_Sectoral!$D$2:$D$20000,"TOTAL",_Data_Sectoral!$E$2:$E$20000,2035) -> 52.576489 | N17: =SUMIFS(_Data_Sectoral!$F$2:$F$20000,_Data_Sectoral!$A$2:$A$20000,"DE",_Data_Sectoral!$C$2:$C$20000,"data_centers",_Data_Sectoral!$D$2:$D$20000,"TOTAL",_Data_Sectoral!$E$2:$E$20000,2036) -> 55.543886 | O17: =SUMIFS(_Data_Sectoral!$F$2:$F$20000,_Data_Sectoral!$A$2:$A$20000,"DE",_Data_Sectoral!$C$2:$C$20000,"data_centers",_Data_Sectoral!$D$2:$D$20000,"TOTAL",_Data_Sectoral!$E$2:$E$20000,2037) -> 58.095007 | P17: =SUMIFS(_Data_Sectoral!$F$2:$F$20000,_Data_Sectoral!$A$2:$A$20000,"DE",_Data_Sectoral!$C$2:$C$20000,"data_centers",_Data_Sectoral!$D$2:$D$20000,"TOTAL",_Data_Sectoral!$E$2:$E$20000,2038) -> 60.136045 | Q17: =SUMIFS(_Data_Sectoral!$F$2:$F$20000,_Data_Sectoral!$A$2:$A$20000,"DE",_Data_Sectoral!$C$2:$C$20000,"data_centers",_Data_Sectoral!$D$2:$D$20000,"TOTAL",_Data_Sectoral!$E$2:$E$20000,2039) -> 61.586742 | R17: =SUMIFS(_Data_Sectoral!$F$2:$F$20000,_Data_Sectoral!$A$2:$A$20000,"DE",_Data_Sectoral!$C$2:$C$20000,"data_centers",_Data_Sectoral!$D$2:$D$20000,"TOTAL",_Data_Sectoral!$E$2:$E$20000,2040) -> 62.385448
A18: Hydrogen | B18: =SUMIFS(_Data_Sectoral!$F$2:$F$20000,_Data_Sectoral!$A$2:$A$20000,"DE",_Data_Sectoral!$C$2:$C$20000,"hydrogen",_Data_Sectoral!$D$2:$D$20000,"TOTAL",_Data_Sectoral!$E$2:$E$20000,2024) -> 0.33 | C18: =SUMIFS(_Data_Sectoral!$F$2:$F$20000,_Data_Sectoral!$A$2:$A$20000,"DE",_Data_Sectoral!$C$2:$C$20000,"hydrogen",_Data_Sectoral!$D$2:$D$20000,"TOTAL",_Data_Sectoral!$E$2:$E$20000,2025) -> 0.51 | D18: =SUMIFS(_Data_Sectoral!$F$2:$F$20000,_Data_Sectoral!$A$2:$A$20000,"DE",_Data_Sectoral!$C$2:$C$20000,"hydrogen",_Data_Sectoral!$D$2:$D$20000,"TOTAL",_Data_Sectoral!$E$2:$E$20000,2026) -> 3.435668 | E18: =SUMIFS(_Data_Sectoral!$F$2:$F$20000,_Data_Sectoral!$A$2:$A$20000,"DE",_Data_Sectoral!$C$2:$C$20000,"hydrogen",_Data_Sectoral!$D$2:$D$20000,"TOTAL",_Data_Sectoral!$E$2:$E$20000,2027) -> 6.361337 | F18: =SUMIFS(_Data_Sectoral!$F$2:$F$20000,_Data_Sectoral!$A$2:$A$20000,"DE",_Data_Sectoral!$C$2:$C$20000,"hydrogen",_Data_Sectoral!$D$2:$D$20000,"TOTAL",_Data_Sectoral!$E$2:$E$20000,2028) -> 6.996787 | G18: =SUMIFS(_Data_Sectoral!$F$2:$F$20000,_Data_Sectoral!$A$2:$A$20000,"DE",_Data_Sectoral!$C$2:$C$20000,"hydrogen",_Data_Sectoral!$D$2:$D$20000,"TOTAL",_Data_Sectoral!$E$2:$E$20000,2029) -> 7.447752 | H18: =SUMIFS(_Data_Sectoral!$F$2:$F$20000,_Data_Sectoral!$A$2:$A$20000,"DE",_Data_Sectoral!$C$2:$C$20000,"hydrogen",_Data_Sectoral!$D$2:$D$20000,"TOTAL",_Data_Sectoral!$E$2:$E$20000,2030) -> 5.7159 | I18: =SUMIFS(_Data_Sectoral!$F$2:$F$20000,_Data_Sectoral!$A$2:$A$20000,"DE",_Data_Sectoral!$C$2:$C$20000,"hydrogen",_Data_Sectoral!$D$2:$D$20000,"TOTAL",_Data_Sectoral!$E$2:$E$20000,2031) -> 6.606004 | J18: =SUMIFS(_Data_Sectoral!$F$2:$F$20000,_Data_Sectoral!$A$2:$A$20000,"DE",_Data_Sectoral!$C$2:$C$20000,"hydrogen",_Data_Sectoral!$D$2:$D$20000,"TOTAL",_Data_Sectoral!$E$2:$E$20000,2032) -> 7.549718 | K18: =SUMIFS(_Data_Sectoral!$F$2:$F$20000,_Data_Sectoral!$A$2:$A$20000,"DE",_Data_Sectoral!$C$2:$C$20000,"hydrogen",_Data_Sectoral!$D$2:$D$20000,"TOTAL",_Data_Sectoral!$E$2:$E$20000,2033) -> 8.596714 | L18: =SUMIFS(_Data_Sectoral!$F$2:$F$20000,_Data_Sectoral!$A$2:$A$20000,"DE",_Data_Sectoral!$C$2:$C$20000,"hydrogen",_Data_Sectoral!$D$2:$D$20000,"TOTAL",_Data_Sectoral!$E$2:$E$20000,2034) -> 9.628729 | M18: =SUMIFS(_Data_Sectoral!$F$2:$F$20000,_Data_Sectoral!$A$2:$A$20000,"DE",_Data_Sectoral!$C$2:$C$20000,"hydrogen",_Data_Sectoral!$D$2:$D$20000,"TOTAL",_Data_Sectoral!$E$2:$E$20000,2035) -> 10.6434 | N18: =SUMIFS(_Data_Sectoral!$F$2:$F$20000,_Data_Sectoral!$A$2:$A$20000,"DE",_Data_Sectoral!$C$2:$C$20000,"hydrogen",_Data_Sectoral!$D$2:$D$20000,"TOTAL",_Data_Sectoral!$E$2:$E$20000,2036) -> 11.638361 | O18: =SUMIFS(_Data_Sectoral!$F$2:$F$20000,_Data_Sectoral!$A$2:$A$20000,"DE",_Data_Sectoral!$C$2:$C$20000,"hydrogen",_Data_Sectoral!$D$2:$D$20000,"TOTAL",_Data_Sectoral!$E$2:$E$20000,2037) -> 12.260934 | P18: =SUMIFS(_Data_Sectoral!$F$2:$F$20000,_Data_Sectoral!$A$2:$A$20000,"DE",_Data_Sectoral!$C$2:$C$20000,"hydrogen",_Data_Sectoral!$D$2:$D$20000,"TOTAL",_Data_Sectoral!$E$2:$E$20000,2038) -> 12.864323 | Q18: =SUMIFS(_Data_Sectoral!$F$2:$F$20000,_Data_Sectoral!$A$2:$A$20000,"DE",_Data_Sectoral!$C$2:$C$20000,"hydrogen",_Data_Sectoral!$D$2:$D$20000,"TOTAL",_Data_Sectoral!$E$2:$E$20000,2039) -> 13.44695 | R18: =SUMIFS(_Data_Sectoral!$F$2:$F$20000,_Data_Sectoral!$A$2:$A$20000,"DE",_Data_Sectoral!$C$2:$C$20000,"hydrogen",_Data_Sectoral!$D$2:$D$20000,"TOTAL",_Data_Sectoral!$E$2:$E$20000,2040) -> 13.6656
A19: Total | B19: =SUM(B14:B18) -> 475.51159 | C19: =SUM(C14:C18) -> 482.10556 | D19: =SUM(D14:D18) -> 493.90662 | E19: =SUM(E14:E18) -> 509.00687 | F19: =SUM(F14:F18) -> 521.62797 | G19: =SUM(G14:G18) -> 535.47251 | H19: =SUM(H14:H18) -> 551.23656 | I19: =SUM(I14:I18) -> 568.166 | ... R19: =SUM(R14:R18) -> 712.89394
A21: France
A22: Sector | B22: 2024 | C22: 2025 | D22: 2026 | E22: 2027 | F22: 2028 | G22: 2029 | H22: 2030 | I22: 2031 | J22: 2032 | K22: 2033 | L22: 2034 | M22: 2035 | N22: 2036 | O22: 2037 | P22: 2038 | Q22: 2039 | R22: 2040
A23: Transport | B23: =SUMIFS(_Data_Sectoral!$F$2:$F$20000,_Data_Sectoral!$A$2:$A$20000,"FR",_Data_Sectoral!$C$2:$C$20000,"transport",_Data_Sectoral!$D$2:$D$20000,"TOTAL",_Data_Sectoral!$E$2:$E$20000,2024) -> 12.17534 | C23: =SUMIFS(_Data_Sectoral!$F$2:$F$20000,_Data_Sectoral!$A$2:$A$20000,"FR",_Data_Sectoral!$C$2:$C$20000,"transport",_Data_Sectoral!$D$2:$D$20000,"TOTAL",_Data_Sectoral!$E$2:$E$20000,2025) -> 13.473119 | D23: =SUMIFS(_Data_Sectoral!$F$2:$F$20000,_Data_Sectoral!$A$2:$A$20000,"FR",_Data_Sectoral!$C$2:$C$20000,"transport",_Data_Sectoral!$D$2:$D$20000,"TOTAL",_Data_Sectoral!$E$2:$E$20000,2026) -> 15.060602 | E23: =SUMIFS(_Data_Sectoral!$F$2:$F$20000,_Data_Sectoral!$A$2:$A$20000,"FR",_Data_Sectoral!$C$2:$C$20000,"transport",_Data_Sectoral!$D$2:$D$20000,"TOTAL",_Data_Sectoral!$E$2:$E$20000,2027) -> 17.153697 | F23: =SUMIFS(_Data_Sectoral!$F$2:$F$20000,_Data_Sectoral!$A$2:$A$20000,"FR",_Data_Sectoral!$C$2:$C$20000,"transport",_Data_Sectoral!$D$2:$D$20000,"TOTAL",_Data_Sectoral!$E$2:$E$20000,2028) -> 19.948087 | G23: =SUMIFS(_Data_Sectoral!$F$2:$F$20000,_Data_Sectoral!$A$2:$A$20000,"FR",_Data_Sectoral!$C$2:$C$20000,"transport",_Data_Sectoral!$D$2:$D$20000,"TOTAL",_Data_Sectoral!$E$2:$E$20000,2029) -> 23.295812 | H23: =SUMIFS(_Data_Sectoral!$F$2:$F$20000,_Data_Sectoral!$A$2:$A$20000,"FR",_Data_Sectoral!$C$2:$C$20000,"transport",_Data_Sectoral!$D$2:$D$20000,"TOTAL",_Data_Sectoral!$E$2:$E$20000,2030) -> 27.051031 | I23: =SUMIFS(_Data_Sectoral!$F$2:$F$20000,_Data_Sectoral!$A$2:$A$20000,"FR",_Data_Sectoral!$C$2:$C$20000,"transport",_Data_Sectoral!$D$2:$D$20000,"TOTAL",_Data_Sectoral!$E$2:$E$20000,2031) -> 30.959984 | J23: =SUMIFS(_Data_Sectoral!$F$2:$F$20000,_Data_Sectoral!$A$2:$A$20000,"FR",_Data_Sectoral!$C$2:$C$20000,"transport",_Data_Sectoral!$D$2:$D$20000,"TOTAL",_Data_Sectoral!$E$2:$E$20000,2032) -> 35.155382 | K23: =SUMIFS(_Data_Sectoral!$F$2:$F$20000,_Data_Sectoral!$A$2:$A$20000,"FR",_Data_Sectoral!$C$2:$C$20000,"transport",_Data_Sectoral!$D$2:$D$20000,"TOTAL",_Data_Sectoral!$E$2:$E$20000,2033) -> 39.526301 | L23: =SUMIFS(_Data_Sectoral!$F$2:$F$20000,_Data_Sectoral!$A$2:$A$20000,"FR",_Data_Sectoral!$C$2:$C$20000,"transport",_Data_Sectoral!$D$2:$D$20000,"TOTAL",_Data_Sectoral!$E$2:$E$20000,2034) -> 44.018019 | M23: =SUMIFS(_Data_Sectoral!$F$2:$F$20000,_Data_Sectoral!$A$2:$A$20000,"FR",_Data_Sectoral!$C$2:$C$20000,"transport",_Data_Sectoral!$D$2:$D$20000,"TOTAL",_Data_Sectoral!$E$2:$E$20000,2035) -> 48.645395 | N23: =SUMIFS(_Data_Sectoral!$F$2:$F$20000,_Data_Sectoral!$A$2:$A$20000,"FR",_Data_Sectoral!$C$2:$C$20000,"transport",_Data_Sectoral!$D$2:$D$20000,"TOTAL",_Data_Sectoral!$E$2:$E$20000,2036) -> 53.188091 | O23: =SUMIFS(_Data_Sectoral!$F$2:$F$20000,_Data_Sectoral!$A$2:$A$20000,"FR",_Data_Sectoral!$C$2:$C$20000,"transport",_Data_Sectoral!$D$2:$D$20000,"TOTAL",_Data_Sectoral!$E$2:$E$20000,2037) -> 57.642584 | P23: =SUMIFS(_Data_Sectoral!$F$2:$F$20000,_Data_Sectoral!$A$2:$A$20000,"FR",_Data_Sectoral!$C$2:$C$20000,"transport",_Data_Sectoral!$D$2:$D$20000,"TOTAL",_Data_Sectoral!$E$2:$E$20000,2038) -> 62.097551 | Q23: =SUMIFS(_Data_Sectoral!$F$2:$F$20000,_Data_Sectoral!$A$2:$A$20000,"FR",_Data_Sectoral!$C$2:$C$20000,"transport",_Data_Sectoral!$D$2:$D$20000,"TOTAL",_Data_Sectoral!$E$2:$E$20000,2039) -> 66.080216 | R23: =SUMIFS(_Data_Sectoral!$F$2:$F$20000,_Data_Sectoral!$A$2:$A$20000,"FR",_Data_Sectoral!$C$2:$C$20000,"transport",_Data_Sectoral!$D$2:$D$20000,"TOTAL",_Data_Sectoral!$E$2:$E$20000,2040) -> 70.772028
A24: Buildings | B24: =SUMIFS(_Data_Sectoral!$F$2:$F$20000,_Data_Sectoral!$A$2:$A$20000,"FR",_Data_Sectoral!$C$2:$C$20000,"buildings",_Data_Sectoral!$D$2:$D$20000,"TOTAL",_Data_Sectoral!$E$2:$E$20000,2024) -> 276.97627 | C24: =SUMIFS(_Data_Sectoral!$F$2:$F$20000,_Data_Sectoral!$A$2:$A$20000,"FR",_Data_Sectoral!$C$2:$C$20000,"buildings",_Data_Sectoral!$D$2:$D$20000,"TOTAL",_Data_Sectoral!$E$2:$E$20000,2025) -> 280.70993 | D24: =SUMIFS(_Data_Sectoral!$F$2:$F$20000,_Data_Sectoral!$A$2:$A$20000,"FR",_Data_Sectoral!$C$2:$C$20000,"buildings",_Data_Sectoral!$D$2:$D$20000,"TOTAL",_Data_Sectoral!$E$2:$E$20000,2026) -> 284.22413 | E24: =SUMIFS(_Data_Sectoral!$F$2:$F$20000,_Data_Sectoral!$A$2:$A$20000,"FR",_Data_Sectoral!$C$2:$C$20000,"buildings",_Data_Sectoral!$D$2:$D$20000,"TOTAL",_Data_Sectoral!$E$2:$E$20000,2027) -> 287.8078 | F24: =SUMIFS(_Data_Sectoral!$F$2:$F$20000,_Data_Sectoral!$A$2:$A$20000,"FR",_Data_Sectoral!$C$2:$C$20000,"buildings",_Data_Sectoral!$D$2:$D$20000,"TOTAL",_Data_Sectoral!$E$2:$E$20000,2028) -> 292.35488 | G24: =SUMIFS(_Data_Sectoral!$F$2:$F$20000,_Data_Sectoral!$A$2:$A$20000,"FR",_Data_Sectoral!$C$2:$C$20000,"buildings",_Data_Sectoral!$D$2:$D$20000,"TOTAL",_Data_Sectoral!$E$2:$E$20000,2029) -> 297.41695 | H24: =SUMIFS(_Data_Sectoral!$F$2:$F$20000,_Data_Sectoral!$A$2:$A$20000,"FR",_Data_Sectoral!$C$2:$C$20000,"buildings",_Data_Sectoral!$D$2:$D$20000,"TOTAL",_Data_Sectoral!$E$2:$E$20000,2030) -> 303.02508 | I24: =SUMIFS(_Data_Sectoral!$F$2:$F$20000,_Data_Sectoral!$A$2:$A$20000,"FR",_Data_Sectoral!$C$2:$C$20000,"buildings",_Data_Sectoral!$D$2:$D$20000,"TOTAL",_Data_Sectoral!$E$2:$E$20000,2031) -> 307.87237 | J24: =SUMIFS(_Data_Sectoral!$F$2:$F$20000,_Data_Sectoral!$A$2:$A$20000,"FR",_Data_Sectoral!$C$2:$C$20000,"buildings",_Data_Sectoral!$D$2:$D$20000,"TOTAL",_Data_Sectoral!$E$2:$E$20000,2032) -> 312.99231 | K24: =SUMIFS(_Data_Sectoral!$F$2:$F$20000,_Data_Sectoral!$A$2:$A$20000,"FR",_Data_Sectoral!$C$2:$C$20000,"buildings",_Data_Sectoral!$D$2:$D$20000,"TOTAL",_Data_Sectoral!$E$2:$E$20000,2033) -> 318.58564 | L24: =SUMIFS(_Data_Sectoral!$F$2:$F$20000,_Data_Sectoral!$A$2:$A$20000,"FR",_Data_Sectoral!$C$2:$C$20000,"buildings",_Data_Sectoral!$D$2:$D$20000,"TOTAL",_Data_Sectoral!$E$2:$E$20000,2034) -> 324.96665 | M24: =SUMIFS(_Data_Sectoral!$F$2:$F$20000,_Data_Sectoral!$A$2:$A$20000,"FR",_Data_Sectoral!$C$2:$C$20000,"buildings",_Data_Sectoral!$D$2:$D$20000,"TOTAL",_Data_Sectoral!$E$2:$E$20000,2035) -> 331.32475 | N24: =SUMIFS(_Data_Sectoral!$F$2:$F$20000,_Data_Sectoral!$A$2:$A$20000,"FR",_Data_Sectoral!$C$2:$C$20000,"buildings",_Data_Sectoral!$D$2:$D$20000,"TOTAL",_Data_Sectoral!$E$2:$E$20000,2036) -> 336.68283 | O24: =SUMIFS(_Data_Sectoral!$F$2:$F$20000,_Data_Sectoral!$A$2:$A$20000,"FR",_Data_Sectoral!$C$2:$C$20000,"buildings",_Data_Sectoral!$D$2:$D$20000,"TOTAL",_Data_Sectoral!$E$2:$E$20000,2037) -> 341.41163 | P24: =SUMIFS(_Data_Sectoral!$F$2:$F$20000,_Data_Sectoral!$A$2:$A$20000,"FR",_Data_Sectoral!$C$2:$C$20000,"buildings",_Data_Sectoral!$D$2:$D$20000,"TOTAL",_Data_Sectoral!$E$2:$E$20000,2038) -> 346.87019 | Q24: =SUMIFS(_Data_Sectoral!$F$2:$F$20000,_Data_Sectoral!$A$2:$A$20000,"FR",_Data_Sectoral!$C$2:$C$20000,"buildings",_Data_Sectoral!$D$2:$D$20000,"TOTAL",_Data_Sectoral!$E$2:$E$20000,2039) -> 352.75671 | R24: =SUMIFS(_Data_Sectoral!$F$2:$F$20000,_Data_Sectoral!$A$2:$A$20000,"FR",_Data_Sectoral!$C$2:$C$20000,"buildings",_Data_Sectoral!$D$2:$D$20000,"TOTAL",_Data_Sectoral!$E$2:$E$20000,2040) -> 357.92401
A25: Industry | B25: =SUMIFS(_Data_Sectoral!$F$2:$F$20000,_Data_Sectoral!$A$2:$A$20000,"FR",_Data_Sectoral!$C$2:$C$20000,"industry",_Data_Sectoral!$D$2:$D$20000,"TOTAL",_Data_Sectoral!$E$2:$E$20000,2024) -> 113.68786 | C25: =SUMIFS(_Data_Sectoral!$F$2:$F$20000,_Data_Sectoral!$A$2:$A$20000,"FR",_Data_Sectoral!$C$2:$C$20000,"industry",_Data_Sectoral!$D$2:$D$20000,"TOTAL",_Data_Sectoral!$E$2:$E$20000,2025) -> 113.7473 | D25: =SUMIFS(_Data_Sectoral!$F$2:$F$20000,_Data_Sectoral!$A$2:$A$20000,"FR",_Data_Sectoral!$C$2:$C$20000,"industry",_Data_Sectoral!$D$2:$D$20000,"TOTAL",_Data_Sectoral!$E$2:$E$20000,2026) -> 113.75378 | E25: =SUMIFS(_Data_Sectoral!$F$2:$F$20000,_Data_Sectoral!$A$2:$A$20000,"FR",_Data_Sectoral!$C$2:$C$20000,"industry",_Data_Sectoral!$D$2:$D$20000,"TOTAL",_Data_Sectoral!$E$2:$E$20000,2027) -> 113.54681 | F25: =SUMIFS(_Data_Sectoral!$F$2:$F$20000,_Data_Sectoral!$A$2:$A$20000,"FR",_Data_Sectoral!$C$2:$C$20000,"industry",_Data_Sectoral!$D$2:$D$20000,"TOTAL",_Data_Sectoral!$E$2:$E$20000,2028) -> 113.64781 | G25: =SUMIFS(_Data_Sectoral!$F$2:$F$20000,_Data_Sectoral!$A$2:$A$20000,"FR",_Data_Sectoral!$C$2:$C$20000,"industry",_Data_Sectoral!$D$2:$D$20000,"TOTAL",_Data_Sectoral!$E$2:$E$20000,2029) -> 113.56379 | H25: =SUMIFS(_Data_Sectoral!$F$2:$F$20000,_Data_Sectoral!$A$2:$A$20000,"FR",_Data_Sectoral!$C$2:$C$20000,"industry",_Data_Sectoral!$D$2:$D$20000,"TOTAL",_Data_Sectoral!$E$2:$E$20000,2030) -> 116.15258 | I25: =SUMIFS(_Data_Sectoral!$F$2:$F$20000,_Data_Sectoral!$A$2:$A$20000,"FR",_Data_Sectoral!$C$2:$C$20000,"industry",_Data_Sectoral!$D$2:$D$20000,"TOTAL",_Data_Sectoral!$E$2:$E$20000,2031) -> 117.54518 | J25: =SUMIFS(_Data_Sectoral!$F$2:$F$20000,_Data_Sectoral!$A$2:$A$20000,"FR",_Data_Sectoral!$C$2:$C$20000,"industry",_Data_Sectoral!$D$2:$D$20000,"TOTAL",_Data_Sectoral!$E$2:$E$20000,2032) -> 119.90797 | K25: =SUMIFS(_Data_Sectoral!$F$2:$F$20000,_Data_Sectoral!$A$2:$A$20000,"FR",_Data_Sectoral!$C$2:$C$20000,"industry",_Data_Sectoral!$D$2:$D$20000,"TOTAL",_Data_Sectoral!$E$2:$E$20000,2033) -> 122.01932 | L25: =SUMIFS(_Data_Sectoral!$F$2:$F$20000,_Data_Sectoral!$A$2:$A$20000,"FR",_Data_Sectoral!$C$2:$C$20000,"industry",_Data_Sectoral!$D$2:$D$20000,"TOTAL",_Data_Sectoral!$E$2:$E$20000,2034) -> 124.42645 | M25: =SUMIFS(_Data_Sectoral!$F$2:$F$20000,_Data_Sectoral!$A$2:$A$20000,"FR",_Data_Sectoral!$C$2:$C$20000,"industry",_Data_Sectoral!$D$2:$D$20000,"TOTAL",_Data_Sectoral!$E$2:$E$20000,2035) -> 126.87382 | N25: =SUMIFS(_Data_Sectoral!$F$2:$F$20000,_Data_Sectoral!$A$2:$A$20000,"FR",_Data_Sectoral!$C$2:$C$20000,"industry",_Data_Sectoral!$D$2:$D$20000,"TOTAL",_Data_Sectoral!$E$2:$E$20000,2036) -> 129.56643 | O25: =SUMIFS(_Data_Sectoral!$F$2:$F$20000,_Data_Sectoral!$A$2:$A$20000,"FR",_Data_Sectoral!$C$2:$C$20000,"industry",_Data_Sectoral!$D$2:$D$20000,"TOTAL",_Data_Sectoral!$E$2:$E$20000,2037) -> 132.46104 | P25: =SUMIFS(_Data_Sectoral!$F$2:$F$20000,_Data_Sectoral!$A$2:$A$20000,"FR",_Data_Sectoral!$C$2:$C$20000,"industry",_Data_Sectoral!$D$2:$D$20000,"TOTAL",_Data_Sectoral!$E$2:$E$20000,2038) -> 135.38043 | Q25: =SUMIFS(_Data_Sectoral!$F$2:$F$20000,_Data_Sectoral!$A$2:$A$20000,"FR",_Data_Sectoral!$C$2:$C$20000,"industry",_Data_Sectoral!$D$2:$D$20000,"TOTAL",_Data_Sectoral!$E$2:$E$20000,2039) -> 138.37094 | R25: =SUMIFS(_Data_Sectoral!$F$2:$F$20000,_Data_Sectoral!$A$2:$A$20000,"FR",_Data_Sectoral!$C$2:$C$20000,"industry",_Data_Sectoral!$D$2:$D$20000,"TOTAL",_Data_Sectoral!$E$2:$E$20000,2040) -> 141.53192
A26: Data Centers | B26: =SUMIFS(_Data_Sectoral!$F$2:$F$20000,_Data_Sectoral!$A$2:$A$20000,"FR",_Data_Sectoral!$C$2:$C$20000,"data_centers",_Data_Sectoral!$D$2:$D$20000,"TOTAL",_Data_Sectoral!$E$2:$E$20000,2024) -> 5.8254 | C26: =SUMIFS(_Data_Sectoral!$F$2:$F$20000,_Data_Sectoral!$A$2:$A$20000,"FR",_Data_Sectoral!$C$2:$C$20000,"data_centers",_Data_Sectoral!$D$2:$D$20000,"TOTAL",_Data_Sectoral!$E$2:$E$20000,2025) -> 6.1510947 | D26: =SUMIFS(_Data_Sectoral!$F$2:$F$20000,_Data_Sectoral!$A$2:$A$20000,"FR",_Data_Sectoral!$C$2:$C$20000,"data_centers",_Data_Sectoral!$D$2:$D$20000,"TOTAL",_Data_Sectoral!$E$2:$E$20000,2026) -> 6.4714197 | E26: =SUMIFS(_Data_Sectoral!$F$2:$F$20000,_Data_Sectoral!$A$2:$A$20000,"FR",_Data_Sectoral!$C$2:$C$20000,"data_centers",_Data_Sectoral!$D$2:$D$20000,"TOTAL",_Data_Sectoral!$E$2:$E$20000,2027) -> 7.4139144 | F26: =SUMIFS(_Data_Sectoral!$F$2:$F$20000,_Data_Sectoral!$A$2:$A$20000,"FR",_Data_Sectoral!$C$2:$C$20000,"data_centers",_Data_Sectoral!$D$2:$D$20000,"TOTAL",_Data_Sectoral!$E$2:$E$20000,2028) -> 8.6168844 | G26: =SUMIFS(_Data_Sectoral!$F$2:$F$20000,_Data_Sectoral!$A$2:$A$20000,"FR",_Data_Sectoral!$C$2:$C$20000,"data_centers",_Data_Sectoral!$D$2:$D$20000,"TOTAL",_Data_Sectoral!$E$2:$E$20000,2029) -> 9.8998517 | H26: =SUMIFS(_Data_Sectoral!$F$2:$F$20000,_Data_Sectoral!$A$2:$A$20000,"FR",_Data_Sectoral!$C$2:$C$20000,"data_centers",_Data_Sectoral!$D$2:$D$20000,"TOTAL",_Data_Sectoral!$E$2:$E$20000,2030) -> 11.123894 | I26: =SUMIFS(_Data_Sectoral!$F$2:$F$20000,_Data_Sectoral!$A$2:$A$20000,"FR",_Data_Sectoral!$C$2:$C$20000,"data_centers",_Data_Sectoral!$D$2:$D$20000,"TOTAL",_Data_Sectoral!$E$2:$E$20000,2031) -> 12.339837 | J26: =SUMIFS(_Data_Sectoral!$F$2:$F$20000,_Data_Sectoral!$A$2:$A$20000,"FR",_Data_Sectoral!$C$2:$C$20000,"data_centers",_Data_Sectoral!$D$2:$D$20000,"TOTAL",_Data_Sectoral!$E$2:$E$20000,2032) -> 13.80182 | K26: =SUMIFS(_Data_Sectoral!$F$2:$F$20000,_Data_Sectoral!$A$2:$A$20000,"FR",_Data_Sectoral!$C$2:$C$20000,"data_centers",_Data_Sectoral!$D$2:$D$20000,"TOTAL",_Data_Sectoral!$E$2:$E$20000,2033) -> 15.258372 | L26: =SUMIFS(_Data_Sectoral!$F$2:$F$20000,_Data_Sectoral!$A$2:$A$20000,"FR",_Data_Sectoral!$C$2:$C$20000,"data_centers",_Data_Sectoral!$D$2:$D$20000,"TOTAL",_Data_Sectoral!$E$2:$E$20000,2034) -> 16.671144 | M26: =SUMIFS(_Data_Sectoral!$F$2:$F$20000,_Data_Sectoral!$A$2:$A$20000,"FR",_Data_Sectoral!$C$2:$C$20000,"data_centers",_Data_Sectoral!$D$2:$D$20000,"TOTAL",_Data_Sectoral!$E$2:$E$20000,2035) -> 17.998945 | N26: =SUMIFS(_Data_Sectoral!$F$2:$F$20000,_Data_Sectoral!$A$2:$A$20000,"FR",_Data_Sectoral!$C$2:$C$20000,"data_centers",_Data_Sectoral!$D$2:$D$20000,"TOTAL",_Data_Sectoral!$E$2:$E$20000,2036) -> 19.199535 | O26: =SUMIFS(_Data_Sectoral!$F$2:$F$20000,_Data_Sectoral!$A$2:$A$20000,"FR",_Data_Sectoral!$C$2:$C$20000,"data_centers",_Data_Sectoral!$D$2:$D$20000,"TOTAL",_Data_Sectoral!$E$2:$E$20000,2037) -> 20.231702 | P26: =SUMIFS(_Data_Sectoral!$F$2:$F$20000,_Data_Sectoral!$A$2:$A$20000,"FR",_Data_Sectoral!$C$2:$C$20000,"data_centers",_Data_Sectoral!$D$2:$D$20000,"TOTAL",_Data_Sectoral!$E$2:$E$20000,2038) -> 21.057493 | Q26: =SUMIFS(_Data_Sectoral!$F$2:$F$20000,_Data_Sectoral!$A$2:$A$20000,"FR",_Data_Sectoral!$C$2:$C$20000,"data_centers",_Data_Sectoral!$D$2:$D$20000,"TOTAL",_Data_Sectoral!$E$2:$E$20000,2039) -> 21.644435 | R26: =SUMIFS(_Data_Sectoral!$F$2:$F$20000,_Data_Sectoral!$A$2:$A$20000,"FR",_Data_Sectoral!$C$2:$C$20000,"data_centers",_Data_Sectoral!$D$2:$D$20000,"TOTAL",_Data_Sectoral!$E$2:$E$20000,2040) -> 21.967587
A27: Hydrogen | B27: =SUMIFS(_Data_Sectoral!$F$2:$F$20000,_Data_Sectoral!$A$2:$A$20000,"FR",_Data_Sectoral!$C$2:$C$20000,"hydrogen",_Data_Sectoral!$D$2:$D$20000,"TOTAL",_Data_Sectoral!$E$2:$E$20000,2024) -> 0.06 | C27: =SUMIFS(_Data_Sectoral!$F$2:$F$20000,_Data_Sectoral!$A$2:$A$20000,"FR",_Data_Sectoral!$C$2:$C$20000,"hydrogen",_Data_Sectoral!$D$2:$D$20000,"TOTAL",_Data_Sectoral!$E$2:$E$20000,2025) -> 0.075 | D27: =SUMIFS(_Data_Sectoral!$F$2:$F$20000,_Data_Sectoral!$A$2:$A$20000,"FR",_Data_Sectoral!$C$2:$C$20000,"hydrogen",_Data_Sectoral!$D$2:$D$20000,"TOTAL",_Data_Sectoral!$E$2:$E$20000,2026) -> 0.946262 | E27: =SUMIFS(_Data_Sectoral!$F$2:$F$20000,_Data_Sectoral!$A$2:$A$20000,"FR",_Data_Sectoral!$C$2:$C$20000,"hydrogen",_Data_Sectoral!$D$2:$D$20000,"TOTAL",_Data_Sectoral!$E$2:$E$20000,2027) -> 1.817525 | F27: =SUMIFS(_Data_Sectoral!$F$2:$F$20000,_Data_Sectoral!$A$2:$A$20000,"FR",_Data_Sectoral!$C$2:$C$20000,"hydrogen",_Data_Sectoral!$D$2:$D$20000,"TOTAL",_Data_Sectoral!$E$2:$E$20000,2028) -> 2.623795 | G27: =SUMIFS(_Data_Sectoral!$F$2:$F$20000,_Data_Sectoral!$A$2:$A$20000,"FR",_Data_Sectoral!$C$2:$C$20000,"hydrogen",_Data_Sectoral!$D$2:$D$20000,"TOTAL",_Data_Sectoral!$E$2:$E$20000,2029) -> 3.689712 | H27: =SUMIFS(_Data_Sectoral!$F$2:$F$20000,_Data_Sectoral!$A$2:$A$20000,"FR",_Data_Sectoral!$C$2:$C$20000,"hydrogen",_Data_Sectoral!$D$2:$D$20000,"TOTAL",_Data_Sectoral!$E$2:$E$20000,2030) -> 3.8106 | I27: =SUMIFS(_Data_Sectoral!$F$2:$F$20000,_Data_Sectoral!$A$2:$A$20000,"FR",_Data_Sectoral!$C$2:$C$20000,"hydrogen",_Data_Sectoral!$D$2:$D$20000,"TOTAL",_Data_Sectoral!$E$2:$E$20000,2031) -> 4.49388 | J27: =SUMIFS(_Data_Sectoral!$F$2:$F$20000,_Data_Sectoral!$A$2:$A$20000,"FR",_Data_Sectoral!$C$2:$C$20000,"hydrogen",_Data_Sectoral!$D$2:$D$20000,"TOTAL",_Data_Sectoral!$E$2:$E$20000,2032) -> 5.24286 | K27: =SUMIFS(_Data_Sectoral!$F$2:$F$20000,_Data_Sectoral!$A$2:$A$20000,"FR",_Data_Sectoral!$C$2:$C$20000,"hydrogen",_Data_Sectoral!$D$2:$D$20000,"TOTAL",_Data_Sectoral!$E$2:$E$20000,2033) -> 6.09696 | L27: =SUMIFS(_Data_Sectoral!$F$2:$F$20000,_Data_Sectoral!$A$2:$A$20000,"FR",_Data_Sectoral!$C$2:$C$20000,"hydrogen",_Data_Sectoral!$D$2:$D$20000,"TOTAL",_Data_Sectoral!$E$2:$E$20000,2034) -> 6.97734 | M27: =SUMIFS(_Data_Sectoral!$F$2:$F$20000,_Data_Sectoral!$A$2:$A$20000,"FR",_Data_Sectoral!$C$2:$C$20000,"hydrogen",_Data_Sectoral!$D$2:$D$20000,"TOTAL",_Data_Sectoral!$E$2:$E$20000,2035) -> 7.884 | N27: =SUMIFS(_Data_Sectoral!$F$2:$F$20000,_Data_Sectoral!$A$2:$A$20000,"FR",_Data_Sectoral!$C$2:$C$20000,"hydrogen",_Data_Sectoral!$D$2:$D$20000,"TOTAL",_Data_Sectoral!$E$2:$E$20000,2036) -> 8.81694 | O27: =SUMIFS(_Data_Sectoral!$F$2:$F$20000,_Data_Sectoral!$A$2:$A$20000,"FR",_Data_Sectoral!$C$2:$C$20000,"hydrogen",_Data_Sectoral!$D$2:$D$20000,"TOTAL",_Data_Sectoral!$E$2:$E$20000,2037) -> 9.5046 | P27: =SUMIFS(_Data_Sectoral!$F$2:$F$20000,_Data_Sectoral!$A$2:$A$20000,"FR",_Data_Sectoral!$C$2:$C$20000,"hydrogen",_Data_Sectoral!$D$2:$D$20000,"TOTAL",_Data_Sectoral!$E$2:$E$20000,2038) -> 10.20978 | Q27: =SUMIFS(_Data_Sectoral!$F$2:$F$20000,_Data_Sectoral!$A$2:$A$20000,"FR",_Data_Sectoral!$C$2:$C$20000,"hydrogen",_Data_Sectoral!$D$2:$D$20000,"TOTAL",_Data_Sectoral!$E$2:$E$20000,2039) -> 10.93248 | R27: =SUMIFS(_Data_Sectoral!$F$2:$F$20000,_Data_Sectoral!$A$2:$A$20000,"FR",_Data_Sectoral!$C$2:$C$20000,"hydrogen",_Data_Sectoral!$D$2:$D$20000,"TOTAL",_Data_Sectoral!$E$2:$E$20000,2040) -> 11.388
A28: Total | B28: =SUM(B23:B27) -> 408.72487 | C28: =SUM(C23:C27) -> 414.15645 | D28: =SUM(D23:D27) -> 420.45619 | E28: =SUM(E23:E27) -> 427.73974 | F28: =SUM(F23:F27) -> 437.19146 | G28: =SUM(G23:G27) -> 447.86612 | H28: =SUM(H23:H27) -> 461.16318 | I28: =SUM(I23:I27) -> 473.21125 | ... R28: =SUM(R23:R27) -> 603.58354
A30: Italy
A31: Sector | B31: 2024 | C31: 2025 | D31: 2026 | E31: 2027 | F31: 2028 | G31: 2029 | H31: 2030 | I31: 2031 | J31: 2032 | K31: 2033 | L31: 2034 | M31: 2035 | N31: 2036 | O31: 2037 | P31: 2038 | Q31: 2039 | R31: 2040
A32: Transport | B32: =SUMIFS(_Data_Sectoral!$F$2:$F$20000,_Data_Sectoral!$A$2:$A$20000,"IT",_Data_Sectoral!$C$2:$C$20000,"transport",_Data_Sectoral!$D$2:$D$20000,"TOTAL",_Data_Sectoral!$E$2:$E$20000,2024) -> 6.9918554 | C32: =SUMIFS(_Data_Sectoral!$F$2:$F$20000,_Data_Sectoral!$A$2:$A$20000,"IT",_Data_Sectoral!$C$2:$C$20000,"transport",_Data_Sectoral!$D$2:$D$20000,"TOTAL",_Data_Sectoral!$E$2:$E$20000,2025) -> 7.756669 | D32: =SUMIFS(_Data_Sectoral!$F$2:$F$20000,_Data_Sectoral!$A$2:$A$20000,"IT",_Data_Sectoral!$C$2:$C$20000,"transport",_Data_Sectoral!$D$2:$D$20000,"TOTAL",_Data_Sectoral!$E$2:$E$20000,2026) -> 8.7172499 | E32: =SUMIFS(_Data_Sectoral!$F$2:$F$20000,_Data_Sectoral!$A$2:$A$20000,"IT",_Data_Sectoral!$C$2:$C$20000,"transport",_Data_Sectoral!$D$2:$D$20000,"TOTAL",_Data_Sectoral!$E$2:$E$20000,2027) -> 10.069928 | F32: =SUMIFS(_Data_Sectoral!$F$2:$F$20000,_Data_Sectoral!$A$2:$A$20000,"IT",_Data_Sectoral!$C$2:$C$20000,"transport",_Data_Sectoral!$D$2:$D$20000,"TOTAL",_Data_Sectoral!$E$2:$E$20000,2028) -> 11.784853 | G32: =SUMIFS(_Data_Sectoral!$F$2:$F$20000,_Data_Sectoral!$A$2:$A$20000,"IT",_Data_Sectoral!$C$2:$C$20000,"transport",_Data_Sectoral!$D$2:$D$20000,"TOTAL",_Data_Sectoral!$E$2:$E$20000,2029) -> 13.815043 | H32: =SUMIFS(_Data_Sectoral!$F$2:$F$20000,_Data_Sectoral!$A$2:$A$20000,"IT",_Data_Sectoral!$C$2:$C$20000,"transport",_Data_Sectoral!$D$2:$D$20000,"TOTAL",_Data_Sectoral!$E$2:$E$20000,2030) -> 16.373009 | I32: =SUMIFS(_Data_Sectoral!$F$2:$F$20000,_Data_Sectoral!$A$2:$A$20000,"IT",_Data_Sectoral!$C$2:$C$20000,"transport",_Data_Sectoral!$D$2:$D$20000,"TOTAL",_Data_Sectoral!$E$2:$E$20000,2031) -> 19.118957 | J32: =SUMIFS(_Data_Sectoral!$F$2:$F$20000,_Data_Sectoral!$A$2:$A$20000,"IT",_Data_Sectoral!$C$2:$C$20000,"transport",_Data_Sectoral!$D$2:$D$20000,"TOTAL",_Data_Sectoral!$E$2:$E$20000,2032) -> 22.221643 | K32: =SUMIFS(_Data_Sectoral!$F$2:$F$20000,_Data_Sectoral!$A$2:$A$20000,"IT",_Data_Sectoral!$C$2:$C$20000,"transport",_Data_Sectoral!$D$2:$D$20000,"TOTAL",_Data_Sectoral!$E$2:$E$20000,2033) -> 25.669789 | L32: =SUMIFS(_Data_Sectoral!$F$2:$F$20000,_Data_Sectoral!$A$2:$A$20000,"IT",_Data_Sectoral!$C$2:$C$20000,"transport",_Data_Sectoral!$D$2:$D$20000,"TOTAL",_Data_Sectoral!$E$2:$E$20000,2034) -> 29.289093 | M32: =SUMIFS(_Data_Sectoral!$F$2:$F$20000,_Data_Sectoral!$A$2:$A$20000,"IT",_Data_Sectoral!$C$2:$C$20000,"transport",_Data_Sectoral!$D$2:$D$20000,"TOTAL",_Data_Sectoral!$E$2:$E$20000,2035) -> 33.026749 | N32: =SUMIFS(_Data_Sectoral!$F$2:$F$20000,_Data_Sectoral!$A$2:$A$20000,"IT",_Data_Sectoral!$C$2:$C$20000,"transport",_Data_Sectoral!$D$2:$D$20000,"TOTAL",_Data_Sectoral!$E$2:$E$20000,2036) -> 36.694065 | O32: =SUMIFS(_Data_Sectoral!$F$2:$F$20000,_Data_Sectoral!$A$2:$A$20000,"IT",_Data_Sectoral!$C$2:$C$20000,"transport",_Data_Sectoral!$D$2:$D$20000,"TOTAL",_Data_Sectoral!$E$2:$E$20000,2037) -> 40.254658 | P32: =SUMIFS(_Data_Sectoral!$F$2:$F$20000,_Data_Sectoral!$A$2:$A$20000,"IT",_Data_Sectoral!$C$2:$C$20000,"transport",_Data_Sectoral!$D$2:$D$20000,"TOTAL",_Data_Sectoral!$E$2:$E$20000,2038) -> 43.832381 | Q32: =SUMIFS(_Data_Sectoral!$F$2:$F$20000,_Data_Sectoral!$A$2:$A$20000,"IT",_Data_Sectoral!$C$2:$C$20000,"transport",_Data_Sectoral!$D$2:$D$20000,"TOTAL",_Data_Sectoral!$E$2:$E$20000,2039) -> 47.436794 | R32: =SUMIFS(_Data_Sectoral!$F$2:$F$20000,_Data_Sectoral!$A$2:$A$20000,"IT",_Data_Sectoral!$C$2:$C$20000,"transport",_Data_Sectoral!$D$2:$D$20000,"TOTAL",_Data_Sectoral!$E$2:$E$20000,2040) -> 51.076017
A33: Buildings | B33: =SUMIFS(_Data_Sectoral!$F$2:$F$20000,_Data_Sectoral!$A$2:$A$20000,"IT",_Data_Sectoral!$C$2:$C$20000,"buildings",_Data_Sectoral!$D$2:$D$20000,"TOTAL",_Data_Sectoral!$E$2:$E$20000,2024) -> 161.57879 | C33: =SUMIFS(_Data_Sectoral!$F$2:$F$20000,_Data_Sectoral!$A$2:$A$20000,"IT",_Data_Sectoral!$C$2:$C$20000,"buildings",_Data_Sectoral!$D$2:$D$20000,"TOTAL",_Data_Sectoral!$E$2:$E$20000,2025) -> 165.59265 | D33: =SUMIFS(_Data_Sectoral!$F$2:$F$20000,_Data_Sectoral!$A$2:$A$20000,"IT",_Data_Sectoral!$C$2:$C$20000,"buildings",_Data_Sectoral!$D$2:$D$20000,"TOTAL",_Data_Sectoral!$E$2:$E$20000,2026) -> 169.45082 | E33: =SUMIFS(_Data_Sectoral!$F$2:$F$20000,_Data_Sectoral!$A$2:$A$20000,"IT",_Data_Sectoral!$C$2:$C$20000,"buildings",_Data_Sectoral!$D$2:$D$20000,"TOTAL",_Data_Sectoral!$E$2:$E$20000,2027) -> 173.15061 | F33: =SUMIFS(_Data_Sectoral!$F$2:$F$20000,_Data_Sectoral!$A$2:$A$20000,"IT",_Data_Sectoral!$C$2:$C$20000,"buildings",_Data_Sectoral!$D$2:$D$20000,"TOTAL",_Data_Sectoral!$E$2:$E$20000,2028) -> 178.27475 | G33: =SUMIFS(_Data_Sectoral!$F$2:$F$20000,_Data_Sectoral!$A$2:$A$20000,"IT",_Data_Sectoral!$C$2:$C$20000,"buildings",_Data_Sectoral!$D$2:$D$20000,"TOTAL",_Data_Sectoral!$E$2:$E$20000,2029) -> 183.86682 | H33: =SUMIFS(_Data_Sectoral!$F$2:$F$20000,_Data_Sectoral!$A$2:$A$20000,"IT",_Data_Sectoral!$C$2:$C$20000,"buildings",_Data_Sectoral!$D$2:$D$20000,"TOTAL",_Data_Sectoral!$E$2:$E$20000,2030) -> 189.91731 | I33: =SUMIFS(_Data_Sectoral!$F$2:$F$20000,_Data_Sectoral!$A$2:$A$20000,"IT",_Data_Sectoral!$C$2:$C$20000,"buildings",_Data_Sectoral!$D$2:$D$20000,"TOTAL",_Data_Sectoral!$E$2:$E$20000,2031) -> 189.21479 | J33: =SUMIFS(_Data_Sectoral!$F$2:$F$20000,_Data_Sectoral!$A$2:$A$20000,"IT",_Data_Sectoral!$C$2:$C$20000,"buildings",_Data_Sectoral!$D$2:$D$20000,"TOTAL",_Data_Sectoral!$E$2:$E$20000,2032) -> 190.09259 | K33: =SUMIFS(_Data_Sectoral!$F$2:$F$20000,_Data_Sectoral!$A$2:$A$20000,"IT",_Data_Sectoral!$C$2:$C$20000,"buildings",_Data_Sectoral!$D$2:$D$20000,"TOTAL",_Data_Sectoral!$E$2:$E$20000,2033) -> 191.567 | L33: =SUMIFS(_Data_Sectoral!$F$2:$F$20000,_Data_Sectoral!$A$2:$A$20000,"IT",_Data_Sectoral!$C$2:$C$20000,"buildings",_Data_Sectoral!$D$2:$D$20000,"TOTAL",_Data_Sectoral!$E$2:$E$20000,2034) -> 194.06731 | M33: =SUMIFS(_Data_Sectoral!$F$2:$F$20000,_Data_Sectoral!$A$2:$A$20000,"IT",_Data_Sectoral!$C$2:$C$20000,"buildings",_Data_Sectoral!$D$2:$D$20000,"TOTAL",_Data_Sectoral!$E$2:$E$20000,2035) -> 196.43547 | N33: =SUMIFS(_Data_Sectoral!$F$2:$F$20000,_Data_Sectoral!$A$2:$A$20000,"IT",_Data_Sectoral!$C$2:$C$20000,"buildings",_Data_Sectoral!$D$2:$D$20000,"TOTAL",_Data_Sectoral!$E$2:$E$20000,2036) -> 198.18028 | O33: =SUMIFS(_Data_Sectoral!$F$2:$F$20000,_Data_Sectoral!$A$2:$A$20000,"IT",_Data_Sectoral!$C$2:$C$20000,"buildings",_Data_Sectoral!$D$2:$D$20000,"TOTAL",_Data_Sectoral!$E$2:$E$20000,2037) -> 197.21805 | P33: =SUMIFS(_Data_Sectoral!$F$2:$F$20000,_Data_Sectoral!$A$2:$A$20000,"IT",_Data_Sectoral!$C$2:$C$20000,"buildings",_Data_Sectoral!$D$2:$D$20000,"TOTAL",_Data_Sectoral!$E$2:$E$20000,2038) -> 197.45676 | Q33: =SUMIFS(_Data_Sectoral!$F$2:$F$20000,_Data_Sectoral!$A$2:$A$20000,"IT",_Data_Sectoral!$C$2:$C$20000,"buildings",_Data_Sectoral!$D$2:$D$20000,"TOTAL",_Data_Sectoral!$E$2:$E$20000,2039) -> 198.78386 | R33: =SUMIFS(_Data_Sectoral!$F$2:$F$20000,_Data_Sectoral!$A$2:$A$20000,"IT",_Data_Sectoral!$C$2:$C$20000,"buildings",_Data_Sectoral!$D$2:$D$20000,"TOTAL",_Data_Sectoral!$E$2:$E$20000,2040) -> 199.95515
A34: Industry | B34: =SUMIFS(_Data_Sectoral!$F$2:$F$20000,_Data_Sectoral!$A$2:$A$20000,"IT",_Data_Sectoral!$C$2:$C$20000,"industry",_Data_Sectoral!$D$2:$D$20000,"TOTAL",_Data_Sectoral!$E$2:$E$20000,2024) -> 126.41462 | C34: =SUMIFS(_Data_Sectoral!$F$2:$F$20000,_Data_Sectoral!$A$2:$A$20000,"IT",_Data_Sectoral!$C$2:$C$20000,"industry",_Data_Sectoral!$D$2:$D$20000,"TOTAL",_Data_Sectoral!$E$2:$E$20000,2025) -> 125.69363 | D34: =SUMIFS(_Data_Sectoral!$F$2:$F$20000,_Data_Sectoral!$A$2:$A$20000,"IT",_Data_Sectoral!$C$2:$C$20000,"industry",_Data_Sectoral!$D$2:$D$20000,"TOTAL",_Data_Sectoral!$E$2:$E$20000,2026) -> 125.15339 | E34: =SUMIFS(_Data_Sectoral!$F$2:$F$20000,_Data_Sectoral!$A$2:$A$20000,"IT",_Data_Sectoral!$C$2:$C$20000,"industry",_Data_Sectoral!$D$2:$D$20000,"TOTAL",_Data_Sectoral!$E$2:$E$20000,2027) -> 124.01604 | F34: =SUMIFS(_Data_Sectoral!$F$2:$F$20000,_Data_Sectoral!$A$2:$A$20000,"IT",_Data_Sectoral!$C$2:$C$20000,"industry",_Data_Sectoral!$D$2:$D$20000,"TOTAL",_Data_Sectoral!$E$2:$E$20000,2028) -> 123.34984 | G34: =SUMIFS(_Data_Sectoral!$F$2:$F$20000,_Data_Sectoral!$A$2:$A$20000,"IT",_Data_Sectoral!$C$2:$C$20000,"industry",_Data_Sectoral!$D$2:$D$20000,"TOTAL",_Data_Sectoral!$E$2:$E$20000,2029) -> 121.87812 | H34: =SUMIFS(_Data_Sectoral!$F$2:$F$20000,_Data_Sectoral!$A$2:$A$20000,"IT",_Data_Sectoral!$C$2:$C$20000,"industry",_Data_Sectoral!$D$2:$D$20000,"TOTAL",_Data_Sectoral!$E$2:$E$20000,2030) -> 120.56294 | I34: =SUMIFS(_Data_Sectoral!$F$2:$F$20000,_Data_Sectoral!$A$2:$A$20000,"IT",_Data_Sectoral!$C$2:$C$20000,"industry",_Data_Sectoral!$D$2:$D$20000,"TOTAL",_Data_Sectoral!$E$2:$E$20000,2031) -> 119.4092 | J34: =SUMIFS(_Data_Sectoral!$F$2:$F$20000,_Data_Sectoral!$A$2:$A$20000,"IT",_Data_Sectoral!$C$2:$C$20000,"industry",_Data_Sectoral!$D$2:$D$20000,"TOTAL",_Data_Sectoral!$E$2:$E$20000,2032) -> 119.50029 | K34: =SUMIFS(_Data_Sectoral!$F$2:$F$20000,_Data_Sectoral!$A$2:$A$20000,"IT",_Data_Sectoral!$C$2:$C$20000,"industry",_Data_Sectoral!$D$2:$D$20000,"TOTAL",_Data_Sectoral!$E$2:$E$20000,2033) -> 120.05171 | L34: =SUMIFS(_Data_Sectoral!$F$2:$F$20000,_Data_Sectoral!$A$2:$A$20000,"IT",_Data_Sectoral!$C$2:$C$20000,"industry",_Data_Sectoral!$D$2:$D$20000,"TOTAL",_Data_Sectoral!$E$2:$E$20000,2034) -> 121.12435 | M34: =SUMIFS(_Data_Sectoral!$F$2:$F$20000,_Data_Sectoral!$A$2:$A$20000,"IT",_Data_Sectoral!$C$2:$C$20000,"industry",_Data_Sectoral!$D$2:$D$20000,"TOTAL",_Data_Sectoral!$E$2:$E$20000,2035) -> 122.26552 | N34: =SUMIFS(_Data_Sectoral!$F$2:$F$20000,_Data_Sectoral!$A$2:$A$20000,"IT",_Data_Sectoral!$C$2:$C$20000,"industry",_Data_Sectoral!$D$2:$D$20000,"TOTAL",_Data_Sectoral!$E$2:$E$20000,2036) -> 123.31524 | O34: =SUMIFS(_Data_Sectoral!$F$2:$F$20000,_Data_Sectoral!$A$2:$A$20000,"IT",_Data_Sectoral!$C$2:$C$20000,"industry",_Data_Sectoral!$D$2:$D$20000,"TOTAL",_Data_Sectoral!$E$2:$E$20000,2037) -> 124.21124 | P34: =SUMIFS(_Data_Sectoral!$F$2:$F$20000,_Data_Sectoral!$A$2:$A$20000,"IT",_Data_Sectoral!$C$2:$C$20000,"industry",_Data_Sectoral!$D$2:$D$20000,"TOTAL",_Data_Sectoral!$E$2:$E$20000,2038) -> 125.27777 | Q34: =SUMIFS(_Data_Sectoral!$F$2:$F$20000,_Data_Sectoral!$A$2:$A$20000,"IT",_Data_Sectoral!$C$2:$C$20000,"industry",_Data_Sectoral!$D$2:$D$20000,"TOTAL",_Data_Sectoral!$E$2:$E$20000,2039) -> 126.43338 | R34: =SUMIFS(_Data_Sectoral!$F$2:$F$20000,_Data_Sectoral!$A$2:$A$20000,"IT",_Data_Sectoral!$C$2:$C$20000,"industry",_Data_Sectoral!$D$2:$D$20000,"TOTAL",_Data_Sectoral!$E$2:$E$20000,2040) -> 127.61561
A35: Data Centers | B35: =SUMIFS(_Data_Sectoral!$F$2:$F$20000,_Data_Sectoral!$A$2:$A$20000,"IT",_Data_Sectoral!$C$2:$C$20000,"data_centers",_Data_Sectoral!$D$2:$D$20000,"TOTAL",_Data_Sectoral!$E$2:$E$20000,2024) -> 2.199855 | C35: =SUMIFS(_Data_Sectoral!$F$2:$F$20000,_Data_Sectoral!$A$2:$A$20000,"IT",_Data_Sectoral!$C$2:$C$20000,"data_centers",_Data_Sectoral!$D$2:$D$20000,"TOTAL",_Data_Sectoral!$E$2:$E$20000,2025) -> 2.9586187 | D35: =SUMIFS(_Data_Sectoral!$F$2:$F$20000,_Data_Sectoral!$A$2:$A$20000,"IT",_Data_Sectoral!$C$2:$C$20000,"data_centers",_Data_Sectoral!$D$2:$D$20000,"TOTAL",_Data_Sectoral!$E$2:$E$20000,2026) -> 4.6581966 | E35: =SUMIFS(_Data_Sectoral!$F$2:$F$20000,_Data_Sectoral!$A$2:$A$20000,"IT",_Data_Sectoral!$C$2:$C$20000,"data_centers",_Data_Sectoral!$D$2:$D$20000,"TOTAL",_Data_Sectoral!$E$2:$E$20000,2027) -> 6.4495516 | F35: =SUMIFS(_Data_Sectoral!$F$2:$F$20000,_Data_Sectoral!$A$2:$A$20000,"IT",_Data_Sectoral!$C$2:$C$20000,"data_centers",_Data_Sectoral!$D$2:$D$20000,"TOTAL",_Data_Sectoral!$E$2:$E$20000,2028) -> 8.7758184 | G35: =SUMIFS(_Data_Sectoral!$F$2:$F$20000,_Data_Sectoral!$A$2:$A$20000,"IT",_Data_Sectoral!$C$2:$C$20000,"data_centers",_Data_Sectoral!$D$2:$D$20000,"TOTAL",_Data_Sectoral!$E$2:$E$20000,2029) -> 10.786399 | H35: =SUMIFS(_Data_Sectoral!$F$2:$F$20000,_Data_Sectoral!$A$2:$A$20000,"IT",_Data_Sectoral!$C$2:$C$20000,"data_centers",_Data_Sectoral!$D$2:$D$20000,"TOTAL",_Data_Sectoral!$E$2:$E$20000,2030) -> 12.357442 | I35: =SUMIFS(_Data_Sectoral!$F$2:$F$20000,_Data_Sectoral!$A$2:$A$20000,"IT",_Data_Sectoral!$C$2:$C$20000,"data_centers",_Data_Sectoral!$D$2:$D$20000,"TOTAL",_Data_Sectoral!$E$2:$E$20000,2031) -> 13.914587 | J35: =SUMIFS(_Data_Sectoral!$F$2:$F$20000,_Data_Sectoral!$A$2:$A$20000,"IT",_Data_Sectoral!$C$2:$C$20000,"data_centers",_Data_Sectoral!$D$2:$D$20000,"TOTAL",_Data_Sectoral!$E$2:$E$20000,2032) -> 15.56314 | K35: =SUMIFS(_Data_Sectoral!$F$2:$F$20000,_Data_Sectoral!$A$2:$A$20000,"IT",_Data_Sectoral!$C$2:$C$20000,"data_centers",_Data_Sectoral!$D$2:$D$20000,"TOTAL",_Data_Sectoral!$E$2:$E$20000,2033) -> 17.20557 | L35: =SUMIFS(_Data_Sectoral!$F$2:$F$20000,_Data_Sectoral!$A$2:$A$20000,"IT",_Data_Sectoral!$C$2:$C$20000,"data_centers",_Data_Sectoral!$D$2:$D$20000,"TOTAL",_Data_Sectoral!$E$2:$E$20000,2034) -> 18.798634 | M35: =SUMIFS(_Data_Sectoral!$F$2:$F$20000,_Data_Sectoral!$A$2:$A$20000,"IT",_Data_Sectoral!$C$2:$C$20000,"data_centers",_Data_Sectoral!$D$2:$D$20000,"TOTAL",_Data_Sectoral!$E$2:$E$20000,2035) -> 20.295883 | N35: =SUMIFS(_Data_Sectoral!$F$2:$F$20000,_Data_Sectoral!$A$2:$A$20000,"IT",_Data_Sectoral!$C$2:$C$20000,"data_centers",_Data_Sectoral!$D$2:$D$20000,"TOTAL",_Data_Sectoral!$E$2:$E$20000,2036) -> 21.649686 | O35: =SUMIFS(_Data_Sectoral!$F$2:$F$20000,_Data_Sectoral!$A$2:$A$20000,"IT",_Data_Sectoral!$C$2:$C$20000,"data_centers",_Data_Sectoral!$D$2:$D$20000,"TOTAL",_Data_Sectoral!$E$2:$E$20000,2037) -> 22.813573 | P35: =SUMIFS(_Data_Sectoral!$F$2:$F$20000,_Data_Sectoral!$A$2:$A$20000,"IT",_Data_Sectoral!$C$2:$C$20000,"data_centers",_Data_Sectoral!$D$2:$D$20000,"TOTAL",_Data_Sectoral!$E$2:$E$20000,2038) -> 23.744747 | Q35: =SUMIFS(_Data_Sectoral!$F$2:$F$20000,_Data_Sectoral!$A$2:$A$20000,"IT",_Data_Sectoral!$C$2:$C$20000,"data_centers",_Data_Sectoral!$D$2:$D$20000,"TOTAL",_Data_Sectoral!$E$2:$E$20000,2039) -> 24.406592 | R35: =SUMIFS(_Data_Sectoral!$F$2:$F$20000,_Data_Sectoral!$A$2:$A$20000,"IT",_Data_Sectoral!$C$2:$C$20000,"data_centers",_Data_Sectoral!$D$2:$D$20000,"TOTAL",_Data_Sectoral!$E$2:$E$20000,2040) -> 24.770983
A36: Hydrogen | B36: =SUMIFS(_Data_Sectoral!$F$2:$F$20000,_Data_Sectoral!$A$2:$A$20000,"IT",_Data_Sectoral!$C$2:$C$20000,"hydrogen",_Data_Sectoral!$D$2:$D$20000,"TOTAL",_Data_Sectoral!$E$2:$E$20000,2024) -> 0.005 | C36: =SUMIFS(_Data_Sectoral!$F$2:$F$20000,_Data_Sectoral!$A$2:$A$20000,"IT",_Data_Sectoral!$C$2:$C$20000,"hydrogen",_Data_Sectoral!$D$2:$D$20000,"TOTAL",_Data_Sectoral!$E$2:$E$20000,2025) -> 0.005 | D36: =SUMIFS(_Data_Sectoral!$F$2:$F$20000,_Data_Sectoral!$A$2:$A$20000,"IT",_Data_Sectoral!$C$2:$C$20000,"hydrogen",_Data_Sectoral!$D$2:$D$20000,"TOTAL",_Data_Sectoral!$E$2:$E$20000,2026) -> 0.197235 | E36: =SUMIFS(_Data_Sectoral!$F$2:$F$20000,_Data_Sectoral!$A$2:$A$20000,"IT",_Data_Sectoral!$C$2:$C$20000,"hydrogen",_Data_Sectoral!$D$2:$D$20000,"TOTAL",_Data_Sectoral!$E$2:$E$20000,2027) -> 0.38947 | F36: =SUMIFS(_Data_Sectoral!$F$2:$F$20000,_Data_Sectoral!$A$2:$A$20000,"IT",_Data_Sectoral!$C$2:$C$20000,"hydrogen",_Data_Sectoral!$D$2:$D$20000,"TOTAL",_Data_Sectoral!$E$2:$E$20000,2028) -> 0.546624 | G36: =SUMIFS(_Data_Sectoral!$F$2:$F$20000,_Data_Sectoral!$A$2:$A$20000,"IT",_Data_Sectoral!$C$2:$C$20000,"hydrogen",_Data_Sectoral!$D$2:$D$20000,"TOTAL",_Data_Sectoral!$E$2:$E$20000,2029) -> 0.751608 | H36: =SUMIFS(_Data_Sectoral!$F$2:$F$20000,_Data_Sectoral!$A$2:$A$20000,"IT",_Data_Sectoral!$C$2:$C$20000,"hydrogen",_Data_Sectoral!$D$2:$D$20000,"TOTAL",_Data_Sectoral!$E$2:$E$20000,2030) -> 0.76212 | I36: =SUMIFS(_Data_Sectoral!$F$2:$F$20000,_Data_Sectoral!$A$2:$A$20000,"IT",_Data_Sectoral!$C$2:$C$20000,"hydrogen",_Data_Sectoral!$D$2:$D$20000,"TOTAL",_Data_Sectoral!$E$2:$E$20000,2031) -> 1.168409 | J36: =SUMIFS(_Data_Sectoral!$F$2:$F$20000,_Data_Sectoral!$A$2:$A$20000,"IT",_Data_Sectoral!$C$2:$C$20000,"hydrogen",_Data_Sectoral!$D$2:$D$20000,"TOTAL",_Data_Sectoral!$E$2:$E$20000,2032) -> 1.677715 | K36: =SUMIFS(_Data_Sectoral!$F$2:$F$20000,_Data_Sectoral!$A$2:$A$20000,"IT",_Data_Sectoral!$C$2:$C$20000,"hydrogen",_Data_Sectoral!$D$2:$D$20000,"TOTAL",_Data_Sectoral!$E$2:$E$20000,2033) -> 2.316845 | L36: =SUMIFS(_Data_Sectoral!$F$2:$F$20000,_Data_Sectoral!$A$2:$A$20000,"IT",_Data_Sectoral!$C$2:$C$20000,"hydrogen",_Data_Sectoral!$D$2:$D$20000,"TOTAL",_Data_Sectoral!$E$2:$E$20000,2034) -> 3.07003 | M36: =SUMIFS(_Data_Sectoral!$F$2:$F$20000,_Data_Sectoral!$A$2:$A$20000,"IT",_Data_Sectoral!$C$2:$C$20000,"hydrogen",_Data_Sectoral!$D$2:$D$20000,"TOTAL",_Data_Sectoral!$E$2:$E$20000,2035) -> 3.942 | N36: =SUMIFS(_Data_Sectoral!$F$2:$F$20000,_Data_Sectoral!$A$2:$A$20000,"IT",_Data_Sectoral!$C$2:$C$20000,"hydrogen",_Data_Sectoral!$D$2:$D$20000,"TOTAL",_Data_Sectoral!$E$2:$E$20000,2036) -> 4.937486 | O36: =SUMIFS(_Data_Sectoral!$F$2:$F$20000,_Data_Sectoral!$A$2:$A$20000,"IT",_Data_Sectoral!$C$2:$C$20000,"hydrogen",_Data_Sectoral!$D$2:$D$20000,"TOTAL",_Data_Sectoral!$E$2:$E$20000,2037) -> 5.892852 | P36: =SUMIFS(_Data_Sectoral!$F$2:$F$20000,_Data_Sectoral!$A$2:$A$20000,"IT",_Data_Sectoral!$C$2:$C$20000,"hydrogen",_Data_Sectoral!$D$2:$D$20000,"TOTAL",_Data_Sectoral!$E$2:$E$20000,2038) -> 6.94265 | Q36: =SUMIFS(_Data_Sectoral!$F$2:$F$20000,_Data_Sectoral!$A$2:$A$20000,"IT",_Data_Sectoral!$C$2:$C$20000,"hydrogen",_Data_Sectoral!$D$2:$D$20000,"TOTAL",_Data_Sectoral!$E$2:$E$20000,2039) -> 8.090035 | R36: =SUMIFS(_Data_Sectoral!$F$2:$F$20000,_Data_Sectoral!$A$2:$A$20000,"IT",_Data_Sectoral!$C$2:$C$20000,"hydrogen",_Data_Sectoral!$D$2:$D$20000,"TOTAL",_Data_Sectoral!$E$2:$E$20000,2040) -> 9.1104
A37: Total | B37: =SUM(B32:B36) -> 297.19013 | C37: =SUM(C32:C36) -> 302.00657 | D37: =SUM(D32:D36) -> 308.17689 | E37: =SUM(E32:E36) -> 314.0756 | F37: =SUM(F32:F36) -> 322.73189 | G37: =SUM(G32:G36) -> 331.09798 | H37: =SUM(H32:H36) -> 339.97282 | I37: =SUM(I32:I36) -> 342.82594 | ... R37: =SUM(R32:R36) -> 412.52816
A39: Spain
A40: Sector | B40: 2024 | C40: 2025 | D40: 2026 | E40: 2027 | F40: 2028 | G40: 2029 | H40: 2030 | I40: 2031 | J40: 2032 | K40: 2033 | L40: 2034 | M40: 2035 | N40: 2036 | O40: 2037 | P40: 2038 | Q40: 2039 | R40: 2040
A41: Transport | B41: =SUMIFS(_Data_Sectoral!$F$2:$F$20000,_Data_Sectoral!$A$2:$A$20000,"ES",_Data_Sectoral!$C$2:$C$20000,"transport",_Data_Sectoral!$D$2:$D$20000,"TOTAL",_Data_Sectoral!$E$2:$E$20000,2024) -> 4.3900014 | C41: =SUMIFS(_Data_Sectoral!$F$2:$F$20000,_Data_Sectoral!$A$2:$A$20000,"ES",_Data_Sectoral!$C$2:$C$20000,"transport",_Data_Sectoral!$D$2:$D$20000,"TOTAL",_Data_Sectoral!$E$2:$E$20000,2025) -> 5.015192 | D41: =SUMIFS(_Data_Sectoral!$F$2:$F$20000,_Data_Sectoral!$A$2:$A$20000,"ES",_Data_Sectoral!$C$2:$C$20000,"transport",_Data_Sectoral!$D$2:$D$20000,"TOTAL",_Data_Sectoral!$E$2:$E$20000,2026) -> 5.9037988 | E41: =SUMIFS(_Data_Sectoral!$F$2:$F$20000,_Data_Sectoral!$A$2:$A$20000,"ES",_Data_Sectoral!$C$2:$C$20000,"transport",_Data_Sectoral!$D$2:$D$20000,"TOTAL",_Data_Sectoral!$E$2:$E$20000,2027) -> 7.1011752 | F41: =SUMIFS(_Data_Sectoral!$F$2:$F$20000,_Data_Sectoral!$A$2:$A$20000,"ES",_Data_Sectoral!$C$2:$C$20000,"transport",_Data_Sectoral!$D$2:$D$20000,"TOTAL",_Data_Sectoral!$E$2:$E$20000,2028) -> 8.53646 | G41: =SUMIFS(_Data_Sectoral!$F$2:$F$20000,_Data_Sectoral!$A$2:$A$20000,"ES",_Data_Sectoral!$C$2:$C$20000,"transport",_Data_Sectoral!$D$2:$D$20000,"TOTAL",_Data_Sectoral!$E$2:$E$20000,2029) -> 10.18001 | H41: =SUMIFS(_Data_Sectoral!$F$2:$F$20000,_Data_Sectoral!$A$2:$A$20000,"ES",_Data_Sectoral!$C$2:$C$20000,"transport",_Data_Sectoral!$D$2:$D$20000,"TOTAL",_Data_Sectoral!$E$2:$E$20000,2030) -> 12.124589 | I41: =SUMIFS(_Data_Sectoral!$F$2:$F$20000,_Data_Sectoral!$A$2:$A$20000,"ES",_Data_Sectoral!$C$2:$C$20000,"transport",_Data_Sectoral!$D$2:$D$20000,"TOTAL",_Data_Sectoral!$E$2:$E$20000,2031) -> 14.206463 | J41: =SUMIFS(_Data_Sectoral!$F$2:$F$20000,_Data_Sectoral!$A$2:$A$20000,"ES",_Data_Sectoral!$C$2:$C$20000,"transport",_Data_Sectoral!$D$2:$D$20000,"TOTAL",_Data_Sectoral!$E$2:$E$20000,2032) -> 16.559587 | K41: =SUMIFS(_Data_Sectoral!$F$2:$F$20000,_Data_Sectoral!$A$2:$A$20000,"ES",_Data_Sectoral!$C$2:$C$20000,"transport",_Data_Sectoral!$D$2:$D$20000,"TOTAL",_Data_Sectoral!$E$2:$E$20000,2033) -> 19.021892 | L41: =SUMIFS(_Data_Sectoral!$F$2:$F$20000,_Data_Sectoral!$A$2:$A$20000,"ES",_Data_Sectoral!$C$2:$C$20000,"transport",_Data_Sectoral!$D$2:$D$20000,"TOTAL",_Data_Sectoral!$E$2:$E$20000,2034) -> 21.775505 | M41: =SUMIFS(_Data_Sectoral!$F$2:$F$20000,_Data_Sectoral!$A$2:$A$20000,"ES",_Data_Sectoral!$C$2:$C$20000,"transport",_Data_Sectoral!$D$2:$D$20000,"TOTAL",_Data_Sectoral!$E$2:$E$20000,2035) -> 24.58676 | N41: =SUMIFS(_Data_Sectoral!$F$2:$F$20000,_Data_Sectoral!$A$2:$A$20000,"ES",_Data_Sectoral!$C$2:$C$20000,"transport",_Data_Sectoral!$D$2:$D$20000,"TOTAL",_Data_Sectoral!$E$2:$E$20000,2036) -> 27.338515 | O41: =SUMIFS(_Data_Sectoral!$F$2:$F$20000,_Data_Sectoral!$A$2:$A$20000,"ES",_Data_Sectoral!$C$2:$C$20000,"transport",_Data_Sectoral!$D$2:$D$20000,"TOTAL",_Data_Sectoral!$E$2:$E$20000,2037) -> 30.247067 | P41: =SUMIFS(_Data_Sectoral!$F$2:$F$20000,_Data_Sectoral!$A$2:$A$20000,"ES",_Data_Sectoral!$C$2:$C$20000,"transport",_Data_Sectoral!$D$2:$D$20000,"TOTAL",_Data_Sectoral!$E$2:$E$20000,2038) -> 33.763953 | Q41: =SUMIFS(_Data_Sectoral!$F$2:$F$20000,_Data_Sectoral!$A$2:$A$20000,"ES",_Data_Sectoral!$C$2:$C$20000,"transport",_Data_Sectoral!$D$2:$D$20000,"TOTAL",_Data_Sectoral!$E$2:$E$20000,2039) -> 37.405382 | R41: =SUMIFS(_Data_Sectoral!$F$2:$F$20000,_Data_Sectoral!$A$2:$A$20000,"ES",_Data_Sectoral!$C$2:$C$20000,"transport",_Data_Sectoral!$D$2:$D$20000,"TOTAL",_Data_Sectoral!$E$2:$E$20000,2040) -> 41.151474
A42: Buildings | B42: =SUMIFS(_Data_Sectoral!$F$2:$F$20000,_Data_Sectoral!$A$2:$A$20000,"ES",_Data_Sectoral!$C$2:$C$20000,"buildings",_Data_Sectoral!$D$2:$D$20000,"TOTAL",_Data_Sectoral!$E$2:$E$20000,2024) -> 151.26116 | C42: =SUMIFS(_Data_Sectoral!$F$2:$F$20000,_Data_Sectoral!$A$2:$A$20000,"ES",_Data_Sectoral!$C$2:$C$20000,"buildings",_Data_Sectoral!$D$2:$D$20000,"TOTAL",_Data_Sectoral!$E$2:$E$20000,2025) -> 153.00513 | D42: =SUMIFS(_Data_Sectoral!$F$2:$F$20000,_Data_Sectoral!$A$2:$A$20000,"ES",_Data_Sectoral!$C$2:$C$20000,"buildings",_Data_Sectoral!$D$2:$D$20000,"TOTAL",_Data_Sectoral!$E$2:$E$20000,2026) -> 154.61652 | E42: =SUMIFS(_Data_Sectoral!$F$2:$F$20000,_Data_Sectoral!$A$2:$A$20000,"ES",_Data_Sectoral!$C$2:$C$20000,"buildings",_Data_Sectoral!$D$2:$D$20000,"TOTAL",_Data_Sectoral!$E$2:$E$20000,2027) -> 155.98355 | F42: =SUMIFS(_Data_Sectoral!$F$2:$F$20000,_Data_Sectoral!$A$2:$A$20000,"ES",_Data_Sectoral!$C$2:$C$20000,"buildings",_Data_Sectoral!$D$2:$D$20000,"TOTAL",_Data_Sectoral!$E$2:$E$20000,2028) -> 157.56863 | G42: =SUMIFS(_Data_Sectoral!$F$2:$F$20000,_Data_Sectoral!$A$2:$A$20000,"ES",_Data_Sectoral!$C$2:$C$20000,"buildings",_Data_Sectoral!$D$2:$D$20000,"TOTAL",_Data_Sectoral!$E$2:$E$20000,2029) -> 159.34183 | H42: =SUMIFS(_Data_Sectoral!$F$2:$F$20000,_Data_Sectoral!$A$2:$A$20000,"ES",_Data_Sectoral!$C$2:$C$20000,"buildings",_Data_Sectoral!$D$2:$D$20000,"TOTAL",_Data_Sectoral!$E$2:$E$20000,2030) -> 161.23693 | I42: =SUMIFS(_Data_Sectoral!$F$2:$F$20000,_Data_Sectoral!$A$2:$A$20000,"ES",_Data_Sectoral!$C$2:$C$20000,"buildings",_Data_Sectoral!$D$2:$D$20000,"TOTAL",_Data_Sectoral!$E$2:$E$20000,2031) -> 162.61006 | J42: =SUMIFS(_Data_Sectoral!$F$2:$F$20000,_Data_Sectoral!$A$2:$A$20000,"ES",_Data_Sectoral!$C$2:$C$20000,"buildings",_Data_Sectoral!$D$2:$D$20000,"TOTAL",_Data_Sectoral!$E$2:$E$20000,2032) -> 164.20104 | K42: =SUMIFS(_Data_Sectoral!$F$2:$F$20000,_Data_Sectoral!$A$2:$A$20000,"ES",_Data_Sectoral!$C$2:$C$20000,"buildings",_Data_Sectoral!$D$2:$D$20000,"TOTAL",_Data_Sectoral!$E$2:$E$20000,2033) -> 165.81934 | L42: =SUMIFS(_Data_Sectoral!$F$2:$F$20000,_Data_Sectoral!$A$2:$A$20000,"ES",_Data_Sectoral!$C$2:$C$20000,"buildings",_Data_Sectoral!$D$2:$D$20000,"TOTAL",_Data_Sectoral!$E$2:$E$20000,2034) -> 167.53231 | M42: =SUMIFS(_Data_Sectoral!$F$2:$F$20000,_Data_Sectoral!$A$2:$A$20000,"ES",_Data_Sectoral!$C$2:$C$20000,"buildings",_Data_Sectoral!$D$2:$D$20000,"TOTAL",_Data_Sectoral!$E$2:$E$20000,2035) -> 169.24214 | N42: =SUMIFS(_Data_Sectoral!$F$2:$F$20000,_Data_Sectoral!$A$2:$A$20000,"ES",_Data_Sectoral!$C$2:$C$20000,"buildings",_Data_Sectoral!$D$2:$D$20000,"TOTAL",_Data_Sectoral!$E$2:$E$20000,2036) -> 170.94393 | O42: =SUMIFS(_Data_Sectoral!$F$2:$F$20000,_Data_Sectoral!$A$2:$A$20000,"ES",_Data_Sectoral!$C$2:$C$20000,"buildings",_Data_Sectoral!$D$2:$D$20000,"TOTAL",_Data_Sectoral!$E$2:$E$20000,2037) -> 172.57412 | P42: =SUMIFS(_Data_Sectoral!$F$2:$F$20000,_Data_Sectoral!$A$2:$A$20000,"ES",_Data_Sectoral!$C$2:$C$20000,"buildings",_Data_Sectoral!$D$2:$D$20000,"TOTAL",_Data_Sectoral!$E$2:$E$20000,2038) -> 174.1029 | Q42: =SUMIFS(_Data_Sectoral!$F$2:$F$20000,_Data_Sectoral!$A$2:$A$20000,"ES",_Data_Sectoral!$C$2:$C$20000,"buildings",_Data_Sectoral!$D$2:$D$20000,"TOTAL",_Data_Sectoral!$E$2:$E$20000,2039) -> 175.79483 | R42: =SUMIFS(_Data_Sectoral!$F$2:$F$20000,_Data_Sectoral!$A$2:$A$20000,"ES",_Data_Sectoral!$C$2:$C$20000,"buildings",_Data_Sectoral!$D$2:$D$20000,"TOTAL",_Data_Sectoral!$E$2:$E$20000,2040) -> 177.4369
A43: Industry | B43: =SUMIFS(_Data_Sectoral!$F$2:$F$20000,_Data_Sectoral!$A$2:$A$20000,"ES",_Data_Sectoral!$C$2:$C$20000,"industry",_Data_Sectoral!$D$2:$D$20000,"TOTAL",_Data_Sectoral!$E$2:$E$20000,2024) -> 78.418076 | C43: =SUMIFS(_Data_Sectoral!$F$2:$F$20000,_Data_Sectoral!$A$2:$A$20000,"ES",_Data_Sectoral!$C$2:$C$20000,"industry",_Data_Sectoral!$D$2:$D$20000,"TOTAL",_Data_Sectoral!$E$2:$E$20000,2025) -> 81.603227 | D43: =SUMIFS(_Data_Sectoral!$F$2:$F$20000,_Data_Sectoral!$A$2:$A$20000,"ES",_Data_Sectoral!$C$2:$C$20000,"industry",_Data_Sectoral!$D$2:$D$20000,"TOTAL",_Data_Sectoral!$E$2:$E$20000,2026) -> 82.978282 | E43: =SUMIFS(_Data_Sectoral!$F$2:$F$20000,_Data_Sectoral!$A$2:$A$20000,"ES",_Data_Sectoral!$C$2:$C$20000,"industry",_Data_Sectoral!$D$2:$D$20000,"TOTAL",_Data_Sectoral!$E$2:$E$20000,2027) -> 83.440505 | F43: =SUMIFS(_Data_Sectoral!$F$2:$F$20000,_Data_Sectoral!$A$2:$A$20000,"ES",_Data_Sectoral!$C$2:$C$20000,"industry",_Data_Sectoral!$D$2:$D$20000,"TOTAL",_Data_Sectoral!$E$2:$E$20000,2028) -> 84.14865 | G43: =SUMIFS(_Data_Sectoral!$F$2:$F$20000,_Data_Sectoral!$A$2:$A$20000,"ES",_Data_Sectoral!$C$2:$C$20000,"industry",_Data_Sectoral!$D$2:$D$20000,"TOTAL",_Data_Sectoral!$E$2:$E$20000,2029) -> 83.913826 | H43: =SUMIFS(_Data_Sectoral!$F$2:$F$20000,_Data_Sectoral!$A$2:$A$20000,"ES",_Data_Sectoral!$C$2:$C$20000,"industry",_Data_Sectoral!$D$2:$D$20000,"TOTAL",_Data_Sectoral!$E$2:$E$20000,2030) -> 83.715042 | I43: =SUMIFS(_Data_Sectoral!$F$2:$F$20000,_Data_Sectoral!$A$2:$A$20000,"ES",_Data_Sectoral!$C$2:$C$20000,"industry",_Data_Sectoral!$D$2:$D$20000,"TOTAL",_Data_Sectoral!$E$2:$E$20000,2031) -> 83.515204 | J43: =SUMIFS(_Data_Sectoral!$F$2:$F$20000,_Data_Sectoral!$A$2:$A$20000,"ES",_Data_Sectoral!$C$2:$C$20000,"industry",_Data_Sectoral!$D$2:$D$20000,"TOTAL",_Data_Sectoral!$E$2:$E$20000,2032) -> 84.509543 | K43: =SUMIFS(_Data_Sectoral!$F$2:$F$20000,_Data_Sectoral!$A$2:$A$20000,"ES",_Data_Sectoral!$C$2:$C$20000,"industry",_Data_Sectoral!$D$2:$D$20000,"TOTAL",_Data_Sectoral!$E$2:$E$20000,2033) -> 86.019195 | L43: =SUMIFS(_Data_Sectoral!$F$2:$F$20000,_Data_Sectoral!$A$2:$A$20000,"ES",_Data_Sectoral!$C$2:$C$20000,"industry",_Data_Sectoral!$D$2:$D$20000,"TOTAL",_Data_Sectoral!$E$2:$E$20000,2034) -> 87.449185 | M43: =SUMIFS(_Data_Sectoral!$F$2:$F$20000,_Data_Sectoral!$A$2:$A$20000,"ES",_Data_Sectoral!$C$2:$C$20000,"industry",_Data_Sectoral!$D$2:$D$20000,"TOTAL",_Data_Sectoral!$E$2:$E$20000,2035) -> 88.944325 | N43: =SUMIFS(_Data_Sectoral!$F$2:$F$20000,_Data_Sectoral!$A$2:$A$20000,"ES",_Data_Sectoral!$C$2:$C$20000,"industry",_Data_Sectoral!$D$2:$D$20000,"TOTAL",_Data_Sectoral!$E$2:$E$20000,2036) -> 90.15338 | O43: =SUMIFS(_Data_Sectoral!$F$2:$F$20000,_Data_Sectoral!$A$2:$A$20000,"ES",_Data_Sectoral!$C$2:$C$20000,"industry",_Data_Sectoral!$D$2:$D$20000,"TOTAL",_Data_Sectoral!$E$2:$E$20000,2037) -> 91.311346 | P43: =SUMIFS(_Data_Sectoral!$F$2:$F$20000,_Data_Sectoral!$A$2:$A$20000,"ES",_Data_Sectoral!$C$2:$C$20000,"industry",_Data_Sectoral!$D$2:$D$20000,"TOTAL",_Data_Sectoral!$E$2:$E$20000,2038) -> 92.415186 | Q43: =SUMIFS(_Data_Sectoral!$F$2:$F$20000,_Data_Sectoral!$A$2:$A$20000,"ES",_Data_Sectoral!$C$2:$C$20000,"industry",_Data_Sectoral!$D$2:$D$20000,"TOTAL",_Data_Sectoral!$E$2:$E$20000,2039) -> 93.507723 | R43: =SUMIFS(_Data_Sectoral!$F$2:$F$20000,_Data_Sectoral!$A$2:$A$20000,"ES",_Data_Sectoral!$C$2:$C$20000,"industry",_Data_Sectoral!$D$2:$D$20000,"TOTAL",_Data_Sectoral!$E$2:$E$20000,2040) -> 94.47966
A44: Data Centers | B44: =SUMIFS(_Data_Sectoral!$F$2:$F$20000,_Data_Sectoral!$A$2:$A$20000,"ES",_Data_Sectoral!$C$2:$C$20000,"data_centers",_Data_Sectoral!$D$2:$D$20000,"TOTAL",_Data_Sectoral!$E$2:$E$20000,2024) -> 2.445135 | C44: =SUMIFS(_Data_Sectoral!$F$2:$F$20000,_Data_Sectoral!$A$2:$A$20000,"ES",_Data_Sectoral!$C$2:$C$20000,"data_centers",_Data_Sectoral!$D$2:$D$20000,"TOTAL",_Data_Sectoral!$E$2:$E$20000,2025) -> 3.0817361 | D44: =SUMIFS(_Data_Sectoral!$F$2:$F$20000,_Data_Sectoral!$A$2:$A$20000,"ES",_Data_Sectoral!$C$2:$C$20000,"data_centers",_Data_Sectoral!$D$2:$D$20000,"TOTAL",_Data_Sectoral!$E$2:$E$20000,2026) -> 4.5844232 | E44: =SUMIFS(_Data_Sectoral!$F$2:$F$20000,_Data_Sectoral!$A$2:$A$20000,"ES",_Data_Sectoral!$C$2:$C$20000,"data_centers",_Data_Sectoral!$D$2:$D$20000,"TOTAL",_Data_Sectoral!$E$2:$E$20000,2027) -> 6.932168 | F44: =SUMIFS(_Data_Sectoral!$F$2:$F$20000,_Data_Sectoral!$A$2:$A$20000,"ES",_Data_Sectoral!$C$2:$C$20000,"data_centers",_Data_Sectoral!$D$2:$D$20000,"TOTAL",_Data_Sectoral!$E$2:$E$20000,2028) -> 8.8934695 | G44: =SUMIFS(_Data_Sectoral!$F$2:$F$20000,_Data_Sectoral!$A$2:$A$20000,"ES",_Data_Sectoral!$C$2:$C$20000,"data_centers",_Data_Sectoral!$D$2:$D$20000,"TOTAL",_Data_Sectoral!$E$2:$E$20000,2029) -> 13.530136 | H44: =SUMIFS(_Data_Sectoral!$F$2:$F$20000,_Data_Sectoral!$A$2:$A$20000,"ES",_Data_Sectoral!$C$2:$C$20000,"data_centers",_Data_Sectoral!$D$2:$D$20000,"TOTAL",_Data_Sectoral!$E$2:$E$20000,2030) -> 16.911069 | I44: =SUMIFS(_Data_Sectoral!$F$2:$F$20000,_Data_Sectoral!$A$2:$A$20000,"ES",_Data_Sectoral!$C$2:$C$20000,"data_centers",_Data_Sectoral!$D$2:$D$20000,"TOTAL",_Data_Sectoral!$E$2:$E$20000,2031) -> 19.186788 | J44: =SUMIFS(_Data_Sectoral!$F$2:$F$20000,_Data_Sectoral!$A$2:$A$20000,"ES",_Data_Sectoral!$C$2:$C$20000,"data_centers",_Data_Sectoral!$D$2:$D$20000,"TOTAL",_Data_Sectoral!$E$2:$E$20000,2032) -> 21.459974 | K44: =SUMIFS(_Data_Sectoral!$F$2:$F$20000,_Data_Sectoral!$A$2:$A$20000,"ES",_Data_Sectoral!$C$2:$C$20000,"data_centers",_Data_Sectoral!$D$2:$D$20000,"TOTAL",_Data_Sectoral!$E$2:$E$20000,2033) -> 23.724717 | L44: =SUMIFS(_Data_Sectoral!$F$2:$F$20000,_Data_Sectoral!$A$2:$A$20000,"ES",_Data_Sectoral!$C$2:$C$20000,"data_centers",_Data_Sectoral!$D$2:$D$20000,"TOTAL",_Data_Sectoral!$E$2:$E$20000,2034) -> 25.921389 | M44: =SUMIFS(_Data_Sectoral!$F$2:$F$20000,_Data_Sectoral!$A$2:$A$20000,"ES",_Data_Sectoral!$C$2:$C$20000,"data_centers",_Data_Sectoral!$D$2:$D$20000,"TOTAL",_Data_Sectoral!$E$2:$E$20000,2035) -> 27.985941 | N44: =SUMIFS(_Data_Sectoral!$F$2:$F$20000,_Data_Sectoral!$A$2:$A$20000,"ES",_Data_Sectoral!$C$2:$C$20000,"data_centers",_Data_Sectoral!$D$2:$D$20000,"TOTAL",_Data_Sectoral!$E$2:$E$20000,2036) -> 29.852696 | O44: =SUMIFS(_Data_Sectoral!$F$2:$F$20000,_Data_Sectoral!$A$2:$A$20000,"ES",_Data_Sectoral!$C$2:$C$20000,"data_centers",_Data_Sectoral!$D$2:$D$20000,"TOTAL",_Data_Sectoral!$E$2:$E$20000,2037) -> 31.457577 | P44: =SUMIFS(_Data_Sectoral!$F$2:$F$20000,_Data_Sectoral!$A$2:$A$20000,"ES",_Data_Sectoral!$C$2:$C$20000,"data_centers",_Data_Sectoral!$D$2:$D$20000,"TOTAL",_Data_Sectoral!$E$2:$E$20000,2038) -> 32.741571 | Q44: =SUMIFS(_Data_Sectoral!$F$2:$F$20000,_Data_Sectoral!$A$2:$A$20000,"ES",_Data_Sectoral!$C$2:$C$20000,"data_centers",_Data_Sectoral!$D$2:$D$20000,"TOTAL",_Data_Sectoral!$E$2:$E$20000,2039) -> 33.654187 | R44: =SUMIFS(_Data_Sectoral!$F$2:$F$20000,_Data_Sectoral!$A$2:$A$20000,"ES",_Data_Sectoral!$C$2:$C$20000,"data_centers",_Data_Sectoral!$D$2:$D$20000,"TOTAL",_Data_Sectoral!$E$2:$E$20000,2040) -> 34.156644
A45: Hydrogen | B45: =SUMIFS(_Data_Sectoral!$F$2:$F$20000,_Data_Sectoral!$A$2:$A$20000,"ES",_Data_Sectoral!$C$2:$C$20000,"hydrogen",_Data_Sectoral!$D$2:$D$20000,"TOTAL",_Data_Sectoral!$E$2:$E$20000,2024) -> 0.105 | C45: =SUMIFS(_Data_Sectoral!$F$2:$F$20000,_Data_Sectoral!$A$2:$A$20000,"ES",_Data_Sectoral!$C$2:$C$20000,"hydrogen",_Data_Sectoral!$D$2:$D$20000,"TOTAL",_Data_Sectoral!$E$2:$E$20000,2025) -> 0.115 | D45: =SUMIFS(_Data_Sectoral!$F$2:$F$20000,_Data_Sectoral!$A$2:$A$20000,"ES",_Data_Sectoral!$C$2:$C$20000,"hydrogen",_Data_Sectoral!$D$2:$D$20000,"TOTAL",_Data_Sectoral!$E$2:$E$20000,2026) -> 1.875025 | E45: =SUMIFS(_Data_Sectoral!$F$2:$F$20000,_Data_Sectoral!$A$2:$A$20000,"ES",_Data_Sectoral!$C$2:$C$20000,"hydrogen",_Data_Sectoral!$D$2:$D$20000,"TOTAL",_Data_Sectoral!$E$2:$E$20000,2027) -> 3.63505 | F45: =SUMIFS(_Data_Sectoral!$F$2:$F$20000,_Data_Sectoral!$A$2:$A$20000,"ES",_Data_Sectoral!$C$2:$C$20000,"hydrogen",_Data_Sectoral!$D$2:$D$20000,"TOTAL",_Data_Sectoral!$E$2:$E$20000,2028) -> 5.356915 | G45: =SUMIFS(_Data_Sectoral!$F$2:$F$20000,_Data_Sectoral!$A$2:$A$20000,"ES",_Data_Sectoral!$C$2:$C$20000,"hydrogen",_Data_Sectoral!$D$2:$D$20000,"TOTAL",_Data_Sectoral!$E$2:$E$20000,2029) -> 7.652736 | H45: =SUMIFS(_Data_Sectoral!$F$2:$F$20000,_Data_Sectoral!$A$2:$A$20000,"ES",_Data_Sectoral!$C$2:$C$20000,"hydrogen",_Data_Sectoral!$D$2:$D$20000,"TOTAL",_Data_Sectoral!$E$2:$E$20000,2030) -> 8.00226 | I45: =SUMIFS(_Data_Sectoral!$F$2:$F$20000,_Data_Sectoral!$A$2:$A$20000,"ES",_Data_Sectoral!$C$2:$C$20000,"hydrogen",_Data_Sectoral!$D$2:$D$20000,"TOTAL",_Data_Sectoral!$E$2:$E$20000,2031) -> 9.616903 | J45: =SUMIFS(_Data_Sectoral!$F$2:$F$20000,_Data_Sectoral!$A$2:$A$20000,"ES",_Data_Sectoral!$C$2:$C$20000,"hydrogen",_Data_Sectoral!$D$2:$D$20000,"TOTAL",_Data_Sectoral!$E$2:$E$20000,2032) -> 11.429435 | K45: =SUMIFS(_Data_Sectoral!$F$2:$F$20000,_Data_Sectoral!$A$2:$A$20000,"ES",_Data_Sectoral!$C$2:$C$20000,"hydrogen",_Data_Sectoral!$D$2:$D$20000,"TOTAL",_Data_Sectoral!$E$2:$E$20000,2033) -> 13.535251 | L45: =SUMIFS(_Data_Sectoral!$F$2:$F$20000,_Data_Sectoral!$A$2:$A$20000,"ES",_Data_Sectoral!$C$2:$C$20000,"hydrogen",_Data_Sectoral!$D$2:$D$20000,"TOTAL",_Data_Sectoral!$E$2:$E$20000,2034) -> 15.768788 | M45: =SUMIFS(_Data_Sectoral!$F$2:$F$20000,_Data_Sectoral!$A$2:$A$20000,"ES",_Data_Sectoral!$C$2:$C$20000,"hydrogen",_Data_Sectoral!$D$2:$D$20000,"TOTAL",_Data_Sectoral!$E$2:$E$20000,2035) -> 18.1332 | N45: =SUMIFS(_Data_Sectoral!$F$2:$F$20000,_Data_Sectoral!$A$2:$A$20000,"ES",_Data_Sectoral!$C$2:$C$20000,"hydrogen",_Data_Sectoral!$D$2:$D$20000,"TOTAL",_Data_Sectoral!$E$2:$E$20000,2036) -> 20.63164 | O45: =SUMIFS(_Data_Sectoral!$F$2:$F$20000,_Data_Sectoral!$A$2:$A$20000,"ES",_Data_Sectoral!$C$2:$C$20000,"hydrogen",_Data_Sectoral!$D$2:$D$20000,"TOTAL",_Data_Sectoral!$E$2:$E$20000,2037) -> 22.620948 | P45: =SUMIFS(_Data_Sectoral!$F$2:$F$20000,_Data_Sectoral!$A$2:$A$20000,"ES",_Data_Sectoral!$C$2:$C$20000,"hydrogen",_Data_Sectoral!$D$2:$D$20000,"TOTAL",_Data_Sectoral!$E$2:$E$20000,2038) -> 24.707668 | Q45: =SUMIFS(_Data_Sectoral!$F$2:$F$20000,_Data_Sectoral!$A$2:$A$20000,"ES",_Data_Sectoral!$C$2:$C$20000,"hydrogen",_Data_Sectoral!$D$2:$D$20000,"TOTAL",_Data_Sectoral!$E$2:$E$20000,2039) -> 26.893901 | R45: =SUMIFS(_Data_Sectoral!$F$2:$F$20000,_Data_Sectoral!$A$2:$A$20000,"ES",_Data_Sectoral!$C$2:$C$20000,"hydrogen",_Data_Sectoral!$D$2:$D$20000,"TOTAL",_Data_Sectoral!$E$2:$E$20000,2040) -> 28.47
A46: Total | B46: =SUM(B41:B45) -> 236.61937 | C46: =SUM(C41:C45) -> 242.82028 | D46: =SUM(D41:D45) -> 249.95805 | E46: =SUM(E41:E45) -> 257.09245 | F46: =SUM(F41:F45) -> 264.50412 | G46: =SUM(G41:G45) -> 274.61853 | H46: =SUM(H41:H45) -> 281.98989 | I46: =SUM(I41:I45) -> 289.13542 | ... R46: =SUM(R41:R45) -> 375.69468
A48: United Kingdom
A49: Sector | B49: 2024 | C49: 2025 | D49: 2026 | E49: 2027 | F49: 2028 | G49: 2029 | H49: 2030 | I49: 2031 | J49: 2032 | K49: 2033 | L49: 2034 | M49: 2035 | N49: 2036 | O49: 2037 | P49: 2038 | Q49: 2039 | R49: 2040
A50: Transport | B50: =SUMIFS(_Data_Sectoral!$F$2:$F$20000,_Data_Sectoral!$A$2:$A$20000,"UK",_Data_Sectoral!$C$2:$C$20000,"transport",_Data_Sectoral!$D$2:$D$20000,"TOTAL",_Data_Sectoral!$E$2:$E$20000,2024) -> 9.9063747 | C50: =SUMIFS(_Data_Sectoral!$F$2:$F$20000,_Data_Sectoral!$A$2:$A$20000,"UK",_Data_Sectoral!$C$2:$C$20000,"transport",_Data_Sectoral!$D$2:$D$20000,"TOTAL",_Data_Sectoral!$E$2:$E$20000,2025) -> 12.01455 | D50: =SUMIFS(_Data_Sectoral!$F$2:$F$20000,_Data_Sectoral!$A$2:$A$20000,"UK",_Data_Sectoral!$C$2:$C$20000,"transport",_Data_Sectoral!$D$2:$D$20000,"TOTAL",_Data_Sectoral!$E$2:$E$20000,2026) -> 14.531051 | E50: =SUMIFS(_Data_Sectoral!$F$2:$F$20000,_Data_Sectoral!$A$2:$A$20000,"UK",_Data_Sectoral!$C$2:$C$20000,"transport",_Data_Sectoral!$D$2:$D$20000,"TOTAL",_Data_Sectoral!$E$2:$E$20000,2027) -> 17.737602 | F50: =SUMIFS(_Data_Sectoral!$F$2:$F$20000,_Data_Sectoral!$A$2:$A$20000,"UK",_Data_Sectoral!$C$2:$C$20000,"transport",_Data_Sectoral!$D$2:$D$20000,"TOTAL",_Data_Sectoral!$E$2:$E$20000,2028) -> 22.015085 | G50: =SUMIFS(_Data_Sectoral!$F$2:$F$20000,_Data_Sectoral!$A$2:$A$20000,"UK",_Data_Sectoral!$C$2:$C$20000,"transport",_Data_Sectoral!$D$2:$D$20000,"TOTAL",_Data_Sectoral!$E$2:$E$20000,2029) -> 27.040353 | H50: =SUMIFS(_Data_Sectoral!$F$2:$F$20000,_Data_Sectoral!$A$2:$A$20000,"UK",_Data_Sectoral!$C$2:$C$20000,"transport",_Data_Sectoral!$D$2:$D$20000,"TOTAL",_Data_Sectoral!$E$2:$E$20000,2030) -> 32.727518 | I50: =SUMIFS(_Data_Sectoral!$F$2:$F$20000,_Data_Sectoral!$A$2:$A$20000,"UK",_Data_Sectoral!$C$2:$C$20000,"transport",_Data_Sectoral!$D$2:$D$20000,"TOTAL",_Data_Sectoral!$E$2:$E$20000,2031) -> 38.991953 | J50: =SUMIFS(_Data_Sectoral!$F$2:$F$20000,_Data_Sectoral!$A$2:$A$20000,"UK",_Data_Sectoral!$C$2:$C$20000,"transport",_Data_Sectoral!$D$2:$D$20000,"TOTAL",_Data_Sectoral!$E$2:$E$20000,2032) -> 45.7329 | K50: =SUMIFS(_Data_Sectoral!$F$2:$F$20000,_Data_Sectoral!$A$2:$A$20000,"UK",_Data_Sectoral!$C$2:$C$20000,"transport",_Data_Sectoral!$D$2:$D$20000,"TOTAL",_Data_Sectoral!$E$2:$E$20000,2033) -> 53.250046 | L50: =SUMIFS(_Data_Sectoral!$F$2:$F$20000,_Data_Sectoral!$A$2:$A$20000,"UK",_Data_Sectoral!$C$2:$C$20000,"transport",_Data_Sectoral!$D$2:$D$20000,"TOTAL",_Data_Sectoral!$E$2:$E$20000,2034) -> 61.803493 | M50: =SUMIFS(_Data_Sectoral!$F$2:$F$20000,_Data_Sectoral!$A$2:$A$20000,"UK",_Data_Sectoral!$C$2:$C$20000,"transport",_Data_Sectoral!$D$2:$D$20000,"TOTAL",_Data_Sectoral!$E$2:$E$20000,2035) -> 70.829233 | N50: =SUMIFS(_Data_Sectoral!$F$2:$F$20000,_Data_Sectoral!$A$2:$A$20000,"UK",_Data_Sectoral!$C$2:$C$20000,"transport",_Data_Sectoral!$D$2:$D$20000,"TOTAL",_Data_Sectoral!$E$2:$E$20000,2036) -> 80.140562 | O50: =SUMIFS(_Data_Sectoral!$F$2:$F$20000,_Data_Sectoral!$A$2:$A$20000,"UK",_Data_Sectoral!$C$2:$C$20000,"transport",_Data_Sectoral!$D$2:$D$20000,"TOTAL",_Data_Sectoral!$E$2:$E$20000,2037) -> 89.592986 | P50: =SUMIFS(_Data_Sectoral!$F$2:$F$20000,_Data_Sectoral!$A$2:$A$20000,"UK",_Data_Sectoral!$C$2:$C$20000,"transport",_Data_Sectoral!$D$2:$D$20000,"TOTAL",_Data_Sectoral!$E$2:$E$20000,2038) -> 98.674234 | Q50: =SUMIFS(_Data_Sectoral!$F$2:$F$20000,_Data_Sectoral!$A$2:$A$20000,"UK",_Data_Sectoral!$C$2:$C$20000,"transport",_Data_Sectoral!$D$2:$D$20000,"TOTAL",_Data_Sectoral!$E$2:$E$20000,2039) -> 107.78703 | R50: =SUMIFS(_Data_Sectoral!$F$2:$F$20000,_Data_Sectoral!$A$2:$A$20000,"UK",_Data_Sectoral!$C$2:$C$20000,"transport",_Data_Sectoral!$D$2:$D$20000,"TOTAL",_Data_Sectoral!$E$2:$E$20000,2040) -> 117.01608
A51: Buildings | B51: =SUMIFS(_Data_Sectoral!$F$2:$F$20000,_Data_Sectoral!$A$2:$A$20000,"UK",_Data_Sectoral!$C$2:$C$20000,"buildings",_Data_Sectoral!$D$2:$D$20000,"TOTAL",_Data_Sectoral!$E$2:$E$20000,2024) -> 193.70456 | C51: =SUMIFS(_Data_Sectoral!$F$2:$F$20000,_Data_Sectoral!$A$2:$A$20000,"UK",_Data_Sectoral!$C$2:$C$20000,"buildings",_Data_Sectoral!$D$2:$D$20000,"TOTAL",_Data_Sectoral!$E$2:$E$20000,2025) -> 194.54815 | D51: =SUMIFS(_Data_Sectoral!$F$2:$F$20000,_Data_Sectoral!$A$2:$A$20000,"UK",_Data_Sectoral!$C$2:$C$20000,"buildings",_Data_Sectoral!$D$2:$D$20000,"TOTAL",_Data_Sectoral!$E$2:$E$20000,2026) -> 195.28176 | E51: =SUMIFS(_Data_Sectoral!$F$2:$F$20000,_Data_Sectoral!$A$2:$A$20000,"UK",_Data_Sectoral!$C$2:$C$20000,"buildings",_Data_Sectoral!$D$2:$D$20000,"TOTAL",_Data_Sectoral!$E$2:$E$20000,2027) -> 196.07141 | F51: =SUMIFS(_Data_Sectoral!$F$2:$F$20000,_Data_Sectoral!$A$2:$A$20000,"UK",_Data_Sectoral!$C$2:$C$20000,"buildings",_Data_Sectoral!$D$2:$D$20000,"TOTAL",_Data_Sectoral!$E$2:$E$20000,2028) -> 197.05729 | G51: =SUMIFS(_Data_Sectoral!$F$2:$F$20000,_Data_Sectoral!$A$2:$A$20000,"UK",_Data_Sectoral!$C$2:$C$20000,"buildings",_Data_Sectoral!$D$2:$D$20000,"TOTAL",_Data_Sectoral!$E$2:$E$20000,2029) -> 198.1853 | H51: =SUMIFS(_Data_Sectoral!$F$2:$F$20000,_Data_Sectoral!$A$2:$A$20000,"UK",_Data_Sectoral!$C$2:$C$20000,"buildings",_Data_Sectoral!$D$2:$D$20000,"TOTAL",_Data_Sectoral!$E$2:$E$20000,2030) -> 199.40462 | I51: =SUMIFS(_Data_Sectoral!$F$2:$F$20000,_Data_Sectoral!$A$2:$A$20000,"UK",_Data_Sectoral!$C$2:$C$20000,"buildings",_Data_Sectoral!$D$2:$D$20000,"TOTAL",_Data_Sectoral!$E$2:$E$20000,2031) -> 200.63347 | J51: =SUMIFS(_Data_Sectoral!$F$2:$F$20000,_Data_Sectoral!$A$2:$A$20000,"UK",_Data_Sectoral!$C$2:$C$20000,"buildings",_Data_Sectoral!$D$2:$D$20000,"TOTAL",_Data_Sectoral!$E$2:$E$20000,2032) -> 201.87661 | K51: =SUMIFS(_Data_Sectoral!$F$2:$F$20000,_Data_Sectoral!$A$2:$A$20000,"UK",_Data_Sectoral!$C$2:$C$20000,"buildings",_Data_Sectoral!$D$2:$D$20000,"TOTAL",_Data_Sectoral!$E$2:$E$20000,2033) -> 203.14077 | L51: =SUMIFS(_Data_Sectoral!$F$2:$F$20000,_Data_Sectoral!$A$2:$A$20000,"UK",_Data_Sectoral!$C$2:$C$20000,"buildings",_Data_Sectoral!$D$2:$D$20000,"TOTAL",_Data_Sectoral!$E$2:$E$20000,2034) -> 204.46274 | M51: =SUMIFS(_Data_Sectoral!$F$2:$F$20000,_Data_Sectoral!$A$2:$A$20000,"UK",_Data_Sectoral!$C$2:$C$20000,"buildings",_Data_Sectoral!$D$2:$D$20000,"TOTAL",_Data_Sectoral!$E$2:$E$20000,2035) -> 205.74736 | N51: =SUMIFS(_Data_Sectoral!$F$2:$F$20000,_Data_Sectoral!$A$2:$A$20000,"UK",_Data_Sectoral!$C$2:$C$20000,"buildings",_Data_Sectoral!$D$2:$D$20000,"TOTAL",_Data_Sectoral!$E$2:$E$20000,2036) -> 207.04306 | O51: =SUMIFS(_Data_Sectoral!$F$2:$F$20000,_Data_Sectoral!$A$2:$A$20000,"UK",_Data_Sectoral!$C$2:$C$20000,"buildings",_Data_Sectoral!$D$2:$D$20000,"TOTAL",_Data_Sectoral!$E$2:$E$20000,2037) -> 208.12257 | P51: =SUMIFS(_Data_Sectoral!$F$2:$F$20000,_Data_Sectoral!$A$2:$A$20000,"UK",_Data_Sectoral!$C$2:$C$20000,"buildings",_Data_Sectoral!$D$2:$D$20000,"TOTAL",_Data_Sectoral!$E$2:$E$20000,2038) -> 209.27809 | Q51: =SUMIFS(_Data_Sectoral!$F$2:$F$20000,_Data_Sectoral!$A$2:$A$20000,"UK",_Data_Sectoral!$C$2:$C$20000,"buildings",_Data_Sectoral!$D$2:$D$20000,"TOTAL",_Data_Sectoral!$E$2:$E$20000,2039) -> 210.47046 | R51: =SUMIFS(_Data_Sectoral!$F$2:$F$20000,_Data_Sectoral!$A$2:$A$20000,"UK",_Data_Sectoral!$C$2:$C$20000,"buildings",_Data_Sectoral!$D$2:$D$20000,"TOTAL",_Data_Sectoral!$E$2:$E$20000,2040) -> 211.65642
A52: Industry | B52: =SUMIFS(_Data_Sectoral!$F$2:$F$20000,_Data_Sectoral!$A$2:$A$20000,"UK",_Data_Sectoral!$C$2:$C$20000,"industry",_Data_Sectoral!$D$2:$D$20000,"TOTAL",_Data_Sectoral!$E$2:$E$20000,2024) -> 71.031063 | C52: =SUMIFS(_Data_Sectoral!$F$2:$F$20000,_Data_Sectoral!$A$2:$A$20000,"UK",_Data_Sectoral!$C$2:$C$20000,"industry",_Data_Sectoral!$D$2:$D$20000,"TOTAL",_Data_Sectoral!$E$2:$E$20000,2025) -> 71.778513 | D52: =SUMIFS(_Data_Sectoral!$F$2:$F$20000,_Data_Sectoral!$A$2:$A$20000,"UK",_Data_Sectoral!$C$2:$C$20000,"industry",_Data_Sectoral!$D$2:$D$20000,"TOTAL",_Data_Sectoral!$E$2:$E$20000,2026) -> 72.005045 | E52: =SUMIFS(_Data_Sectoral!$F$2:$F$20000,_Data_Sectoral!$A$2:$A$20000,"UK",_Data_Sectoral!$C$2:$C$20000,"industry",_Data_Sectoral!$D$2:$D$20000,"TOTAL",_Data_Sectoral!$E$2:$E$20000,2027) -> 72.535948 | F52: =SUMIFS(_Data_Sectoral!$F$2:$F$20000,_Data_Sectoral!$A$2:$A$20000,"UK",_Data_Sectoral!$C$2:$C$20000,"industry",_Data_Sectoral!$D$2:$D$20000,"TOTAL",_Data_Sectoral!$E$2:$E$20000,2028) -> 73.169224 | G52: =SUMIFS(_Data_Sectoral!$F$2:$F$20000,_Data_Sectoral!$A$2:$A$20000,"UK",_Data_Sectoral!$C$2:$C$20000,"industry",_Data_Sectoral!$D$2:$D$20000,"TOTAL",_Data_Sectoral!$E$2:$E$20000,2029) -> 75.217122 | H52: =SUMIFS(_Data_Sectoral!$F$2:$F$20000,_Data_Sectoral!$A$2:$A$20000,"UK",_Data_Sectoral!$C$2:$C$20000,"industry",_Data_Sectoral!$D$2:$D$20000,"TOTAL",_Data_Sectoral!$E$2:$E$20000,2030) -> 76.190706 | I52: =SUMIFS(_Data_Sectoral!$F$2:$F$20000,_Data_Sectoral!$A$2:$A$20000,"UK",_Data_Sectoral!$C$2:$C$20000,"industry",_Data_Sectoral!$D$2:$D$20000,"TOTAL",_Data_Sectoral!$E$2:$E$20000,2031) -> 77.554363 | J52: =SUMIFS(_Data_Sectoral!$F$2:$F$20000,_Data_Sectoral!$A$2:$A$20000,"UK",_Data_Sectoral!$C$2:$C$20000,"industry",_Data_Sectoral!$D$2:$D$20000,"TOTAL",_Data_Sectoral!$E$2:$E$20000,2032) -> 79.077419 | K52: =SUMIFS(_Data_Sectoral!$F$2:$F$20000,_Data_Sectoral!$A$2:$A$20000,"UK",_Data_Sectoral!$C$2:$C$20000,"industry",_Data_Sectoral!$D$2:$D$20000,"TOTAL",_Data_Sectoral!$E$2:$E$20000,2033) -> 80.849957 | L52: =SUMIFS(_Data_Sectoral!$F$2:$F$20000,_Data_Sectoral!$A$2:$A$20000,"UK",_Data_Sectoral!$C$2:$C$20000,"industry",_Data_Sectoral!$D$2:$D$20000,"TOTAL",_Data_Sectoral!$E$2:$E$20000,2034) -> 82.542819 | M52: =SUMIFS(_Data_Sectoral!$F$2:$F$20000,_Data_Sectoral!$A$2:$A$20000,"UK",_Data_Sectoral!$C$2:$C$20000,"industry",_Data_Sectoral!$D$2:$D$20000,"TOTAL",_Data_Sectoral!$E$2:$E$20000,2035) -> 84.25319 | N52: =SUMIFS(_Data_Sectoral!$F$2:$F$20000,_Data_Sectoral!$A$2:$A$20000,"UK",_Data_Sectoral!$C$2:$C$20000,"industry",_Data_Sectoral!$D$2:$D$20000,"TOTAL",_Data_Sectoral!$E$2:$E$20000,2036) -> 86.174675 | O52: =SUMIFS(_Data_Sectoral!$F$2:$F$20000,_Data_Sectoral!$A$2:$A$20000,"UK",_Data_Sectoral!$C$2:$C$20000,"industry",_Data_Sectoral!$D$2:$D$20000,"TOTAL",_Data_Sectoral!$E$2:$E$20000,2037) -> 87.89565 | P52: =SUMIFS(_Data_Sectoral!$F$2:$F$20000,_Data_Sectoral!$A$2:$A$20000,"UK",_Data_Sectoral!$C$2:$C$20000,"industry",_Data_Sectoral!$D$2:$D$20000,"TOTAL",_Data_Sectoral!$E$2:$E$20000,2038) -> 89.566931 | Q52: =SUMIFS(_Data_Sectoral!$F$2:$F$20000,_Data_Sectoral!$A$2:$A$20000,"UK",_Data_Sectoral!$C$2:$C$20000,"industry",_Data_Sectoral!$D$2:$D$20000,"TOTAL",_Data_Sectoral!$E$2:$E$20000,2039) -> 91.075241 | R52: =SUMIFS(_Data_Sectoral!$F$2:$F$20000,_Data_Sectoral!$A$2:$A$20000,"UK",_Data_Sectoral!$C$2:$C$20000,"industry",_Data_Sectoral!$D$2:$D$20000,"TOTAL",_Data_Sectoral!$E$2:$E$20000,2040) -> 93.322209
A53: Data Centers | B53: =SUMIFS(_Data_Sectoral!$F$2:$F$20000,_Data_Sectoral!$A$2:$A$20000,"UK",_Data_Sectoral!$C$2:$C$20000,"data_centers",_Data_Sectoral!$D$2:$D$20000,"TOTAL",_Data_Sectoral!$E$2:$E$20000,2024) -> 12.95385 | C53: =SUMIFS(_Data_Sectoral!$F$2:$F$20000,_Data_Sectoral!$A$2:$A$20000,"UK",_Data_Sectoral!$C$2:$C$20000,"data_centers",_Data_Sectoral!$D$2:$D$20000,"TOTAL",_Data_Sectoral!$E$2:$E$20000,2025) -> 14.046508 | D53: =SUMIFS(_Data_Sectoral!$F$2:$F$20000,_Data_Sectoral!$A$2:$A$20000,"UK",_Data_Sectoral!$C$2:$C$20000,"data_centers",_Data_Sectoral!$D$2:$D$20000,"TOTAL",_Data_Sectoral!$E$2:$E$20000,2026) -> 15.611082 | E53: =SUMIFS(_Data_Sectoral!$F$2:$F$20000,_Data_Sectoral!$A$2:$A$20000,"UK",_Data_Sectoral!$C$2:$C$20000,"data_centers",_Data_Sectoral!$D$2:$D$20000,"TOTAL",_Data_Sectoral!$E$2:$E$20000,2027) -> 17.387785 | F53: =SUMIFS(_Data_Sectoral!$F$2:$F$20000,_Data_Sectoral!$A$2:$A$20000,"UK",_Data_Sectoral!$C$2:$C$20000,"data_centers",_Data_Sectoral!$D$2:$D$20000,"TOTAL",_Data_Sectoral!$E$2:$E$20000,2028) -> 19.035491 | G53: =SUMIFS(_Data_Sectoral!$F$2:$F$20000,_Data_Sectoral!$A$2:$A$20000,"UK",_Data_Sectoral!$C$2:$C$20000,"data_centers",_Data_Sectoral!$D$2:$D$20000,"TOTAL",_Data_Sectoral!$E$2:$E$20000,2029) -> 20.943052 | H53: =SUMIFS(_Data_Sectoral!$F$2:$F$20000,_Data_Sectoral!$A$2:$A$20000,"UK",_Data_Sectoral!$C$2:$C$20000,"data_centers",_Data_Sectoral!$D$2:$D$20000,"TOTAL",_Data_Sectoral!$E$2:$E$20000,2030) -> 23.036861 | I53: =SUMIFS(_Data_Sectoral!$F$2:$F$20000,_Data_Sectoral!$A$2:$A$20000,"UK",_Data_Sectoral!$C$2:$C$20000,"data_centers",_Data_Sectoral!$D$2:$D$20000,"TOTAL",_Data_Sectoral!$E$2:$E$20000,2031) -> 25.131847 | J53: =SUMIFS(_Data_Sectoral!$F$2:$F$20000,_Data_Sectoral!$A$2:$A$20000,"UK",_Data_Sectoral!$C$2:$C$20000,"data_centers",_Data_Sectoral!$D$2:$D$20000,"TOTAL",_Data_Sectoral!$E$2:$E$20000,2032) -> 28.109385 | K53: =SUMIFS(_Data_Sectoral!$F$2:$F$20000,_Data_Sectoral!$A$2:$A$20000,"UK",_Data_Sectoral!$C$2:$C$20000,"data_centers",_Data_Sectoral!$D$2:$D$20000,"TOTAL",_Data_Sectoral!$E$2:$E$20000,2033) -> 31.075862 | L53: =SUMIFS(_Data_Sectoral!$F$2:$F$20000,_Data_Sectoral!$A$2:$A$20000,"UK",_Data_Sectoral!$C$2:$C$20000,"data_centers",_Data_Sectoral!$D$2:$D$20000,"TOTAL",_Data_Sectoral!$E$2:$E$20000,2034) -> 33.953176 | M53: =SUMIFS(_Data_Sectoral!$F$2:$F$20000,_Data_Sectoral!$A$2:$A$20000,"UK",_Data_Sectoral!$C$2:$C$20000,"data_centers",_Data_Sectoral!$D$2:$D$20000,"TOTAL",_Data_Sectoral!$E$2:$E$20000,2035) -> 36.657433 | N53: =SUMIFS(_Data_Sectoral!$F$2:$F$20000,_Data_Sectoral!$A$2:$A$20000,"UK",_Data_Sectoral!$C$2:$C$20000,"data_centers",_Data_Sectoral!$D$2:$D$20000,"TOTAL",_Data_Sectoral!$E$2:$E$20000,2036) -> 39.102607 | O53: =SUMIFS(_Data_Sectoral!$F$2:$F$20000,_Data_Sectoral!$A$2:$A$20000,"UK",_Data_Sectoral!$C$2:$C$20000,"data_centers",_Data_Sectoral!$D$2:$D$20000,"TOTAL",_Data_Sectoral!$E$2:$E$20000,2037) -> 41.204763 | P53: =SUMIFS(_Data_Sectoral!$F$2:$F$20000,_Data_Sectoral!$A$2:$A$20000,"UK",_Data_Sectoral!$C$2:$C$20000,"data_centers",_Data_Sectoral!$D$2:$D$20000,"TOTAL",_Data_Sectoral!$E$2:$E$20000,2038) -> 42.886604 | Q53: =SUMIFS(_Data_Sectoral!$F$2:$F$20000,_Data_Sectoral!$A$2:$A$20000,"UK",_Data_Sectoral!$C$2:$C$20000,"data_centers",_Data_Sectoral!$D$2:$D$20000,"TOTAL",_Data_Sectoral!$E$2:$E$20000,2039) -> 44.081996 | R53: =SUMIFS(_Data_Sectoral!$F$2:$F$20000,_Data_Sectoral!$A$2:$A$20000,"UK",_Data_Sectoral!$C$2:$C$20000,"data_centers",_Data_Sectoral!$D$2:$D$20000,"TOTAL",_Data_Sectoral!$E$2:$E$20000,2040) -> 44.74014
A54: Hydrogen | B54: =SUMIFS(_Data_Sectoral!$F$2:$F$20000,_Data_Sectoral!$A$2:$A$20000,"UK",_Data_Sectoral!$C$2:$C$20000,"hydrogen",_Data_Sectoral!$D$2:$D$20000,"TOTAL",_Data_Sectoral!$E$2:$E$20000,2024) -> 0.055 | C54: =SUMIFS(_Data_Sectoral!$F$2:$F$20000,_Data_Sectoral!$A$2:$A$20000,"UK",_Data_Sectoral!$C$2:$C$20000,"hydrogen",_Data_Sectoral!$D$2:$D$20000,"TOTAL",_Data_Sectoral!$E$2:$E$20000,2025) -> 0.07 | D54: =SUMIFS(_Data_Sectoral!$F$2:$F$20000,_Data_Sectoral!$A$2:$A$20000,"UK",_Data_Sectoral!$C$2:$C$20000,"hydrogen",_Data_Sectoral!$D$2:$D$20000,"TOTAL",_Data_Sectoral!$E$2:$E$20000,2026) -> 0.619204 | E54: =SUMIFS(_Data_Sectoral!$F$2:$F$20000,_Data_Sectoral!$A$2:$A$20000,"UK",_Data_Sectoral!$C$2:$C$20000,"hydrogen",_Data_Sectoral!$D$2:$D$20000,"TOTAL",_Data_Sectoral!$E$2:$E$20000,2027) -> 1.168409 | F54: =SUMIFS(_Data_Sectoral!$F$2:$F$20000,_Data_Sectoral!$A$2:$A$20000,"UK",_Data_Sectoral!$C$2:$C$20000,"hydrogen",_Data_Sectoral!$D$2:$D$20000,"TOTAL",_Data_Sectoral!$E$2:$E$20000,2028) -> 1.749197 | G54: =SUMIFS(_Data_Sectoral!$F$2:$F$20000,_Data_Sectoral!$A$2:$A$20000,"UK",_Data_Sectoral!$C$2:$C$20000,"hydrogen",_Data_Sectoral!$D$2:$D$20000,"TOTAL",_Data_Sectoral!$E$2:$E$20000,2029) -> 2.528136 | H54: =SUMIFS(_Data_Sectoral!$F$2:$F$20000,_Data_Sectoral!$A$2:$A$20000,"UK",_Data_Sectoral!$C$2:$C$20000,"hydrogen",_Data_Sectoral!$D$2:$D$20000,"TOTAL",_Data_Sectoral!$E$2:$E$20000,2030) -> 2.66742 | I54: =SUMIFS(_Data_Sectoral!$F$2:$F$20000,_Data_Sectoral!$A$2:$A$20000,"UK",_Data_Sectoral!$C$2:$C$20000,"hydrogen",_Data_Sectoral!$D$2:$D$20000,"TOTAL",_Data_Sectoral!$E$2:$E$20000,2031) -> 3.145716 | J54: =SUMIFS(_Data_Sectoral!$F$2:$F$20000,_Data_Sectoral!$A$2:$A$20000,"UK",_Data_Sectoral!$C$2:$C$20000,"hydrogen",_Data_Sectoral!$D$2:$D$20000,"TOTAL",_Data_Sectoral!$E$2:$E$20000,2032) -> 3.670002 | K54: =SUMIFS(_Data_Sectoral!$F$2:$F$20000,_Data_Sectoral!$A$2:$A$20000,"UK",_Data_Sectoral!$C$2:$C$20000,"hydrogen",_Data_Sectoral!$D$2:$D$20000,"TOTAL",_Data_Sectoral!$E$2:$E$20000,2033) -> 4.267872 | L54: =SUMIFS(_Data_Sectoral!$F$2:$F$20000,_Data_Sectoral!$A$2:$A$20000,"UK",_Data_Sectoral!$C$2:$C$20000,"hydrogen",_Data_Sectoral!$D$2:$D$20000,"TOTAL",_Data_Sectoral!$E$2:$E$20000,2034) -> 4.884138 | M54: =SUMIFS(_Data_Sectoral!$F$2:$F$20000,_Data_Sectoral!$A$2:$A$20000,"UK",_Data_Sectoral!$C$2:$C$20000,"hydrogen",_Data_Sectoral!$D$2:$D$20000,"TOTAL",_Data_Sectoral!$E$2:$E$20000,2035) -> 5.5188 | N54: =SUMIFS(_Data_Sectoral!$F$2:$F$20000,_Data_Sectoral!$A$2:$A$20000,"UK",_Data_Sectoral!$C$2:$C$20000,"hydrogen",_Data_Sectoral!$D$2:$D$20000,"TOTAL",_Data_Sectoral!$E$2:$E$20000,2036) -> 6.171858 | O54: =SUMIFS(_Data_Sectoral!$F$2:$F$20000,_Data_Sectoral!$A$2:$A$20000,"UK",_Data_Sectoral!$C$2:$C$20000,"hydrogen",_Data_Sectoral!$D$2:$D$20000,"TOTAL",_Data_Sectoral!$E$2:$E$20000,2037) -> 6.65322 | P54: =SUMIFS(_Data_Sectoral!$F$2:$F$20000,_Data_Sectoral!$A$2:$A$20000,"UK",_Data_Sectoral!$C$2:$C$20000,"hydrogen",_Data_Sectoral!$D$2:$D$20000,"TOTAL",_Data_Sectoral!$E$2:$E$20000,2038) -> 7.146846 | Q54: =SUMIFS(_Data_Sectoral!$F$2:$F$20000,_Data_Sectoral!$A$2:$A$20000,"UK",_Data_Sectoral!$C$2:$C$20000,"hydrogen",_Data_Sectoral!$D$2:$D$20000,"TOTAL",_Data_Sectoral!$E$2:$E$20000,2039) -> 7.652736 | R54: =SUMIFS(_Data_Sectoral!$F$2:$F$20000,_Data_Sectoral!$A$2:$A$20000,"UK",_Data_Sectoral!$C$2:$C$20000,"hydrogen",_Data_Sectoral!$D$2:$D$20000,"TOTAL",_Data_Sectoral!$E$2:$E$20000,2040) -> 7.9716
A55: Total | B55: =SUM(B50:B54) -> 287.65085 | C55: =SUM(C50:C54) -> 292.45772 | D55: =SUM(D50:D54) -> 298.04814 | E55: =SUM(E50:E54) -> 304.90116 | F55: =SUM(F50:F54) -> 313.02629 | G55: =SUM(G50:G54) -> 323.91396 | H55: =SUM(H50:H54) -> 334.02713 | I55: =SUM(I50:I54) -> 345.45735 | ... R55: =SUM(R50:R54) -> 474.70645
A57: Poland
A58: Sector | B58: 2024 | C58: 2025 | D58: 2026 | E58: 2027 | F58: 2028 | G58: 2029 | H58: 2030 | I58: 2031 | J58: 2032 | K58: 2033 | L58: 2034 | M58: 2035 | N58: 2036 | O58: 2037 | P58: 2038 | Q58: 2039 | R58: 2040
A59: Transport | B59: =SUMIFS(_Data_Sectoral!$F$2:$F$20000,_Data_Sectoral!$A$2:$A$20000,"PL",_Data_Sectoral!$C$2:$C$20000,"transport",_Data_Sectoral!$D$2:$D$20000,"TOTAL",_Data_Sectoral!$E$2:$E$20000,2024) -> 3.091057 | C59: =SUMIFS(_Data_Sectoral!$F$2:$F$20000,_Data_Sectoral!$A$2:$A$20000,"PL",_Data_Sectoral!$C$2:$C$20000,"transport",_Data_Sectoral!$D$2:$D$20000,"TOTAL",_Data_Sectoral!$E$2:$E$20000,2025) -> 3.2743579 | D59: =SUMIFS(_Data_Sectoral!$F$2:$F$20000,_Data_Sectoral!$A$2:$A$20000,"PL",_Data_Sectoral!$C$2:$C$20000,"transport",_Data_Sectoral!$D$2:$D$20000,"TOTAL",_Data_Sectoral!$E$2:$E$20000,2026) -> 3.5989662 | E59: =SUMIFS(_Data_Sectoral!$F$2:$F$20000,_Data_Sectoral!$A$2:$A$20000,"PL",_Data_Sectoral!$C$2:$C$20000,"transport",_Data_Sectoral!$D$2:$D$20000,"TOTAL",_Data_Sectoral!$E$2:$E$20000,2027) -> 4.0184778 | F59: =SUMIFS(_Data_Sectoral!$F$2:$F$20000,_Data_Sectoral!$A$2:$A$20000,"PL",_Data_Sectoral!$C$2:$C$20000,"transport",_Data_Sectoral!$D$2:$D$20000,"TOTAL",_Data_Sectoral!$E$2:$E$20000,2028) -> 4.5261543 | G59: =SUMIFS(_Data_Sectoral!$F$2:$F$20000,_Data_Sectoral!$A$2:$A$20000,"PL",_Data_Sectoral!$C$2:$C$20000,"transport",_Data_Sectoral!$D$2:$D$20000,"TOTAL",_Data_Sectoral!$E$2:$E$20000,2029) -> 5.0834974 | H59: =SUMIFS(_Data_Sectoral!$F$2:$F$20000,_Data_Sectoral!$A$2:$A$20000,"PL",_Data_Sectoral!$C$2:$C$20000,"transport",_Data_Sectoral!$D$2:$D$20000,"TOTAL",_Data_Sectoral!$E$2:$E$20000,2030) -> 5.7571575 | I59: =SUMIFS(_Data_Sectoral!$F$2:$F$20000,_Data_Sectoral!$A$2:$A$20000,"PL",_Data_Sectoral!$C$2:$C$20000,"transport",_Data_Sectoral!$D$2:$D$20000,"TOTAL",_Data_Sectoral!$E$2:$E$20000,2031) -> 6.4700232 | J59: =SUMIFS(_Data_Sectoral!$F$2:$F$20000,_Data_Sectoral!$A$2:$A$20000,"PL",_Data_Sectoral!$C$2:$C$20000,"transport",_Data_Sectoral!$D$2:$D$20000,"TOTAL",_Data_Sectoral!$E$2:$E$20000,2032) -> 7.2787539 | K59: =SUMIFS(_Data_Sectoral!$F$2:$F$20000,_Data_Sectoral!$A$2:$A$20000,"PL",_Data_Sectoral!$C$2:$C$20000,"transport",_Data_Sectoral!$D$2:$D$20000,"TOTAL",_Data_Sectoral!$E$2:$E$20000,2033) -> 8.1396474 | L59: =SUMIFS(_Data_Sectoral!$F$2:$F$20000,_Data_Sectoral!$A$2:$A$20000,"PL",_Data_Sectoral!$C$2:$C$20000,"transport",_Data_Sectoral!$D$2:$D$20000,"TOTAL",_Data_Sectoral!$E$2:$E$20000,2034) -> 9.1101648 | M59: =SUMIFS(_Data_Sectoral!$F$2:$F$20000,_Data_Sectoral!$A$2:$A$20000,"PL",_Data_Sectoral!$C$2:$C$20000,"transport",_Data_Sectoral!$D$2:$D$20000,"TOTAL",_Data_Sectoral!$E$2:$E$20000,2035) -> 10.167224 | N59: =SUMIFS(_Data_Sectoral!$F$2:$F$20000,_Data_Sectoral!$A$2:$A$20000,"PL",_Data_Sectoral!$C$2:$C$20000,"transport",_Data_Sectoral!$D$2:$D$20000,"TOTAL",_Data_Sectoral!$E$2:$E$20000,2036) -> 11.380387 | O59: =SUMIFS(_Data_Sectoral!$F$2:$F$20000,_Data_Sectoral!$A$2:$A$20000,"PL",_Data_Sectoral!$C$2:$C$20000,"transport",_Data_Sectoral!$D$2:$D$20000,"TOTAL",_Data_Sectoral!$E$2:$E$20000,2037) -> 12.6402 | P59: =SUMIFS(_Data_Sectoral!$F$2:$F$20000,_Data_Sectoral!$A$2:$A$20000,"PL",_Data_Sectoral!$C$2:$C$20000,"transport",_Data_Sectoral!$D$2:$D$20000,"TOTAL",_Data_Sectoral!$E$2:$E$20000,2038) -> 13.943997 | Q59: =SUMIFS(_Data_Sectoral!$F$2:$F$20000,_Data_Sectoral!$A$2:$A$20000,"PL",_Data_Sectoral!$C$2:$C$20000,"transport",_Data_Sectoral!$D$2:$D$20000,"TOTAL",_Data_Sectoral!$E$2:$E$20000,2039) -> 15.359006 | R59: =SUMIFS(_Data_Sectoral!$F$2:$F$20000,_Data_Sectoral!$A$2:$A$20000,"PL",_Data_Sectoral!$C$2:$C$20000,"transport",_Data_Sectoral!$D$2:$D$20000,"TOTAL",_Data_Sectoral!$E$2:$E$20000,2040) -> 16.804963
A60: Buildings | B60: =SUMIFS(_Data_Sectoral!$F$2:$F$20000,_Data_Sectoral!$A$2:$A$20000,"PL",_Data_Sectoral!$C$2:$C$20000,"buildings",_Data_Sectoral!$D$2:$D$20000,"TOTAL",_Data_Sectoral!$E$2:$E$20000,2024) -> 81.878581 | C60: =SUMIFS(_Data_Sectoral!$F$2:$F$20000,_Data_Sectoral!$A$2:$A$20000,"PL",_Data_Sectoral!$C$2:$C$20000,"buildings",_Data_Sectoral!$D$2:$D$20000,"TOTAL",_Data_Sectoral!$E$2:$E$20000,2025) -> 82.677508 | D60: =SUMIFS(_Data_Sectoral!$F$2:$F$20000,_Data_Sectoral!$A$2:$A$20000,"PL",_Data_Sectoral!$C$2:$C$20000,"buildings",_Data_Sectoral!$D$2:$D$20000,"TOTAL",_Data_Sectoral!$E$2:$E$20000,2026) -> 84.119539 | E60: =SUMIFS(_Data_Sectoral!$F$2:$F$20000,_Data_Sectoral!$A$2:$A$20000,"PL",_Data_Sectoral!$C$2:$C$20000,"buildings",_Data_Sectoral!$D$2:$D$20000,"TOTAL",_Data_Sectoral!$E$2:$E$20000,2027) -> 85.852344 | F60: =SUMIFS(_Data_Sectoral!$F$2:$F$20000,_Data_Sectoral!$A$2:$A$20000,"PL",_Data_Sectoral!$C$2:$C$20000,"buildings",_Data_Sectoral!$D$2:$D$20000,"TOTAL",_Data_Sectoral!$E$2:$E$20000,2028) -> 89.29346 | G60: =SUMIFS(_Data_Sectoral!$F$2:$F$20000,_Data_Sectoral!$A$2:$A$20000,"PL",_Data_Sectoral!$C$2:$C$20000,"buildings",_Data_Sectoral!$D$2:$D$20000,"TOTAL",_Data_Sectoral!$E$2:$E$20000,2029) -> 92.777139 | H60: =SUMIFS(_Data_Sectoral!$F$2:$F$20000,_Data_Sectoral!$A$2:$A$20000,"PL",_Data_Sectoral!$C$2:$C$20000,"buildings",_Data_Sectoral!$D$2:$D$20000,"TOTAL",_Data_Sectoral!$E$2:$E$20000,2030) -> 96.338721 | I60: =SUMIFS(_Data_Sectoral!$F$2:$F$20000,_Data_Sectoral!$A$2:$A$20000,"PL",_Data_Sectoral!$C$2:$C$20000,"buildings",_Data_Sectoral!$D$2:$D$20000,"TOTAL",_Data_Sectoral!$E$2:$E$20000,2031) -> 99.858419 | J60: =SUMIFS(_Data_Sectoral!$F$2:$F$20000,_Data_Sectoral!$A$2:$A$20000,"PL",_Data_Sectoral!$C$2:$C$20000,"buildings",_Data_Sectoral!$D$2:$D$20000,"TOTAL",_Data_Sectoral!$E$2:$E$20000,2032) -> 103.36843 | K60: =SUMIFS(_Data_Sectoral!$F$2:$F$20000,_Data_Sectoral!$A$2:$A$20000,"PL",_Data_Sectoral!$C$2:$C$20000,"buildings",_Data_Sectoral!$D$2:$D$20000,"TOTAL",_Data_Sectoral!$E$2:$E$20000,2033) -> 106.88428 | L60: =SUMIFS(_Data_Sectoral!$F$2:$F$20000,_Data_Sectoral!$A$2:$A$20000,"PL",_Data_Sectoral!$C$2:$C$20000,"buildings",_Data_Sectoral!$D$2:$D$20000,"TOTAL",_Data_Sectoral!$E$2:$E$20000,2034) -> 110.4021 | M60: =SUMIFS(_Data_Sectoral!$F$2:$F$20000,_Data_Sectoral!$A$2:$A$20000,"PL",_Data_Sectoral!$C$2:$C$20000,"buildings",_Data_Sectoral!$D$2:$D$20000,"TOTAL",_Data_Sectoral!$E$2:$E$20000,2035) -> 113.92138 | N60: =SUMIFS(_Data_Sectoral!$F$2:$F$20000,_Data_Sectoral!$A$2:$A$20000,"PL",_Data_Sectoral!$C$2:$C$20000,"buildings",_Data_Sectoral!$D$2:$D$20000,"TOTAL",_Data_Sectoral!$E$2:$E$20000,2036) -> 116.74605 | O60: =SUMIFS(_Data_Sectoral!$F$2:$F$20000,_Data_Sectoral!$A$2:$A$20000,"PL",_Data_Sectoral!$C$2:$C$20000,"buildings",_Data_Sectoral!$D$2:$D$20000,"TOTAL",_Data_Sectoral!$E$2:$E$20000,2037) -> 119.44803 | P60: =SUMIFS(_Data_Sectoral!$F$2:$F$20000,_Data_Sectoral!$A$2:$A$20000,"PL",_Data_Sectoral!$C$2:$C$20000,"buildings",_Data_Sectoral!$D$2:$D$20000,"TOTAL",_Data_Sectoral!$E$2:$E$20000,2038) -> 122.11384 | Q60: =SUMIFS(_Data_Sectoral!$F$2:$F$20000,_Data_Sectoral!$A$2:$A$20000,"PL",_Data_Sectoral!$C$2:$C$20000,"buildings",_Data_Sectoral!$D$2:$D$20000,"TOTAL",_Data_Sectoral!$E$2:$E$20000,2039) -> 124.76017 | R60: =SUMIFS(_Data_Sectoral!$F$2:$F$20000,_Data_Sectoral!$A$2:$A$20000,"PL",_Data_Sectoral!$C$2:$C$20000,"buildings",_Data_Sectoral!$D$2:$D$20000,"TOTAL",_Data_Sectoral!$E$2:$E$20000,2040) -> 126.60851
A61: Industry | B61: =SUMIFS(_Data_Sectoral!$F$2:$F$20000,_Data_Sectoral!$A$2:$A$20000,"PL",_Data_Sectoral!$C$2:$C$20000,"industry",_Data_Sectoral!$D$2:$D$20000,"TOTAL",_Data_Sectoral!$E$2:$E$20000,2024) -> 67.2453 | C61: =SUMIFS(_Data_Sectoral!$F$2:$F$20000,_Data_Sectoral!$A$2:$A$20000,"PL",_Data_Sectoral!$C$2:$C$20000,"industry",_Data_Sectoral!$D$2:$D$20000,"TOTAL",_Data_Sectoral!$E$2:$E$20000,2025) -> 68.085293 | D61: =SUMIFS(_Data_Sectoral!$F$2:$F$20000,_Data_Sectoral!$A$2:$A$20000,"PL",_Data_Sectoral!$C$2:$C$20000,"industry",_Data_Sectoral!$D$2:$D$20000,"TOTAL",_Data_Sectoral!$E$2:$E$20000,2026) -> 68.64626 | E61: =SUMIFS(_Data_Sectoral!$F$2:$F$20000,_Data_Sectoral!$A$2:$A$20000,"PL",_Data_Sectoral!$C$2:$C$20000,"industry",_Data_Sectoral!$D$2:$D$20000,"TOTAL",_Data_Sectoral!$E$2:$E$20000,2027) -> 69.040188 | F61: =SUMIFS(_Data_Sectoral!$F$2:$F$20000,_Data_Sectoral!$A$2:$A$20000,"PL",_Data_Sectoral!$C$2:$C$20000,"industry",_Data_Sectoral!$D$2:$D$20000,"TOTAL",_Data_Sectoral!$E$2:$E$20000,2028) -> 69.626211 | G61: =SUMIFS(_Data_Sectoral!$F$2:$F$20000,_Data_Sectoral!$A$2:$A$20000,"PL",_Data_Sectoral!$C$2:$C$20000,"industry",_Data_Sectoral!$D$2:$D$20000,"TOTAL",_Data_Sectoral!$E$2:$E$20000,2029) -> 70.708624 | H61: =SUMIFS(_Data_Sectoral!$F$2:$F$20000,_Data_Sectoral!$A$2:$A$20000,"PL",_Data_Sectoral!$C$2:$C$20000,"industry",_Data_Sectoral!$D$2:$D$20000,"TOTAL",_Data_Sectoral!$E$2:$E$20000,2030) -> 71.714863 | I61: =SUMIFS(_Data_Sectoral!$F$2:$F$20000,_Data_Sectoral!$A$2:$A$20000,"PL",_Data_Sectoral!$C$2:$C$20000,"industry",_Data_Sectoral!$D$2:$D$20000,"TOTAL",_Data_Sectoral!$E$2:$E$20000,2031) -> 72.446876 | J61: =SUMIFS(_Data_Sectoral!$F$2:$F$20000,_Data_Sectoral!$A$2:$A$20000,"PL",_Data_Sectoral!$C$2:$C$20000,"industry",_Data_Sectoral!$D$2:$D$20000,"TOTAL",_Data_Sectoral!$E$2:$E$20000,2032) -> 73.472299 | K61: =SUMIFS(_Data_Sectoral!$F$2:$F$20000,_Data_Sectoral!$A$2:$A$20000,"PL",_Data_Sectoral!$C$2:$C$20000,"industry",_Data_Sectoral!$D$2:$D$20000,"TOTAL",_Data_Sectoral!$E$2:$E$20000,2033) -> 74.628149 | L61: =SUMIFS(_Data_Sectoral!$F$2:$F$20000,_Data_Sectoral!$A$2:$A$20000,"PL",_Data_Sectoral!$C$2:$C$20000,"industry",_Data_Sectoral!$D$2:$D$20000,"TOTAL",_Data_Sectoral!$E$2:$E$20000,2034) -> 75.862295 | M61: =SUMIFS(_Data_Sectoral!$F$2:$F$20000,_Data_Sectoral!$A$2:$A$20000,"PL",_Data_Sectoral!$C$2:$C$20000,"industry",_Data_Sectoral!$D$2:$D$20000,"TOTAL",_Data_Sectoral!$E$2:$E$20000,2035) -> 77.128598 | N61: =SUMIFS(_Data_Sectoral!$F$2:$F$20000,_Data_Sectoral!$A$2:$A$20000,"PL",_Data_Sectoral!$C$2:$C$20000,"industry",_Data_Sectoral!$D$2:$D$20000,"TOTAL",_Data_Sectoral!$E$2:$E$20000,2036) -> 78.191293 | O61: =SUMIFS(_Data_Sectoral!$F$2:$F$20000,_Data_Sectoral!$A$2:$A$20000,"PL",_Data_Sectoral!$C$2:$C$20000,"industry",_Data_Sectoral!$D$2:$D$20000,"TOTAL",_Data_Sectoral!$E$2:$E$20000,2037) -> 79.219821 | P61: =SUMIFS(_Data_Sectoral!$F$2:$F$20000,_Data_Sectoral!$A$2:$A$20000,"PL",_Data_Sectoral!$C$2:$C$20000,"industry",_Data_Sectoral!$D$2:$D$20000,"TOTAL",_Data_Sectoral!$E$2:$E$20000,2038) -> 80.239993 | Q61: =SUMIFS(_Data_Sectoral!$F$2:$F$20000,_Data_Sectoral!$A$2:$A$20000,"PL",_Data_Sectoral!$C$2:$C$20000,"industry",_Data_Sectoral!$D$2:$D$20000,"TOTAL",_Data_Sectoral!$E$2:$E$20000,2039) -> 81.275224 | R61: =SUMIFS(_Data_Sectoral!$F$2:$F$20000,_Data_Sectoral!$A$2:$A$20000,"PL",_Data_Sectoral!$C$2:$C$20000,"industry",_Data_Sectoral!$D$2:$D$20000,"TOTAL",_Data_Sectoral!$E$2:$E$20000,2040) -> 82.364794
A62: Data Centers | B62: =SUMIFS(_Data_Sectoral!$F$2:$F$20000,_Data_Sectoral!$A$2:$A$20000,"PL",_Data_Sectoral!$C$2:$C$20000,"data_centers",_Data_Sectoral!$D$2:$D$20000,"TOTAL",_Data_Sectoral!$E$2:$E$20000,2024) -> 1.62498 | C62: =SUMIFS(_Data_Sectoral!$F$2:$F$20000,_Data_Sectoral!$A$2:$A$20000,"PL",_Data_Sectoral!$C$2:$C$20000,"data_centers",_Data_Sectoral!$D$2:$D$20000,"TOTAL",_Data_Sectoral!$E$2:$E$20000,2025) -> 1.8304004 | D62: =SUMIFS(_Data_Sectoral!$F$2:$F$20000,_Data_Sectoral!$A$2:$A$20000,"PL",_Data_Sectoral!$C$2:$C$20000,"data_centers",_Data_Sectoral!$D$2:$D$20000,"TOTAL",_Data_Sectoral!$E$2:$E$20000,2026) -> 2.2485762 | E62: =SUMIFS(_Data_Sectoral!$F$2:$F$20000,_Data_Sectoral!$A$2:$A$20000,"PL",_Data_Sectoral!$C$2:$C$20000,"data_centers",_Data_Sectoral!$D$2:$D$20000,"TOTAL",_Data_Sectoral!$E$2:$E$20000,2027) -> 2.7685863 | F62: =SUMIFS(_Data_Sectoral!$F$2:$F$20000,_Data_Sectoral!$A$2:$A$20000,"PL",_Data_Sectoral!$C$2:$C$20000,"data_centers",_Data_Sectoral!$D$2:$D$20000,"TOTAL",_Data_Sectoral!$E$2:$E$20000,2028) -> 2.8782338 | G62: =SUMIFS(_Data_Sectoral!$F$2:$F$20000,_Data_Sectoral!$A$2:$A$20000,"PL",_Data_Sectoral!$C$2:$C$20000,"data_centers",_Data_Sectoral!$D$2:$D$20000,"TOTAL",_Data_Sectoral!$E$2:$E$20000,2029) -> 3.2916142 | H62: =SUMIFS(_Data_Sectoral!$F$2:$F$20000,_Data_Sectoral!$A$2:$A$20000,"PL",_Data_Sectoral!$C$2:$C$20000,"data_centers",_Data_Sectoral!$D$2:$D$20000,"TOTAL",_Data_Sectoral!$E$2:$E$20000,2030) -> 3.5094458 | I62: =SUMIFS(_Data_Sectoral!$F$2:$F$20000,_Data_Sectoral!$A$2:$A$20000,"PL",_Data_Sectoral!$C$2:$C$20000,"data_centers",_Data_Sectoral!$D$2:$D$20000,"TOTAL",_Data_Sectoral!$E$2:$E$20000,2031) -> 3.7830041 | J62: =SUMIFS(_Data_Sectoral!$F$2:$F$20000,_Data_Sectoral!$A$2:$A$20000,"PL",_Data_Sectoral!$C$2:$C$20000,"data_centers",_Data_Sectoral!$D$2:$D$20000,"TOTAL",_Data_Sectoral!$E$2:$E$20000,2032) -> 4.2312018 | K62: =SUMIFS(_Data_Sectoral!$F$2:$F$20000,_Data_Sectoral!$A$2:$A$20000,"PL",_Data_Sectoral!$C$2:$C$20000,"data_centers",_Data_Sectoral!$D$2:$D$20000,"TOTAL",_Data_Sectoral!$E$2:$E$20000,2033) -> 4.6777346 | L62: =SUMIFS(_Data_Sectoral!$F$2:$F$20000,_Data_Sectoral!$A$2:$A$20000,"PL",_Data_Sectoral!$C$2:$C$20000,"data_centers",_Data_Sectoral!$D$2:$D$20000,"TOTAL",_Data_Sectoral!$E$2:$E$20000,2034) -> 5.1108461 | M62: =SUMIFS(_Data_Sectoral!$F$2:$F$20000,_Data_Sectoral!$A$2:$A$20000,"PL",_Data_Sectoral!$C$2:$C$20000,"data_centers",_Data_Sectoral!$D$2:$D$20000,"TOTAL",_Data_Sectoral!$E$2:$E$20000,2035) -> 5.5179079 | N62: =SUMIFS(_Data_Sectoral!$F$2:$F$20000,_Data_Sectoral!$A$2:$A$20000,"PL",_Data_Sectoral!$C$2:$C$20000,"data_centers",_Data_Sectoral!$D$2:$D$20000,"TOTAL",_Data_Sectoral!$E$2:$E$20000,2036) -> 5.8859708 | O62: =SUMIFS(_Data_Sectoral!$F$2:$F$20000,_Data_Sectoral!$A$2:$A$20000,"PL",_Data_Sectoral!$C$2:$C$20000,"data_centers",_Data_Sectoral!$D$2:$D$20000,"TOTAL",_Data_Sectoral!$E$2:$E$20000,2037) -> 6.2024005 | P62: =SUMIFS(_Data_Sectoral!$F$2:$F$20000,_Data_Sectoral!$A$2:$A$20000,"PL",_Data_Sectoral!$C$2:$C$20000,"data_centers",_Data_Sectoral!$D$2:$D$20000,"TOTAL",_Data_Sectoral!$E$2:$E$20000,2038) -> 6.4555619 | Q62: =SUMIFS(_Data_Sectoral!$F$2:$F$20000,_Data_Sectoral!$A$2:$A$20000,"PL",_Data_Sectoral!$C$2:$C$20000,"data_centers",_Data_Sectoral!$D$2:$D$20000,"TOTAL",_Data_Sectoral!$E$2:$E$20000,2039) -> 6.6354999 | R62: =SUMIFS(_Data_Sectoral!$F$2:$F$20000,_Data_Sectoral!$A$2:$A$20000,"PL",_Data_Sectoral!$C$2:$C$20000,"data_centers",_Data_Sectoral!$D$2:$D$20000,"TOTAL",_Data_Sectoral!$E$2:$E$20000,2040) -> 6.7345679
A63: Hydrogen | B63: =SUMIFS(_Data_Sectoral!$F$2:$F$20000,_Data_Sectoral!$A$2:$A$20000,"PL",_Data_Sectoral!$C$2:$C$20000,"hydrogen",_Data_Sectoral!$D$2:$D$20000,"TOTAL",_Data_Sectoral!$E$2:$E$20000,2024) -> 0.02 | C63: =SUMIFS(_Data_Sectoral!$F$2:$F$20000,_Data_Sectoral!$A$2:$A$20000,"PL",_Data_Sectoral!$C$2:$C$20000,"hydrogen",_Data_Sectoral!$D$2:$D$20000,"TOTAL",_Data_Sectoral!$E$2:$E$20000,2025) -> 0.025 | D63: =SUMIFS(_Data_Sectoral!$F$2:$F$20000,_Data_Sectoral!$A$2:$A$20000,"PL",_Data_Sectoral!$C$2:$C$20000,"hydrogen",_Data_Sectoral!$D$2:$D$20000,"TOTAL",_Data_Sectoral!$E$2:$E$20000,2026) -> 0.077412 | E63: =SUMIFS(_Data_Sectoral!$F$2:$F$20000,_Data_Sectoral!$A$2:$A$20000,"PL",_Data_Sectoral!$C$2:$C$20000,"hydrogen",_Data_Sectoral!$D$2:$D$20000,"TOTAL",_Data_Sectoral!$E$2:$E$20000,2027) -> 0.129823 | F63: =SUMIFS(_Data_Sectoral!$F$2:$F$20000,_Data_Sectoral!$A$2:$A$20000,"PL",_Data_Sectoral!$C$2:$C$20000,"hydrogen",_Data_Sectoral!$D$2:$D$20000,"TOTAL",_Data_Sectoral!$E$2:$E$20000,2028) -> 0.21865 | G63: =SUMIFS(_Data_Sectoral!$F$2:$F$20000,_Data_Sectoral!$A$2:$A$20000,"PL",_Data_Sectoral!$C$2:$C$20000,"hydrogen",_Data_Sectoral!$D$2:$D$20000,"TOTAL",_Data_Sectoral!$E$2:$E$20000,2029) -> 0.34164 | H63: =SUMIFS(_Data_Sectoral!$F$2:$F$20000,_Data_Sectoral!$A$2:$A$20000,"PL",_Data_Sectoral!$C$2:$C$20000,"hydrogen",_Data_Sectoral!$D$2:$D$20000,"TOTAL",_Data_Sectoral!$E$2:$E$20000,2030) -> 0.38106 | I63: =SUMIFS(_Data_Sectoral!$F$2:$F$20000,_Data_Sectoral!$A$2:$A$20000,"PL",_Data_Sectoral!$C$2:$C$20000,"hydrogen",_Data_Sectoral!$D$2:$D$20000,"TOTAL",_Data_Sectoral!$E$2:$E$20000,2031) -> 0.494327 | J63: =SUMIFS(_Data_Sectoral!$F$2:$F$20000,_Data_Sectoral!$A$2:$A$20000,"PL",_Data_Sectoral!$C$2:$C$20000,"hydrogen",_Data_Sectoral!$D$2:$D$20000,"TOTAL",_Data_Sectoral!$E$2:$E$20000,2032) -> 0.629143 | K63: =SUMIFS(_Data_Sectoral!$F$2:$F$20000,_Data_Sectoral!$A$2:$A$20000,"PL",_Data_Sectoral!$C$2:$C$20000,"hydrogen",_Data_Sectoral!$D$2:$D$20000,"TOTAL",_Data_Sectoral!$E$2:$E$20000,2033) -> 0.792605 | L63: =SUMIFS(_Data_Sectoral!$F$2:$F$20000,_Data_Sectoral!$A$2:$A$20000,"PL",_Data_Sectoral!$C$2:$C$20000,"hydrogen",_Data_Sectoral!$D$2:$D$20000,"TOTAL",_Data_Sectoral!$E$2:$E$20000,2034) -> 0.976828 | M63: =SUMIFS(_Data_Sectoral!$F$2:$F$20000,_Data_Sectoral!$A$2:$A$20000,"PL",_Data_Sectoral!$C$2:$C$20000,"hydrogen",_Data_Sectoral!$D$2:$D$20000,"TOTAL",_Data_Sectoral!$E$2:$E$20000,2035) -> 1.1826 | N63: =SUMIFS(_Data_Sectoral!$F$2:$F$20000,_Data_Sectoral!$A$2:$A$20000,"PL",_Data_Sectoral!$C$2:$C$20000,"hydrogen",_Data_Sectoral!$D$2:$D$20000,"TOTAL",_Data_Sectoral!$E$2:$E$20000,2036) -> 1.41071 | O63: =SUMIFS(_Data_Sectoral!$F$2:$F$20000,_Data_Sectoral!$A$2:$A$20000,"PL",_Data_Sectoral!$C$2:$C$20000,"hydrogen",_Data_Sectoral!$D$2:$D$20000,"TOTAL",_Data_Sectoral!$E$2:$E$20000,2037) -> 1.615782 | P63: =SUMIFS(_Data_Sectoral!$F$2:$F$20000,_Data_Sectoral!$A$2:$A$20000,"PL",_Data_Sectoral!$C$2:$C$20000,"hydrogen",_Data_Sectoral!$D$2:$D$20000,"TOTAL",_Data_Sectoral!$E$2:$E$20000,2038) -> 1.83776 | Q63: =SUMIFS(_Data_Sectoral!$F$2:$F$20000,_Data_Sectoral!$A$2:$A$20000,"PL",_Data_Sectoral!$C$2:$C$20000,"hydrogen",_Data_Sectoral!$D$2:$D$20000,"TOTAL",_Data_Sectoral!$E$2:$E$20000,2039) -> 2.077171 | R63: =SUMIFS(_Data_Sectoral!$F$2:$F$20000,_Data_Sectoral!$A$2:$A$20000,"PL",_Data_Sectoral!$C$2:$C$20000,"hydrogen",_Data_Sectoral!$D$2:$D$20000,"TOTAL",_Data_Sectoral!$E$2:$E$20000,2040) -> 2.2776
A64: Total | B64: =SUM(B59:B63) -> 153.85992 | C64: =SUM(C59:C63) -> 155.89256 | D64: =SUM(D59:D63) -> 158.69075 | E64: =SUM(E59:E63) -> 161.80942 | F64: =SUM(F59:F63) -> 166.54271 | G64: =SUM(G59:G63) -> 172.20252 | H64: =SUM(H59:H63) -> 177.70125 | I64: =SUM(I59:I63) -> 183.05265 | ... R64: =SUM(R59:R63) -> 234.79043
A66: Canada
A67: Sector | B67: 2024 | C67: 2025 | D67: 2026 | E67: 2027 | F67: 2028 | G67: 2029 | H67: 2030 | I67: 2031 | J67: 2032 | K67: 2033 | L67: 2034 | M67: 2035 | N67: 2036 | O67: 2037 | P67: 2038 | Q67: 2039 | R67: 2040
A68: Transport | B68: =SUMIFS(_Data_Sectoral!$F$2:$F$20000,_Data_Sectoral!$A$2:$A$20000,"CA",_Data_Sectoral!$C$2:$C$20000,"transport",_Data_Sectoral!$D$2:$D$20000,"TOTAL",_Data_Sectoral!$E$2:$E$20000,2024) -> 9.2790679 | C68: =SUMIFS(_Data_Sectoral!$F$2:$F$20000,_Data_Sectoral!$A$2:$A$20000,"CA",_Data_Sectoral!$C$2:$C$20000,"transport",_Data_Sectoral!$D$2:$D$20000,"TOTAL",_Data_Sectoral!$E$2:$E$20000,2025) -> 9.9968787 | D68: =SUMIFS(_Data_Sectoral!$F$2:$F$20000,_Data_Sectoral!$A$2:$A$20000,"CA",_Data_Sectoral!$C$2:$C$20000,"transport",_Data_Sectoral!$D$2:$D$20000,"TOTAL",_Data_Sectoral!$E$2:$E$20000,2026) -> 11.15883 | E68: =SUMIFS(_Data_Sectoral!$F$2:$F$20000,_Data_Sectoral!$A$2:$A$20000,"CA",_Data_Sectoral!$C$2:$C$20000,"transport",_Data_Sectoral!$D$2:$D$20000,"TOTAL",_Data_Sectoral!$E$2:$E$20000,2027) -> 12.824698 | F68: =SUMIFS(_Data_Sectoral!$F$2:$F$20000,_Data_Sectoral!$A$2:$A$20000,"CA",_Data_Sectoral!$C$2:$C$20000,"transport",_Data_Sectoral!$D$2:$D$20000,"TOTAL",_Data_Sectoral!$E$2:$E$20000,2028) -> 14.95478 | G68: =SUMIFS(_Data_Sectoral!$F$2:$F$20000,_Data_Sectoral!$A$2:$A$20000,"CA",_Data_Sectoral!$C$2:$C$20000,"transport",_Data_Sectoral!$D$2:$D$20000,"TOTAL",_Data_Sectoral!$E$2:$E$20000,2029) -> 17.53312 | H68: =SUMIFS(_Data_Sectoral!$F$2:$F$20000,_Data_Sectoral!$A$2:$A$20000,"CA",_Data_Sectoral!$C$2:$C$20000,"transport",_Data_Sectoral!$D$2:$D$20000,"TOTAL",_Data_Sectoral!$E$2:$E$20000,2030) -> 20.71499 | I68: =SUMIFS(_Data_Sectoral!$F$2:$F$20000,_Data_Sectoral!$A$2:$A$20000,"CA",_Data_Sectoral!$C$2:$C$20000,"transport",_Data_Sectoral!$D$2:$D$20000,"TOTAL",_Data_Sectoral!$E$2:$E$20000,2031) -> 24.224172 | J68: =SUMIFS(_Data_Sectoral!$F$2:$F$20000,_Data_Sectoral!$A$2:$A$20000,"CA",_Data_Sectoral!$C$2:$C$20000,"transport",_Data_Sectoral!$D$2:$D$20000,"TOTAL",_Data_Sectoral!$E$2:$E$20000,2032) -> 28.105859 | K68: =SUMIFS(_Data_Sectoral!$F$2:$F$20000,_Data_Sectoral!$A$2:$A$20000,"CA",_Data_Sectoral!$C$2:$C$20000,"transport",_Data_Sectoral!$D$2:$D$20000,"TOTAL",_Data_Sectoral!$E$2:$E$20000,2033) -> 32.568111 | L68: =SUMIFS(_Data_Sectoral!$F$2:$F$20000,_Data_Sectoral!$A$2:$A$20000,"CA",_Data_Sectoral!$C$2:$C$20000,"transport",_Data_Sectoral!$D$2:$D$20000,"TOTAL",_Data_Sectoral!$E$2:$E$20000,2034) -> 37.132406 | M68: =SUMIFS(_Data_Sectoral!$F$2:$F$20000,_Data_Sectoral!$A$2:$A$20000,"CA",_Data_Sectoral!$C$2:$C$20000,"transport",_Data_Sectoral!$D$2:$D$20000,"TOTAL",_Data_Sectoral!$E$2:$E$20000,2035) -> 42.393288 | N68: =SUMIFS(_Data_Sectoral!$F$2:$F$20000,_Data_Sectoral!$A$2:$A$20000,"CA",_Data_Sectoral!$C$2:$C$20000,"transport",_Data_Sectoral!$D$2:$D$20000,"TOTAL",_Data_Sectoral!$E$2:$E$20000,2036) -> 47.271824 | O68: =SUMIFS(_Data_Sectoral!$F$2:$F$20000,_Data_Sectoral!$A$2:$A$20000,"CA",_Data_Sectoral!$C$2:$C$20000,"transport",_Data_Sectoral!$D$2:$D$20000,"TOTAL",_Data_Sectoral!$E$2:$E$20000,2037) -> 52.049974 | P68: =SUMIFS(_Data_Sectoral!$F$2:$F$20000,_Data_Sectoral!$A$2:$A$20000,"CA",_Data_Sectoral!$C$2:$C$20000,"transport",_Data_Sectoral!$D$2:$D$20000,"TOTAL",_Data_Sectoral!$E$2:$E$20000,2038) -> 56.753494 | Q68: =SUMIFS(_Data_Sectoral!$F$2:$F$20000,_Data_Sectoral!$A$2:$A$20000,"CA",_Data_Sectoral!$C$2:$C$20000,"transport",_Data_Sectoral!$D$2:$D$20000,"TOTAL",_Data_Sectoral!$E$2:$E$20000,2039) -> 61.941216 | R68: =SUMIFS(_Data_Sectoral!$F$2:$F$20000,_Data_Sectoral!$A$2:$A$20000,"CA",_Data_Sectoral!$C$2:$C$20000,"transport",_Data_Sectoral!$D$2:$D$20000,"TOTAL",_Data_Sectoral!$E$2:$E$20000,2040) -> 67.680163
A69: Buildings | B69: =SUMIFS(_Data_Sectoral!$F$2:$F$20000,_Data_Sectoral!$A$2:$A$20000,"CA",_Data_Sectoral!$C$2:$C$20000,"buildings",_Data_Sectoral!$D$2:$D$20000,"TOTAL",_Data_Sectoral!$E$2:$E$20000,2024) -> 311.46606 | C69: =SUMIFS(_Data_Sectoral!$F$2:$F$20000,_Data_Sectoral!$A$2:$A$20000,"CA",_Data_Sectoral!$C$2:$C$20000,"buildings",_Data_Sectoral!$D$2:$D$20000,"TOTAL",_Data_Sectoral!$E$2:$E$20000,2025) -> 311.55721 | D69: =SUMIFS(_Data_Sectoral!$F$2:$F$20000,_Data_Sectoral!$A$2:$A$20000,"CA",_Data_Sectoral!$C$2:$C$20000,"buildings",_Data_Sectoral!$D$2:$D$20000,"TOTAL",_Data_Sectoral!$E$2:$E$20000,2026) -> 312.13995 | E69: =SUMIFS(_Data_Sectoral!$F$2:$F$20000,_Data_Sectoral!$A$2:$A$20000,"CA",_Data_Sectoral!$C$2:$C$20000,"buildings",_Data_Sectoral!$D$2:$D$20000,"TOTAL",_Data_Sectoral!$E$2:$E$20000,2027) -> 312.9459 | F69: =SUMIFS(_Data_Sectoral!$F$2:$F$20000,_Data_Sectoral!$A$2:$A$20000,"CA",_Data_Sectoral!$C$2:$C$20000,"buildings",_Data_Sectoral!$D$2:$D$20000,"TOTAL",_Data_Sectoral!$E$2:$E$20000,2028) -> 313.55515 | G69: =SUMIFS(_Data_Sectoral!$F$2:$F$20000,_Data_Sectoral!$A$2:$A$20000,"CA",_Data_Sectoral!$C$2:$C$20000,"buildings",_Data_Sectoral!$D$2:$D$20000,"TOTAL",_Data_Sectoral!$E$2:$E$20000,2029) -> 314.70366 | H69: =SUMIFS(_Data_Sectoral!$F$2:$F$20000,_Data_Sectoral!$A$2:$A$20000,"CA",_Data_Sectoral!$C$2:$C$20000,"buildings",_Data_Sectoral!$D$2:$D$20000,"TOTAL",_Data_Sectoral!$E$2:$E$20000,2030) -> 315.40032 | I69: =SUMIFS(_Data_Sectoral!$F$2:$F$20000,_Data_Sectoral!$A$2:$A$20000,"CA",_Data_Sectoral!$C$2:$C$20000,"buildings",_Data_Sectoral!$D$2:$D$20000,"TOTAL",_Data_Sectoral!$E$2:$E$20000,2031) -> 316.06496 | J69: =SUMIFS(_Data_Sectoral!$F$2:$F$20000,_Data_Sectoral!$A$2:$A$20000,"CA",_Data_Sectoral!$C$2:$C$20000,"buildings",_Data_Sectoral!$D$2:$D$20000,"TOTAL",_Data_Sectoral!$E$2:$E$20000,2032) -> 316.61852 | K69: =SUMIFS(_Data_Sectoral!$F$2:$F$20000,_Data_Sectoral!$A$2:$A$20000,"CA",_Data_Sectoral!$C$2:$C$20000,"buildings",_Data_Sectoral!$D$2:$D$20000,"TOTAL",_Data_Sectoral!$E$2:$E$20000,2033) -> 317.22558 | L69: =SUMIFS(_Data_Sectoral!$F$2:$F$20000,_Data_Sectoral!$A$2:$A$20000,"CA",_Data_Sectoral!$C$2:$C$20000,"buildings",_Data_Sectoral!$D$2:$D$20000,"TOTAL",_Data_Sectoral!$E$2:$E$20000,2034) -> 317.90271 | M69: =SUMIFS(_Data_Sectoral!$F$2:$F$20000,_Data_Sectoral!$A$2:$A$20000,"CA",_Data_Sectoral!$C$2:$C$20000,"buildings",_Data_Sectoral!$D$2:$D$20000,"TOTAL",_Data_Sectoral!$E$2:$E$20000,2035) -> 318.93913 | N69: =SUMIFS(_Data_Sectoral!$F$2:$F$20000,_Data_Sectoral!$A$2:$A$20000,"CA",_Data_Sectoral!$C$2:$C$20000,"buildings",_Data_Sectoral!$D$2:$D$20000,"TOTAL",_Data_Sectoral!$E$2:$E$20000,2036) -> 319.87848 | O69: =SUMIFS(_Data_Sectoral!$F$2:$F$20000,_Data_Sectoral!$A$2:$A$20000,"CA",_Data_Sectoral!$C$2:$C$20000,"buildings",_Data_Sectoral!$D$2:$D$20000,"TOTAL",_Data_Sectoral!$E$2:$E$20000,2037) -> 321.06839 | P69: =SUMIFS(_Data_Sectoral!$F$2:$F$20000,_Data_Sectoral!$A$2:$A$20000,"CA",_Data_Sectoral!$C$2:$C$20000,"buildings",_Data_Sectoral!$D$2:$D$20000,"TOTAL",_Data_Sectoral!$E$2:$E$20000,2038) -> 321.64033 | Q69: =SUMIFS(_Data_Sectoral!$F$2:$F$20000,_Data_Sectoral!$A$2:$A$20000,"CA",_Data_Sectoral!$C$2:$C$20000,"buildings",_Data_Sectoral!$D$2:$D$20000,"TOTAL",_Data_Sectoral!$E$2:$E$20000,2039) -> 322.9045 | R69: =SUMIFS(_Data_Sectoral!$F$2:$F$20000,_Data_Sectoral!$A$2:$A$20000,"CA",_Data_Sectoral!$C$2:$C$20000,"buildings",_Data_Sectoral!$D$2:$D$20000,"TOTAL",_Data_Sectoral!$E$2:$E$20000,2040) -> 323.54849
A70: Cooling | B70: =SUMIFS(_Data_Sectoral!$F$2:$F$20000,_Data_Sectoral!$A$2:$A$20000,"CA",_Data_Sectoral!$C$2:$C$20000,"cooling",_Data_Sectoral!$D$2:$D$20000,"TOTAL",_Data_Sectoral!$E$2:$E$20000,2024) -> 23.853942 | C70: =SUMIFS(_Data_Sectoral!$F$2:$F$20000,_Data_Sectoral!$A$2:$A$20000,"CA",_Data_Sectoral!$C$2:$C$20000,"cooling",_Data_Sectoral!$D$2:$D$20000,"TOTAL",_Data_Sectoral!$E$2:$E$20000,2025) -> 25.193335 | D70: =SUMIFS(_Data_Sectoral!$F$2:$F$20000,_Data_Sectoral!$A$2:$A$20000,"CA",_Data_Sectoral!$C$2:$C$20000,"cooling",_Data_Sectoral!$D$2:$D$20000,"TOTAL",_Data_Sectoral!$E$2:$E$20000,2026) -> 26.529078 | E70: =SUMIFS(_Data_Sectoral!$F$2:$F$20000,_Data_Sectoral!$A$2:$A$20000,"CA",_Data_Sectoral!$C$2:$C$20000,"cooling",_Data_Sectoral!$D$2:$D$20000,"TOTAL",_Data_Sectoral!$E$2:$E$20000,2027) -> 27.464284 | F70: =SUMIFS(_Data_Sectoral!$F$2:$F$20000,_Data_Sectoral!$A$2:$A$20000,"CA",_Data_Sectoral!$C$2:$C$20000,"cooling",_Data_Sectoral!$D$2:$D$20000,"TOTAL",_Data_Sectoral!$E$2:$E$20000,2028) -> 28.245293 | G70: =SUMIFS(_Data_Sectoral!$F$2:$F$20000,_Data_Sectoral!$A$2:$A$20000,"CA",_Data_Sectoral!$C$2:$C$20000,"cooling",_Data_Sectoral!$D$2:$D$20000,"TOTAL",_Data_Sectoral!$E$2:$E$20000,2029) -> 28.641727 | H70: =SUMIFS(_Data_Sectoral!$F$2:$F$20000,_Data_Sectoral!$A$2:$A$20000,"CA",_Data_Sectoral!$C$2:$C$20000,"cooling",_Data_Sectoral!$D$2:$D$20000,"TOTAL",_Data_Sectoral!$E$2:$E$20000,2030) -> 28.583855 | I70: =SUMIFS(_Data_Sectoral!$F$2:$F$20000,_Data_Sectoral!$A$2:$A$20000,"CA",_Data_Sectoral!$C$2:$C$20000,"cooling",_Data_Sectoral!$D$2:$D$20000,"TOTAL",_Data_Sectoral!$E$2:$E$20000,2031) -> 28.415745 | J70: =SUMIFS(_Data_Sectoral!$F$2:$F$20000,_Data_Sectoral!$A$2:$A$20000,"CA",_Data_Sectoral!$C$2:$C$20000,"cooling",_Data_Sectoral!$D$2:$D$20000,"TOTAL",_Data_Sectoral!$E$2:$E$20000,2032) -> 30.027219 | K70: =SUMIFS(_Data_Sectoral!$F$2:$F$20000,_Data_Sectoral!$A$2:$A$20000,"CA",_Data_Sectoral!$C$2:$C$20000,"cooling",_Data_Sectoral!$D$2:$D$20000,"TOTAL",_Data_Sectoral!$E$2:$E$20000,2033) -> 31.565436 | L70: =SUMIFS(_Data_Sectoral!$F$2:$F$20000,_Data_Sectoral!$A$2:$A$20000,"CA",_Data_Sectoral!$C$2:$C$20000,"cooling",_Data_Sectoral!$D$2:$D$20000,"TOTAL",_Data_Sectoral!$E$2:$E$20000,2034) -> 33.923833 | M70: =SUMIFS(_Data_Sectoral!$F$2:$F$20000,_Data_Sectoral!$A$2:$A$20000,"CA",_Data_Sectoral!$C$2:$C$20000,"cooling",_Data_Sectoral!$D$2:$D$20000,"TOTAL",_Data_Sectoral!$E$2:$E$20000,2035) -> 35.269988 | N70: =SUMIFS(_Data_Sectoral!$F$2:$F$20000,_Data_Sectoral!$A$2:$A$20000,"CA",_Data_Sectoral!$C$2:$C$20000,"cooling",_Data_Sectoral!$D$2:$D$20000,"TOTAL",_Data_Sectoral!$E$2:$E$20000,2036) -> 35.2592 | O70: =SUMIFS(_Data_Sectoral!$F$2:$F$20000,_Data_Sectoral!$A$2:$A$20000,"CA",_Data_Sectoral!$C$2:$C$20000,"cooling",_Data_Sectoral!$D$2:$D$20000,"TOTAL",_Data_Sectoral!$E$2:$E$20000,2037) -> 33.879265 | P70: =SUMIFS(_Data_Sectoral!$F$2:$F$20000,_Data_Sectoral!$A$2:$A$20000,"CA",_Data_Sectoral!$C$2:$C$20000,"cooling",_Data_Sectoral!$D$2:$D$20000,"TOTAL",_Data_Sectoral!$E$2:$E$20000,2038) -> 32.854976 | Q70: =SUMIFS(_Data_Sectoral!$F$2:$F$20000,_Data_Sectoral!$A$2:$A$20000,"CA",_Data_Sectoral!$C$2:$C$20000,"cooling",_Data_Sectoral!$D$2:$D$20000,"TOTAL",_Data_Sectoral!$E$2:$E$20000,2039) -> 34.758755 | R70: =SUMIFS(_Data_Sectoral!$F$2:$F$20000,_Data_Sectoral!$A$2:$A$20000,"CA",_Data_Sectoral!$C$2:$C$20000,"cooling",_Data_Sectoral!$D$2:$D$20000,"TOTAL",_Data_Sectoral!$E$2:$E$20000,2040) -> 36.783259
A71: Industry | B71: =SUMIFS(_Data_Sectoral!$F$2:$F$20000,_Data_Sectoral!$A$2:$A$20000,"CA",_Data_Sectoral!$C$2:$C$20000,"industry",_Data_Sectoral!$D$2:$D$20000,"TOTAL",_Data_Sectoral!$E$2:$E$20000,2024) -> 226.8503 | C71: =SUMIFS(_Data_Sectoral!$F$2:$F$20000,_Data_Sectoral!$A$2:$A$20000,"CA",_Data_Sectoral!$C$2:$C$20000,"industry",_Data_Sectoral!$D$2:$D$20000,"TOTAL",_Data_Sectoral!$E$2:$E$20000,2025) -> 225.58987 | D71: =SUMIFS(_Data_Sectoral!$F$2:$F$20000,_Data_Sectoral!$A$2:$A$20000,"CA",_Data_Sectoral!$C$2:$C$20000,"industry",_Data_Sectoral!$D$2:$D$20000,"TOTAL",_Data_Sectoral!$E$2:$E$20000,2026) -> 221.79596 | E71: =SUMIFS(_Data_Sectoral!$F$2:$F$20000,_Data_Sectoral!$A$2:$A$20000,"CA",_Data_Sectoral!$C$2:$C$20000,"industry",_Data_Sectoral!$D$2:$D$20000,"TOTAL",_Data_Sectoral!$E$2:$E$20000,2027) -> 226.46276 | F71: =SUMIFS(_Data_Sectoral!$F$2:$F$20000,_Data_Sectoral!$A$2:$A$20000,"CA",_Data_Sectoral!$C$2:$C$20000,"industry",_Data_Sectoral!$D$2:$D$20000,"TOTAL",_Data_Sectoral!$E$2:$E$20000,2028) -> 229.82444 | G71: =SUMIFS(_Data_Sectoral!$F$2:$F$20000,_Data_Sectoral!$A$2:$A$20000,"CA",_Data_Sectoral!$C$2:$C$20000,"industry",_Data_Sectoral!$D$2:$D$20000,"TOTAL",_Data_Sectoral!$E$2:$E$20000,2029) -> 230.50223 | H71: =SUMIFS(_Data_Sectoral!$F$2:$F$20000,_Data_Sectoral!$A$2:$A$20000,"CA",_Data_Sectoral!$C$2:$C$20000,"industry",_Data_Sectoral!$D$2:$D$20000,"TOTAL",_Data_Sectoral!$E$2:$E$20000,2030) -> 231.45831 | I71: =SUMIFS(_Data_Sectoral!$F$2:$F$20000,_Data_Sectoral!$A$2:$A$20000,"CA",_Data_Sectoral!$C$2:$C$20000,"industry",_Data_Sectoral!$D$2:$D$20000,"TOTAL",_Data_Sectoral!$E$2:$E$20000,2031) -> 232.40533 | J71: =SUMIFS(_Data_Sectoral!$F$2:$F$20000,_Data_Sectoral!$A$2:$A$20000,"CA",_Data_Sectoral!$C$2:$C$20000,"industry",_Data_Sectoral!$D$2:$D$20000,"TOTAL",_Data_Sectoral!$E$2:$E$20000,2032) -> 233.9013 | K71: =SUMIFS(_Data_Sectoral!$F$2:$F$20000,_Data_Sectoral!$A$2:$A$20000,"CA",_Data_Sectoral!$C$2:$C$20000,"industry",_Data_Sectoral!$D$2:$D$20000,"TOTAL",_Data_Sectoral!$E$2:$E$20000,2033) -> 234.96096 | L71: =SUMIFS(_Data_Sectoral!$F$2:$F$20000,_Data_Sectoral!$A$2:$A$20000,"CA",_Data_Sectoral!$C$2:$C$20000,"industry",_Data_Sectoral!$D$2:$D$20000,"TOTAL",_Data_Sectoral!$E$2:$E$20000,2034) -> 235.63486 | M71: =SUMIFS(_Data_Sectoral!$F$2:$F$20000,_Data_Sectoral!$A$2:$A$20000,"CA",_Data_Sectoral!$C$2:$C$20000,"industry",_Data_Sectoral!$D$2:$D$20000,"TOTAL",_Data_Sectoral!$E$2:$E$20000,2035) -> 236.10445 | N71: =SUMIFS(_Data_Sectoral!$F$2:$F$20000,_Data_Sectoral!$A$2:$A$20000,"CA",_Data_Sectoral!$C$2:$C$20000,"industry",_Data_Sectoral!$D$2:$D$20000,"TOTAL",_Data_Sectoral!$E$2:$E$20000,2036) -> 236.72579 | O71: =SUMIFS(_Data_Sectoral!$F$2:$F$20000,_Data_Sectoral!$A$2:$A$20000,"CA",_Data_Sectoral!$C$2:$C$20000,"industry",_Data_Sectoral!$D$2:$D$20000,"TOTAL",_Data_Sectoral!$E$2:$E$20000,2037) -> 237.15211 | P71: =SUMIFS(_Data_Sectoral!$F$2:$F$20000,_Data_Sectoral!$A$2:$A$20000,"CA",_Data_Sectoral!$C$2:$C$20000,"industry",_Data_Sectoral!$D$2:$D$20000,"TOTAL",_Data_Sectoral!$E$2:$E$20000,2038) -> 237.80754 | Q71: =SUMIFS(_Data_Sectoral!$F$2:$F$20000,_Data_Sectoral!$A$2:$A$20000,"CA",_Data_Sectoral!$C$2:$C$20000,"industry",_Data_Sectoral!$D$2:$D$20000,"TOTAL",_Data_Sectoral!$E$2:$E$20000,2039) -> 238.35615 | R71: =SUMIFS(_Data_Sectoral!$F$2:$F$20000,_Data_Sectoral!$A$2:$A$20000,"CA",_Data_Sectoral!$C$2:$C$20000,"industry",_Data_Sectoral!$D$2:$D$20000,"TOTAL",_Data_Sectoral!$E$2:$E$20000,2040) -> 238.98626
A72: Data Centers | B72: =SUMIFS(_Data_Sectoral!$F$2:$F$20000,_Data_Sectoral!$A$2:$A$20000,"CA",_Data_Sectoral!$C$2:$C$20000,"data_centers",_Data_Sectoral!$D$2:$D$20000,"TOTAL",_Data_Sectoral!$E$2:$E$20000,2024) -> 9.3075 | C72: =SUMIFS(_Data_Sectoral!$F$2:$F$20000,_Data_Sectoral!$A$2:$A$20000,"CA",_Data_Sectoral!$C$2:$C$20000,"data_centers",_Data_Sectoral!$D$2:$D$20000,"TOTAL",_Data_Sectoral!$E$2:$E$20000,2025) -> 16.580499 | D72: =SUMIFS(_Data_Sectoral!$F$2:$F$20000,_Data_Sectoral!$A$2:$A$20000,"CA",_Data_Sectoral!$C$2:$C$20000,"data_centers",_Data_Sectoral!$D$2:$D$20000,"TOTAL",_Data_Sectoral!$E$2:$E$20000,2026) -> 26.580459 | E72: =SUMIFS(_Data_Sectoral!$F$2:$F$20000,_Data_Sectoral!$A$2:$A$20000,"CA",_Data_Sectoral!$C$2:$C$20000,"data_centers",_Data_Sectoral!$D$2:$D$20000,"TOTAL",_Data_Sectoral!$E$2:$E$20000,2027) -> 36.836691 | F72: =SUMIFS(_Data_Sectoral!$F$2:$F$20000,_Data_Sectoral!$A$2:$A$20000,"CA",_Data_Sectoral!$C$2:$C$20000,"data_centers",_Data_Sectoral!$D$2:$D$20000,"TOTAL",_Data_Sectoral!$E$2:$E$20000,2028) -> 47.552795 | G72: =SUMIFS(_Data_Sectoral!$F$2:$F$20000,_Data_Sectoral!$A$2:$A$20000,"CA",_Data_Sectoral!$C$2:$C$20000,"data_centers",_Data_Sectoral!$D$2:$D$20000,"TOTAL",_Data_Sectoral!$E$2:$E$20000,2029) -> 61.68001 | H72: =SUMIFS(_Data_Sectoral!$F$2:$F$20000,_Data_Sectoral!$A$2:$A$20000,"CA",_Data_Sectoral!$C$2:$C$20000,"data_centers",_Data_Sectoral!$D$2:$D$20000,"TOTAL",_Data_Sectoral!$E$2:$E$20000,2030) -> 79.174316 | I72: =SUMIFS(_Data_Sectoral!$F$2:$F$20000,_Data_Sectoral!$A$2:$A$20000,"CA",_Data_Sectoral!$C$2:$C$20000,"data_centers",_Data_Sectoral!$D$2:$D$20000,"TOTAL",_Data_Sectoral!$E$2:$E$20000,2031) -> 110.36456 | J72: =SUMIFS(_Data_Sectoral!$F$2:$F$20000,_Data_Sectoral!$A$2:$A$20000,"CA",_Data_Sectoral!$C$2:$C$20000,"data_centers",_Data_Sectoral!$D$2:$D$20000,"TOTAL",_Data_Sectoral!$E$2:$E$20000,2032) -> 143.93096 | K72: =SUMIFS(_Data_Sectoral!$F$2:$F$20000,_Data_Sectoral!$A$2:$A$20000,"CA",_Data_Sectoral!$C$2:$C$20000,"data_centers",_Data_Sectoral!$D$2:$D$20000,"TOTAL",_Data_Sectoral!$E$2:$E$20000,2033) -> 175.49548 | L72: =SUMIFS(_Data_Sectoral!$F$2:$F$20000,_Data_Sectoral!$A$2:$A$20000,"CA",_Data_Sectoral!$C$2:$C$20000,"data_centers",_Data_Sectoral!$D$2:$D$20000,"TOTAL",_Data_Sectoral!$E$2:$E$20000,2034) -> 196.4676 | M72: =SUMIFS(_Data_Sectoral!$F$2:$F$20000,_Data_Sectoral!$A$2:$A$20000,"CA",_Data_Sectoral!$C$2:$C$20000,"data_centers",_Data_Sectoral!$D$2:$D$20000,"TOTAL",_Data_Sectoral!$E$2:$E$20000,2035) -> 219.54777 | N72: =SUMIFS(_Data_Sectoral!$F$2:$F$20000,_Data_Sectoral!$A$2:$A$20000,"CA",_Data_Sectoral!$C$2:$C$20000,"data_centers",_Data_Sectoral!$D$2:$D$20000,"TOTAL",_Data_Sectoral!$E$2:$E$20000,2036) -> 242.03527 | O72: =SUMIFS(_Data_Sectoral!$F$2:$F$20000,_Data_Sectoral!$A$2:$A$20000,"CA",_Data_Sectoral!$C$2:$C$20000,"data_centers",_Data_Sectoral!$D$2:$D$20000,"TOTAL",_Data_Sectoral!$E$2:$E$20000,2037) -> 267.66253 | P72: =SUMIFS(_Data_Sectoral!$F$2:$F$20000,_Data_Sectoral!$A$2:$A$20000,"CA",_Data_Sectoral!$C$2:$C$20000,"data_centers",_Data_Sectoral!$D$2:$D$20000,"TOTAL",_Data_Sectoral!$E$2:$E$20000,2038) -> 292.47758 | Q72: =SUMIFS(_Data_Sectoral!$F$2:$F$20000,_Data_Sectoral!$A$2:$A$20000,"CA",_Data_Sectoral!$C$2:$C$20000,"data_centers",_Data_Sectoral!$D$2:$D$20000,"TOTAL",_Data_Sectoral!$E$2:$E$20000,2039) -> 311.49385 | R72: =SUMIFS(_Data_Sectoral!$F$2:$F$20000,_Data_Sectoral!$A$2:$A$20000,"CA",_Data_Sectoral!$C$2:$C$20000,"data_centers",_Data_Sectoral!$D$2:$D$20000,"TOTAL",_Data_Sectoral!$E$2:$E$20000,2040) -> 332.349
A73: Hydrogen | B73: =SUMIFS(_Data_Sectoral!$F$2:$F$20000,_Data_Sectoral!$A$2:$A$20000,"CA",_Data_Sectoral!$C$2:$C$20000,"hydrogen",_Data_Sectoral!$D$2:$D$20000,"TOTAL",_Data_Sectoral!$E$2:$E$20000,2024) -> 0 | C73: =SUMIFS(_Data_Sectoral!$F$2:$F$20000,_Data_Sectoral!$A$2:$A$20000,"CA",_Data_Sectoral!$C$2:$C$20000,"hydrogen",_Data_Sectoral!$D$2:$D$20000,"TOTAL",_Data_Sectoral!$E$2:$E$20000,2025) -> 0 | D73: =SUMIFS(_Data_Sectoral!$F$2:$F$20000,_Data_Sectoral!$A$2:$A$20000,"CA",_Data_Sectoral!$C$2:$C$20000,"hydrogen",_Data_Sectoral!$D$2:$D$20000,"TOTAL",_Data_Sectoral!$E$2:$E$20000,2026) -> 0.33288 | E73: =SUMIFS(_Data_Sectoral!$F$2:$F$20000,_Data_Sectoral!$A$2:$A$20000,"CA",_Data_Sectoral!$C$2:$C$20000,"hydrogen",_Data_Sectoral!$D$2:$D$20000,"TOTAL",_Data_Sectoral!$E$2:$E$20000,2027) -> 0.68328 | F73: =SUMIFS(_Data_Sectoral!$F$2:$F$20000,_Data_Sectoral!$A$2:$A$20000,"CA",_Data_Sectoral!$C$2:$C$20000,"hydrogen",_Data_Sectoral!$D$2:$D$20000,"TOTAL",_Data_Sectoral!$E$2:$E$20000,2028) -> 1.36656 | G73: =SUMIFS(_Data_Sectoral!$F$2:$F$20000,_Data_Sectoral!$A$2:$A$20000,"CA",_Data_Sectoral!$C$2:$C$20000,"hydrogen",_Data_Sectoral!$D$2:$D$20000,"TOTAL",_Data_Sectoral!$E$2:$E$20000,2029) -> 2.39148 | H73: =SUMIFS(_Data_Sectoral!$F$2:$F$20000,_Data_Sectoral!$A$2:$A$20000,"CA",_Data_Sectoral!$C$2:$C$20000,"hydrogen",_Data_Sectoral!$D$2:$D$20000,"TOTAL",_Data_Sectoral!$E$2:$E$20000,2030) -> 2.5404 | I73: =SUMIFS(_Data_Sectoral!$F$2:$F$20000,_Data_Sectoral!$A$2:$A$20000,"CA",_Data_Sectoral!$C$2:$C$20000,"hydrogen",_Data_Sectoral!$D$2:$D$20000,"TOTAL",_Data_Sectoral!$E$2:$E$20000,2031) -> 2.99592 | J73: =SUMIFS(_Data_Sectoral!$F$2:$F$20000,_Data_Sectoral!$A$2:$A$20000,"CA",_Data_Sectoral!$C$2:$C$20000,"hydrogen",_Data_Sectoral!$D$2:$D$20000,"TOTAL",_Data_Sectoral!$E$2:$E$20000,2032) -> 3.49524 | K73: =SUMIFS(_Data_Sectoral!$F$2:$F$20000,_Data_Sectoral!$A$2:$A$20000,"CA",_Data_Sectoral!$C$2:$C$20000,"hydrogen",_Data_Sectoral!$D$2:$D$20000,"TOTAL",_Data_Sectoral!$E$2:$E$20000,2033) -> 4.06464 | L73: =SUMIFS(_Data_Sectoral!$F$2:$F$20000,_Data_Sectoral!$A$2:$A$20000,"CA",_Data_Sectoral!$C$2:$C$20000,"hydrogen",_Data_Sectoral!$D$2:$D$20000,"TOTAL",_Data_Sectoral!$E$2:$E$20000,2034) -> 4.65156 | M73: =SUMIFS(_Data_Sectoral!$F$2:$F$20000,_Data_Sectoral!$A$2:$A$20000,"CA",_Data_Sectoral!$C$2:$C$20000,"hydrogen",_Data_Sectoral!$D$2:$D$20000,"TOTAL",_Data_Sectoral!$E$2:$E$20000,2035) -> 5.256 | N73: =SUMIFS(_Data_Sectoral!$F$2:$F$20000,_Data_Sectoral!$A$2:$A$20000,"CA",_Data_Sectoral!$C$2:$C$20000,"hydrogen",_Data_Sectoral!$D$2:$D$20000,"TOTAL",_Data_Sectoral!$E$2:$E$20000,2036) -> 5.87796 | O73: =SUMIFS(_Data_Sectoral!$F$2:$F$20000,_Data_Sectoral!$A$2:$A$20000,"CA",_Data_Sectoral!$C$2:$C$20000,"hydrogen",_Data_Sectoral!$D$2:$D$20000,"TOTAL",_Data_Sectoral!$E$2:$E$20000,2037) -> 6.51744 | P73: =SUMIFS(_Data_Sectoral!$F$2:$F$20000,_Data_Sectoral!$A$2:$A$20000,"CA",_Data_Sectoral!$C$2:$C$20000,"hydrogen",_Data_Sectoral!$D$2:$D$20000,"TOTAL",_Data_Sectoral!$E$2:$E$20000,2038) -> 7.17444 | Q73: =SUMIFS(_Data_Sectoral!$F$2:$F$20000,_Data_Sectoral!$A$2:$A$20000,"CA",_Data_Sectoral!$C$2:$C$20000,"hydrogen",_Data_Sectoral!$D$2:$D$20000,"TOTAL",_Data_Sectoral!$E$2:$E$20000,2039) -> 7.84896 | R73: =SUMIFS(_Data_Sectoral!$F$2:$F$20000,_Data_Sectoral!$A$2:$A$20000,"CA",_Data_Sectoral!$C$2:$C$20000,"hydrogen",_Data_Sectoral!$D$2:$D$20000,"TOTAL",_Data_Sectoral!$E$2:$E$20000,2040) -> 8.541
A74: Total | B74: =SUM(B68:B73) -> 580.75687 | C74: =SUM(C68:C73) -> 588.9178 | D74: =SUM(D68:D73) -> 598.53716 | E74: =SUM(E68:E73) -> 617.21762 | F74: =SUM(F68:F73) -> 635.49902 | G74: =SUM(G68:G73) -> 655.45223 | H74: =SUM(H68:H73) -> 677.87219 | I74: =SUM(I68:I73) -> 714.47069 | ... R74: =SUM(R68:R73) -> 1007.8882
A76: United States
A77: Sector | B77: 2024 | C77: 2025 | D77: 2026 | E77: 2027 | F77: 2028 | G77: 2029 | H77: 2030 | I77: 2031 | J77: 2032 | K77: 2033 | L77: 2034 | M77: 2035 | N77: 2036 | O77: 2037 | P77: 2038 | Q77: 2039 | R77: 2040
A78: Transport | B78: =SUMIFS(_Data_Sectoral!$F$2:$F$20000,_Data_Sectoral!$A$2:$A$20000,"US",_Data_Sectoral!$C$2:$C$20000,"transport",_Data_Sectoral!$D$2:$D$20000,"TOTAL",_Data_Sectoral!$E$2:$E$20000,2024) -> 23.534897 | C78: =SUMIFS(_Data_Sectoral!$F$2:$F$20000,_Data_Sectoral!$A$2:$A$20000,"US",_Data_Sectoral!$C$2:$C$20000,"transport",_Data_Sectoral!$D$2:$D$20000,"TOTAL",_Data_Sectoral!$E$2:$E$20000,2025) -> 44.34878 | D78: =SUMIFS(_Data_Sectoral!$F$2:$F$20000,_Data_Sectoral!$A$2:$A$20000,"US",_Data_Sectoral!$C$2:$C$20000,"transport",_Data_Sectoral!$D$2:$D$20000,"TOTAL",_Data_Sectoral!$E$2:$E$20000,2026) -> 52.323662 | E78: =SUMIFS(_Data_Sectoral!$F$2:$F$20000,_Data_Sectoral!$A$2:$A$20000,"US",_Data_Sectoral!$C$2:$C$20000,"transport",_Data_Sectoral!$D$2:$D$20000,"TOTAL",_Data_Sectoral!$E$2:$E$20000,2027) -> 62.734641 | F78: =SUMIFS(_Data_Sectoral!$F$2:$F$20000,_Data_Sectoral!$A$2:$A$20000,"US",_Data_Sectoral!$C$2:$C$20000,"transport",_Data_Sectoral!$D$2:$D$20000,"TOTAL",_Data_Sectoral!$E$2:$E$20000,2028) -> 75.903218 | G78: =SUMIFS(_Data_Sectoral!$F$2:$F$20000,_Data_Sectoral!$A$2:$A$20000,"US",_Data_Sectoral!$C$2:$C$20000,"transport",_Data_Sectoral!$D$2:$D$20000,"TOTAL",_Data_Sectoral!$E$2:$E$20000,2029) -> 91.991512 | H78: =SUMIFS(_Data_Sectoral!$F$2:$F$20000,_Data_Sectoral!$A$2:$A$20000,"US",_Data_Sectoral!$C$2:$C$20000,"transport",_Data_Sectoral!$D$2:$D$20000,"TOTAL",_Data_Sectoral!$E$2:$E$20000,2030) -> 112.13051 | I78: =SUMIFS(_Data_Sectoral!$F$2:$F$20000,_Data_Sectoral!$A$2:$A$20000,"US",_Data_Sectoral!$C$2:$C$20000,"transport",_Data_Sectoral!$D$2:$D$20000,"TOTAL",_Data_Sectoral!$E$2:$E$20000,2031) -> 137.02456 | J78: =SUMIFS(_Data_Sectoral!$F$2:$F$20000,_Data_Sectoral!$A$2:$A$20000,"US",_Data_Sectoral!$C$2:$C$20000,"transport",_Data_Sectoral!$D$2:$D$20000,"TOTAL",_Data_Sectoral!$E$2:$E$20000,2032) -> 165.67794 | K78: =SUMIFS(_Data_Sectoral!$F$2:$F$20000,_Data_Sectoral!$A$2:$A$20000,"US",_Data_Sectoral!$C$2:$C$20000,"transport",_Data_Sectoral!$D$2:$D$20000,"TOTAL",_Data_Sectoral!$E$2:$E$20000,2033) -> 201.47718 | L78: =SUMIFS(_Data_Sectoral!$F$2:$F$20000,_Data_Sectoral!$A$2:$A$20000,"US",_Data_Sectoral!$C$2:$C$20000,"transport",_Data_Sectoral!$D$2:$D$20000,"TOTAL",_Data_Sectoral!$E$2:$E$20000,2034) -> 238.65988 | M78: =SUMIFS(_Data_Sectoral!$F$2:$F$20000,_Data_Sectoral!$A$2:$A$20000,"US",_Data_Sectoral!$C$2:$C$20000,"transport",_Data_Sectoral!$D$2:$D$20000,"TOTAL",_Data_Sectoral!$E$2:$E$20000,2035) -> 280.28723 | N78: =SUMIFS(_Data_Sectoral!$F$2:$F$20000,_Data_Sectoral!$A$2:$A$20000,"US",_Data_Sectoral!$C$2:$C$20000,"transport",_Data_Sectoral!$D$2:$D$20000,"TOTAL",_Data_Sectoral!$E$2:$E$20000,2036) -> 326.27798 | O78: =SUMIFS(_Data_Sectoral!$F$2:$F$20000,_Data_Sectoral!$A$2:$A$20000,"US",_Data_Sectoral!$C$2:$C$20000,"transport",_Data_Sectoral!$D$2:$D$20000,"TOTAL",_Data_Sectoral!$E$2:$E$20000,2037) -> 372.50398 | P78: =SUMIFS(_Data_Sectoral!$F$2:$F$20000,_Data_Sectoral!$A$2:$A$20000,"US",_Data_Sectoral!$C$2:$C$20000,"transport",_Data_Sectoral!$D$2:$D$20000,"TOTAL",_Data_Sectoral!$E$2:$E$20000,2038) -> 421.94943 | Q78: =SUMIFS(_Data_Sectoral!$F$2:$F$20000,_Data_Sectoral!$A$2:$A$20000,"US",_Data_Sectoral!$C$2:$C$20000,"transport",_Data_Sectoral!$D$2:$D$20000,"TOTAL",_Data_Sectoral!$E$2:$E$20000,2039) -> 474.55352 | R78: =SUMIFS(_Data_Sectoral!$F$2:$F$20000,_Data_Sectoral!$A$2:$A$20000,"US",_Data_Sectoral!$C$2:$C$20000,"transport",_Data_Sectoral!$D$2:$D$20000,"TOTAL",_Data_Sectoral!$E$2:$E$20000,2040) -> 531.33131
A79: Buildings | B79: =SUMIFS(_Data_Sectoral!$F$2:$F$20000,_Data_Sectoral!$A$2:$A$20000,"US",_Data_Sectoral!$C$2:$C$20000,"buildings",_Data_Sectoral!$D$2:$D$20000,"TOTAL",_Data_Sectoral!$E$2:$E$20000,2024) -> 2398.7143 | C79: =SUMIFS(_Data_Sectoral!$F$2:$F$20000,_Data_Sectoral!$A$2:$A$20000,"US",_Data_Sectoral!$C$2:$C$20000,"buildings",_Data_Sectoral!$D$2:$D$20000,"TOTAL",_Data_Sectoral!$E$2:$E$20000,2025) -> 2411.4412 | D79: =SUMIFS(_Data_Sectoral!$F$2:$F$20000,_Data_Sectoral!$A$2:$A$20000,"US",_Data_Sectoral!$C$2:$C$20000,"buildings",_Data_Sectoral!$D$2:$D$20000,"TOTAL",_Data_Sectoral!$E$2:$E$20000,2026) -> 2415.1282 | E79: =SUMIFS(_Data_Sectoral!$F$2:$F$20000,_Data_Sectoral!$A$2:$A$20000,"US",_Data_Sectoral!$C$2:$C$20000,"buildings",_Data_Sectoral!$D$2:$D$20000,"TOTAL",_Data_Sectoral!$E$2:$E$20000,2027) -> 2418.1789 | F79: =SUMIFS(_Data_Sectoral!$F$2:$F$20000,_Data_Sectoral!$A$2:$A$20000,"US",_Data_Sectoral!$C$2:$C$20000,"buildings",_Data_Sectoral!$D$2:$D$20000,"TOTAL",_Data_Sectoral!$E$2:$E$20000,2028) -> 2419.7014 | G79: =SUMIFS(_Data_Sectoral!$F$2:$F$20000,_Data_Sectoral!$A$2:$A$20000,"US",_Data_Sectoral!$C$2:$C$20000,"buildings",_Data_Sectoral!$D$2:$D$20000,"TOTAL",_Data_Sectoral!$E$2:$E$20000,2029) -> 2421.0509 | H79: =SUMIFS(_Data_Sectoral!$F$2:$F$20000,_Data_Sectoral!$A$2:$A$20000,"US",_Data_Sectoral!$C$2:$C$20000,"buildings",_Data_Sectoral!$D$2:$D$20000,"TOTAL",_Data_Sectoral!$E$2:$E$20000,2030) -> 2419.2698 | I79: =SUMIFS(_Data_Sectoral!$F$2:$F$20000,_Data_Sectoral!$A$2:$A$20000,"US",_Data_Sectoral!$C$2:$C$20000,"buildings",_Data_Sectoral!$D$2:$D$20000,"TOTAL",_Data_Sectoral!$E$2:$E$20000,2031) -> 2453.576 | J79: =SUMIFS(_Data_Sectoral!$F$2:$F$20000,_Data_Sectoral!$A$2:$A$20000,"US",_Data_Sectoral!$C$2:$C$20000,"buildings",_Data_Sectoral!$D$2:$D$20000,"TOTAL",_Data_Sectoral!$E$2:$E$20000,2032) -> 2488.1029 | K79: =SUMIFS(_Data_Sectoral!$F$2:$F$20000,_Data_Sectoral!$A$2:$A$20000,"US",_Data_Sectoral!$C$2:$C$20000,"buildings",_Data_Sectoral!$D$2:$D$20000,"TOTAL",_Data_Sectoral!$E$2:$E$20000,2033) -> 2523.8996 | L79: =SUMIFS(_Data_Sectoral!$F$2:$F$20000,_Data_Sectoral!$A$2:$A$20000,"US",_Data_Sectoral!$C$2:$C$20000,"buildings",_Data_Sectoral!$D$2:$D$20000,"TOTAL",_Data_Sectoral!$E$2:$E$20000,2034) -> 2556.9936 | M79: =SUMIFS(_Data_Sectoral!$F$2:$F$20000,_Data_Sectoral!$A$2:$A$20000,"US",_Data_Sectoral!$C$2:$C$20000,"buildings",_Data_Sectoral!$D$2:$D$20000,"TOTAL",_Data_Sectoral!$E$2:$E$20000,2035) -> 2592.1505 | N79: =SUMIFS(_Data_Sectoral!$F$2:$F$20000,_Data_Sectoral!$A$2:$A$20000,"US",_Data_Sectoral!$C$2:$C$20000,"buildings",_Data_Sectoral!$D$2:$D$20000,"TOTAL",_Data_Sectoral!$E$2:$E$20000,2036) -> 2628.385 | O79: =SUMIFS(_Data_Sectoral!$F$2:$F$20000,_Data_Sectoral!$A$2:$A$20000,"US",_Data_Sectoral!$C$2:$C$20000,"buildings",_Data_Sectoral!$D$2:$D$20000,"TOTAL",_Data_Sectoral!$E$2:$E$20000,2037) -> 2664.0511 | P79: =SUMIFS(_Data_Sectoral!$F$2:$F$20000,_Data_Sectoral!$A$2:$A$20000,"US",_Data_Sectoral!$C$2:$C$20000,"buildings",_Data_Sectoral!$D$2:$D$20000,"TOTAL",_Data_Sectoral!$E$2:$E$20000,2038) -> 2699.8743 | Q79: =SUMIFS(_Data_Sectoral!$F$2:$F$20000,_Data_Sectoral!$A$2:$A$20000,"US",_Data_Sectoral!$C$2:$C$20000,"buildings",_Data_Sectoral!$D$2:$D$20000,"TOTAL",_Data_Sectoral!$E$2:$E$20000,2039) -> 2736.5104 | R79: =SUMIFS(_Data_Sectoral!$F$2:$F$20000,_Data_Sectoral!$A$2:$A$20000,"US",_Data_Sectoral!$C$2:$C$20000,"buildings",_Data_Sectoral!$D$2:$D$20000,"TOTAL",_Data_Sectoral!$E$2:$E$20000,2040) -> 2777.1962
A80: Cooling | B80: =SUMIFS(_Data_Sectoral!$F$2:$F$20000,_Data_Sectoral!$A$2:$A$20000,"US",_Data_Sectoral!$C$2:$C$20000,"cooling",_Data_Sectoral!$D$2:$D$20000,"TOTAL",_Data_Sectoral!$E$2:$E$20000,2024) -> 404.90694 | C80: =SUMIFS(_Data_Sectoral!$F$2:$F$20000,_Data_Sectoral!$A$2:$A$20000,"US",_Data_Sectoral!$C$2:$C$20000,"cooling",_Data_Sectoral!$D$2:$D$20000,"TOTAL",_Data_Sectoral!$E$2:$E$20000,2025) -> 410.1226 | D80: =SUMIFS(_Data_Sectoral!$F$2:$F$20000,_Data_Sectoral!$A$2:$A$20000,"US",_Data_Sectoral!$C$2:$C$20000,"cooling",_Data_Sectoral!$D$2:$D$20000,"TOTAL",_Data_Sectoral!$E$2:$E$20000,2026) -> 420.32601 | E80: =SUMIFS(_Data_Sectoral!$F$2:$F$20000,_Data_Sectoral!$A$2:$A$20000,"US",_Data_Sectoral!$C$2:$C$20000,"cooling",_Data_Sectoral!$D$2:$D$20000,"TOTAL",_Data_Sectoral!$E$2:$E$20000,2027) -> 424.57178 | F80: =SUMIFS(_Data_Sectoral!$F$2:$F$20000,_Data_Sectoral!$A$2:$A$20000,"US",_Data_Sectoral!$C$2:$C$20000,"cooling",_Data_Sectoral!$D$2:$D$20000,"TOTAL",_Data_Sectoral!$E$2:$E$20000,2028) -> 437.24943 | G80: =SUMIFS(_Data_Sectoral!$F$2:$F$20000,_Data_Sectoral!$A$2:$A$20000,"US",_Data_Sectoral!$C$2:$C$20000,"cooling",_Data_Sectoral!$D$2:$D$20000,"TOTAL",_Data_Sectoral!$E$2:$E$20000,2029) -> 442.16679 | H80: =SUMIFS(_Data_Sectoral!$F$2:$F$20000,_Data_Sectoral!$A$2:$A$20000,"US",_Data_Sectoral!$C$2:$C$20000,"cooling",_Data_Sectoral!$D$2:$D$20000,"TOTAL",_Data_Sectoral!$E$2:$E$20000,2030) -> 450.01584 | I80: =SUMIFS(_Data_Sectoral!$F$2:$F$20000,_Data_Sectoral!$A$2:$A$20000,"US",_Data_Sectoral!$C$2:$C$20000,"cooling",_Data_Sectoral!$D$2:$D$20000,"TOTAL",_Data_Sectoral!$E$2:$E$20000,2031) -> 451.2225 | J80: =SUMIFS(_Data_Sectoral!$F$2:$F$20000,_Data_Sectoral!$A$2:$A$20000,"US",_Data_Sectoral!$C$2:$C$20000,"cooling",_Data_Sectoral!$D$2:$D$20000,"TOTAL",_Data_Sectoral!$E$2:$E$20000,2032) -> 466.52163 | K80: =SUMIFS(_Data_Sectoral!$F$2:$F$20000,_Data_Sectoral!$A$2:$A$20000,"US",_Data_Sectoral!$C$2:$C$20000,"cooling",_Data_Sectoral!$D$2:$D$20000,"TOTAL",_Data_Sectoral!$E$2:$E$20000,2033) -> 477.28115 | L80: =SUMIFS(_Data_Sectoral!$F$2:$F$20000,_Data_Sectoral!$A$2:$A$20000,"US",_Data_Sectoral!$C$2:$C$20000,"cooling",_Data_Sectoral!$D$2:$D$20000,"TOTAL",_Data_Sectoral!$E$2:$E$20000,2034) -> 489.39434 | M80: =SUMIFS(_Data_Sectoral!$F$2:$F$20000,_Data_Sectoral!$A$2:$A$20000,"US",_Data_Sectoral!$C$2:$C$20000,"cooling",_Data_Sectoral!$D$2:$D$20000,"TOTAL",_Data_Sectoral!$E$2:$E$20000,2035) -> 495.46407 | N80: =SUMIFS(_Data_Sectoral!$F$2:$F$20000,_Data_Sectoral!$A$2:$A$20000,"US",_Data_Sectoral!$C$2:$C$20000,"cooling",_Data_Sectoral!$D$2:$D$20000,"TOTAL",_Data_Sectoral!$E$2:$E$20000,2036) -> 501.49275 | O80: =SUMIFS(_Data_Sectoral!$F$2:$F$20000,_Data_Sectoral!$A$2:$A$20000,"US",_Data_Sectoral!$C$2:$C$20000,"cooling",_Data_Sectoral!$D$2:$D$20000,"TOTAL",_Data_Sectoral!$E$2:$E$20000,2037) -> 515.05673 | P80: =SUMIFS(_Data_Sectoral!$F$2:$F$20000,_Data_Sectoral!$A$2:$A$20000,"US",_Data_Sectoral!$C$2:$C$20000,"cooling",_Data_Sectoral!$D$2:$D$20000,"TOTAL",_Data_Sectoral!$E$2:$E$20000,2038) -> 522.4616 | Q80: =SUMIFS(_Data_Sectoral!$F$2:$F$20000,_Data_Sectoral!$A$2:$A$20000,"US",_Data_Sectoral!$C$2:$C$20000,"cooling",_Data_Sectoral!$D$2:$D$20000,"TOTAL",_Data_Sectoral!$E$2:$E$20000,2039) -> 538.64221 | R80: =SUMIFS(_Data_Sectoral!$F$2:$F$20000,_Data_Sectoral!$A$2:$A$20000,"US",_Data_Sectoral!$C$2:$C$20000,"cooling",_Data_Sectoral!$D$2:$D$20000,"TOTAL",_Data_Sectoral!$E$2:$E$20000,2040) -> 544.55492
A81: Industry | B81: =SUMIFS(_Data_Sectoral!$F$2:$F$20000,_Data_Sectoral!$A$2:$A$20000,"US",_Data_Sectoral!$C$2:$C$20000,"industry",_Data_Sectoral!$D$2:$D$20000,"TOTAL",_Data_Sectoral!$E$2:$E$20000,2024) -> 1199.1866 | C81: =SUMIFS(_Data_Sectoral!$F$2:$F$20000,_Data_Sectoral!$A$2:$A$20000,"US",_Data_Sectoral!$C$2:$C$20000,"industry",_Data_Sectoral!$D$2:$D$20000,"TOTAL",_Data_Sectoral!$E$2:$E$20000,2025) -> 1213.8624 | D81: =SUMIFS(_Data_Sectoral!$F$2:$F$20000,_Data_Sectoral!$A$2:$A$20000,"US",_Data_Sectoral!$C$2:$C$20000,"industry",_Data_Sectoral!$D$2:$D$20000,"TOTAL",_Data_Sectoral!$E$2:$E$20000,2026) -> 1223.2082 | E81: =SUMIFS(_Data_Sectoral!$F$2:$F$20000,_Data_Sectoral!$A$2:$A$20000,"US",_Data_Sectoral!$C$2:$C$20000,"industry",_Data_Sectoral!$D$2:$D$20000,"TOTAL",_Data_Sectoral!$E$2:$E$20000,2027) -> 1242.5585 | F81: =SUMIFS(_Data_Sectoral!$F$2:$F$20000,_Data_Sectoral!$A$2:$A$20000,"US",_Data_Sectoral!$C$2:$C$20000,"industry",_Data_Sectoral!$D$2:$D$20000,"TOTAL",_Data_Sectoral!$E$2:$E$20000,2028) -> 1259.7989 | G81: =SUMIFS(_Data_Sectoral!$F$2:$F$20000,_Data_Sectoral!$A$2:$A$20000,"US",_Data_Sectoral!$C$2:$C$20000,"industry",_Data_Sectoral!$D$2:$D$20000,"TOTAL",_Data_Sectoral!$E$2:$E$20000,2029) -> 1287.066 | H81: =SUMIFS(_Data_Sectoral!$F$2:$F$20000,_Data_Sectoral!$A$2:$A$20000,"US",_Data_Sectoral!$C$2:$C$20000,"industry",_Data_Sectoral!$D$2:$D$20000,"TOTAL",_Data_Sectoral!$E$2:$E$20000,2030) -> 1304.3772 | I81: =SUMIFS(_Data_Sectoral!$F$2:$F$20000,_Data_Sectoral!$A$2:$A$20000,"US",_Data_Sectoral!$C$2:$C$20000,"industry",_Data_Sectoral!$D$2:$D$20000,"TOTAL",_Data_Sectoral!$E$2:$E$20000,2031) -> 1341.5065 | J81: =SUMIFS(_Data_Sectoral!$F$2:$F$20000,_Data_Sectoral!$A$2:$A$20000,"US",_Data_Sectoral!$C$2:$C$20000,"industry",_Data_Sectoral!$D$2:$D$20000,"TOTAL",_Data_Sectoral!$E$2:$E$20000,2032) -> 1384.6911 | K81: =SUMIFS(_Data_Sectoral!$F$2:$F$20000,_Data_Sectoral!$A$2:$A$20000,"US",_Data_Sectoral!$C$2:$C$20000,"industry",_Data_Sectoral!$D$2:$D$20000,"TOTAL",_Data_Sectoral!$E$2:$E$20000,2033) -> 1426.4413 | L81: =SUMIFS(_Data_Sectoral!$F$2:$F$20000,_Data_Sectoral!$A$2:$A$20000,"US",_Data_Sectoral!$C$2:$C$20000,"industry",_Data_Sectoral!$D$2:$D$20000,"TOTAL",_Data_Sectoral!$E$2:$E$20000,2034) -> 1466.5583 | M81: =SUMIFS(_Data_Sectoral!$F$2:$F$20000,_Data_Sectoral!$A$2:$A$20000,"US",_Data_Sectoral!$C$2:$C$20000,"industry",_Data_Sectoral!$D$2:$D$20000,"TOTAL",_Data_Sectoral!$E$2:$E$20000,2035) -> 1510.314 | N81: =SUMIFS(_Data_Sectoral!$F$2:$F$20000,_Data_Sectoral!$A$2:$A$20000,"US",_Data_Sectoral!$C$2:$C$20000,"industry",_Data_Sectoral!$D$2:$D$20000,"TOTAL",_Data_Sectoral!$E$2:$E$20000,2036) -> 1544.1344 | O81: =SUMIFS(_Data_Sectoral!$F$2:$F$20000,_Data_Sectoral!$A$2:$A$20000,"US",_Data_Sectoral!$C$2:$C$20000,"industry",_Data_Sectoral!$D$2:$D$20000,"TOTAL",_Data_Sectoral!$E$2:$E$20000,2037) -> 1583.9506 | P81: =SUMIFS(_Data_Sectoral!$F$2:$F$20000,_Data_Sectoral!$A$2:$A$20000,"US",_Data_Sectoral!$C$2:$C$20000,"industry",_Data_Sectoral!$D$2:$D$20000,"TOTAL",_Data_Sectoral!$E$2:$E$20000,2038) -> 1622.8514 | Q81: =SUMIFS(_Data_Sectoral!$F$2:$F$20000,_Data_Sectoral!$A$2:$A$20000,"US",_Data_Sectoral!$C$2:$C$20000,"industry",_Data_Sectoral!$D$2:$D$20000,"TOTAL",_Data_Sectoral!$E$2:$E$20000,2039) -> 1662.1714 | R81: =SUMIFS(_Data_Sectoral!$F$2:$F$20000,_Data_Sectoral!$A$2:$A$20000,"US",_Data_Sectoral!$C$2:$C$20000,"industry",_Data_Sectoral!$D$2:$D$20000,"TOTAL",_Data_Sectoral!$E$2:$E$20000,2040) -> 1697.758
A82: Data Centers | B82: =SUMIFS(_Data_Sectoral!$F$2:$F$20000,_Data_Sectoral!$A$2:$A$20000,"US",_Data_Sectoral!$C$2:$C$20000,"data_centers",_Data_Sectoral!$D$2:$D$20000,"TOTAL",_Data_Sectoral!$E$2:$E$20000,2024) -> 126.8724 | C82: =SUMIFS(_Data_Sectoral!$F$2:$F$20000,_Data_Sectoral!$A$2:$A$20000,"US",_Data_Sectoral!$C$2:$C$20000,"data_centers",_Data_Sectoral!$D$2:$D$20000,"TOTAL",_Data_Sectoral!$E$2:$E$20000,2025) -> 128.26116 | D82: =SUMIFS(_Data_Sectoral!$F$2:$F$20000,_Data_Sectoral!$A$2:$A$20000,"US",_Data_Sectoral!$C$2:$C$20000,"data_centers",_Data_Sectoral!$D$2:$D$20000,"TOTAL",_Data_Sectoral!$E$2:$E$20000,2026) -> 184.43344 | E82: =SUMIFS(_Data_Sectoral!$F$2:$F$20000,_Data_Sectoral!$A$2:$A$20000,"US",_Data_Sectoral!$C$2:$C$20000,"data_centers",_Data_Sectoral!$D$2:$D$20000,"TOTAL",_Data_Sectoral!$E$2:$E$20000,2027) -> 311.36313 | F82: =SUMIFS(_Data_Sectoral!$F$2:$F$20000,_Data_Sectoral!$A$2:$A$20000,"US",_Data_Sectoral!$C$2:$C$20000,"data_centers",_Data_Sectoral!$D$2:$D$20000,"TOTAL",_Data_Sectoral!$E$2:$E$20000,2028) -> 460.82113 | G82: =SUMIFS(_Data_Sectoral!$F$2:$F$20000,_Data_Sectoral!$A$2:$A$20000,"US",_Data_Sectoral!$C$2:$C$20000,"data_centers",_Data_Sectoral!$D$2:$D$20000,"TOTAL",_Data_Sectoral!$E$2:$E$20000,2029) -> 624.72391 | H82: =SUMIFS(_Data_Sectoral!$F$2:$F$20000,_Data_Sectoral!$A$2:$A$20000,"US",_Data_Sectoral!$C$2:$C$20000,"data_centers",_Data_Sectoral!$D$2:$D$20000,"TOTAL",_Data_Sectoral!$E$2:$E$20000,2030) -> 820.87026 | I82: =SUMIFS(_Data_Sectoral!$F$2:$F$20000,_Data_Sectoral!$A$2:$A$20000,"US",_Data_Sectoral!$C$2:$C$20000,"data_centers",_Data_Sectoral!$D$2:$D$20000,"TOTAL",_Data_Sectoral!$E$2:$E$20000,2031) -> 1003.6303 | J82: =SUMIFS(_Data_Sectoral!$F$2:$F$20000,_Data_Sectoral!$A$2:$A$20000,"US",_Data_Sectoral!$C$2:$C$20000,"data_centers",_Data_Sectoral!$D$2:$D$20000,"TOTAL",_Data_Sectoral!$E$2:$E$20000,2032) -> 1173.8003 | K82: =SUMIFS(_Data_Sectoral!$F$2:$F$20000,_Data_Sectoral!$A$2:$A$20000,"US",_Data_Sectoral!$C$2:$C$20000,"data_centers",_Data_Sectoral!$D$2:$D$20000,"TOTAL",_Data_Sectoral!$E$2:$E$20000,2033) -> 1306.5567 | L82: =SUMIFS(_Data_Sectoral!$F$2:$F$20000,_Data_Sectoral!$A$2:$A$20000,"US",_Data_Sectoral!$C$2:$C$20000,"data_centers",_Data_Sectoral!$D$2:$D$20000,"TOTAL",_Data_Sectoral!$E$2:$E$20000,2034) -> 1462.5993 | M82: =SUMIFS(_Data_Sectoral!$F$2:$F$20000,_Data_Sectoral!$A$2:$A$20000,"US",_Data_Sectoral!$C$2:$C$20000,"data_centers",_Data_Sectoral!$D$2:$D$20000,"TOTAL",_Data_Sectoral!$E$2:$E$20000,2035) -> 1599.3003 | N82: =SUMIFS(_Data_Sectoral!$F$2:$F$20000,_Data_Sectoral!$A$2:$A$20000,"US",_Data_Sectoral!$C$2:$C$20000,"data_centers",_Data_Sectoral!$D$2:$D$20000,"TOTAL",_Data_Sectoral!$E$2:$E$20000,2036) -> 1737.1828 | O82: =SUMIFS(_Data_Sectoral!$F$2:$F$20000,_Data_Sectoral!$A$2:$A$20000,"US",_Data_Sectoral!$C$2:$C$20000,"data_centers",_Data_Sectoral!$D$2:$D$20000,"TOTAL",_Data_Sectoral!$E$2:$E$20000,2037) -> 1866.2307 | P82: =SUMIFS(_Data_Sectoral!$F$2:$F$20000,_Data_Sectoral!$A$2:$A$20000,"US",_Data_Sectoral!$C$2:$C$20000,"data_centers",_Data_Sectoral!$D$2:$D$20000,"TOTAL",_Data_Sectoral!$E$2:$E$20000,2038) -> 1982.6035 | Q82: =SUMIFS(_Data_Sectoral!$F$2:$F$20000,_Data_Sectoral!$A$2:$A$20000,"US",_Data_Sectoral!$C$2:$C$20000,"data_centers",_Data_Sectoral!$D$2:$D$20000,"TOTAL",_Data_Sectoral!$E$2:$E$20000,2039) -> 2082.5834 | R82: =SUMIFS(_Data_Sectoral!$F$2:$F$20000,_Data_Sectoral!$A$2:$A$20000,"US",_Data_Sectoral!$C$2:$C$20000,"data_centers",_Data_Sectoral!$D$2:$D$20000,"TOTAL",_Data_Sectoral!$E$2:$E$20000,2040) -> 2162.7628
A83: Hydrogen | B83: =SUMIFS(_Data_Sectoral!$F$2:$F$20000,_Data_Sectoral!$A$2:$A$20000,"US",_Data_Sectoral!$C$2:$C$20000,"hydrogen",_Data_Sectoral!$D$2:$D$20000,"TOTAL",_Data_Sectoral!$E$2:$E$20000,2024) -> 1.82 | C83: =SUMIFS(_Data_Sectoral!$F$2:$F$20000,_Data_Sectoral!$A$2:$A$20000,"US",_Data_Sectoral!$C$2:$C$20000,"hydrogen",_Data_Sectoral!$D$2:$D$20000,"TOTAL",_Data_Sectoral!$E$2:$E$20000,2025) -> 1.898 | D83: =SUMIFS(_Data_Sectoral!$F$2:$F$20000,_Data_Sectoral!$A$2:$A$20000,"US",_Data_Sectoral!$C$2:$C$20000,"hydrogen",_Data_Sectoral!$D$2:$D$20000,"TOTAL",_Data_Sectoral!$E$2:$E$20000,2026) -> 4.6968 | E83: =SUMIFS(_Data_Sectoral!$F$2:$F$20000,_Data_Sectoral!$A$2:$A$20000,"US",_Data_Sectoral!$C$2:$C$20000,"hydrogen",_Data_Sectoral!$D$2:$D$20000,"TOTAL",_Data_Sectoral!$E$2:$E$20000,2027) -> 7.1604 | F83: =SUMIFS(_Data_Sectoral!$F$2:$F$20000,_Data_Sectoral!$A$2:$A$20000,"US",_Data_Sectoral!$C$2:$C$20000,"hydrogen",_Data_Sectoral!$D$2:$D$20000,"TOTAL",_Data_Sectoral!$E$2:$E$20000,2028) -> 7.878 | G83: =SUMIFS(_Data_Sectoral!$F$2:$F$20000,_Data_Sectoral!$A$2:$A$20000,"US",_Data_Sectoral!$C$2:$C$20000,"hydrogen",_Data_Sectoral!$D$2:$D$20000,"TOTAL",_Data_Sectoral!$E$2:$E$20000,2029) -> 7.8 | H83: =SUMIFS(_Data_Sectoral!$F$2:$F$20000,_Data_Sectoral!$A$2:$A$20000,"US",_Data_Sectoral!$C$2:$C$20000,"hydrogen",_Data_Sectoral!$D$2:$D$20000,"TOTAL",_Data_Sectoral!$E$2:$E$20000,2030) -> 5.742 | I83: =SUMIFS(_Data_Sectoral!$F$2:$F$20000,_Data_Sectoral!$A$2:$A$20000,"US",_Data_Sectoral!$C$2:$C$20000,"hydrogen",_Data_Sectoral!$D$2:$D$20000,"TOTAL",_Data_Sectoral!$E$2:$E$20000,2031) -> 5.586 | J83: =SUMIFS(_Data_Sectoral!$F$2:$F$20000,_Data_Sectoral!$A$2:$A$20000,"US",_Data_Sectoral!$C$2:$C$20000,"hydrogen",_Data_Sectoral!$D$2:$D$20000,"TOTAL",_Data_Sectoral!$E$2:$E$20000,2032) -> 5.529 | K83: =SUMIFS(_Data_Sectoral!$F$2:$F$20000,_Data_Sectoral!$A$2:$A$20000,"US",_Data_Sectoral!$C$2:$C$20000,"hydrogen",_Data_Sectoral!$D$2:$D$20000,"TOTAL",_Data_Sectoral!$E$2:$E$20000,2033) -> 5.568 | L83: =SUMIFS(_Data_Sectoral!$F$2:$F$20000,_Data_Sectoral!$A$2:$A$20000,"US",_Data_Sectoral!$C$2:$C$20000,"hydrogen",_Data_Sectoral!$D$2:$D$20000,"TOTAL",_Data_Sectoral!$E$2:$E$20000,2034) -> 5.6168 | M83: =SUMIFS(_Data_Sectoral!$F$2:$F$20000,_Data_Sectoral!$A$2:$A$20000,"US",_Data_Sectoral!$C$2:$C$20000,"hydrogen",_Data_Sectoral!$D$2:$D$20000,"TOTAL",_Data_Sectoral!$E$2:$E$20000,2035) -> 5.652 | N83: =SUMIFS(_Data_Sectoral!$F$2:$F$20000,_Data_Sectoral!$A$2:$A$20000,"US",_Data_Sectoral!$C$2:$C$20000,"hydrogen",_Data_Sectoral!$D$2:$D$20000,"TOTAL",_Data_Sectoral!$E$2:$E$20000,2036) -> 5.6852 | O83: =SUMIFS(_Data_Sectoral!$F$2:$F$20000,_Data_Sectoral!$A$2:$A$20000,"US",_Data_Sectoral!$C$2:$C$20000,"hydrogen",_Data_Sectoral!$D$2:$D$20000,"TOTAL",_Data_Sectoral!$E$2:$E$20000,2037) -> 5.7288 | P83: =SUMIFS(_Data_Sectoral!$F$2:$F$20000,_Data_Sectoral!$A$2:$A$20000,"US",_Data_Sectoral!$C$2:$C$20000,"hydrogen",_Data_Sectoral!$D$2:$D$20000,"TOTAL",_Data_Sectoral!$E$2:$E$20000,2038) -> 5.7582 | Q83: =SUMIFS(_Data_Sectoral!$F$2:$F$20000,_Data_Sectoral!$A$2:$A$20000,"US",_Data_Sectoral!$C$2:$C$20000,"hydrogen",_Data_Sectoral!$D$2:$D$20000,"TOTAL",_Data_Sectoral!$E$2:$E$20000,2039) -> 5.7984 | R83: =SUMIFS(_Data_Sectoral!$F$2:$F$20000,_Data_Sectoral!$A$2:$A$20000,"US",_Data_Sectoral!$C$2:$C$20000,"hydrogen",_Data_Sectoral!$D$2:$D$20000,"TOTAL",_Data_Sectoral!$E$2:$E$20000,2040) -> 5.824
A84: Total | B84: =SUM(B78:B83) -> 4155.0351 | C84: =SUM(C78:C83) -> 4209.9341 | D84: =SUM(D78:D83) -> 4300.1163 | E84: =SUM(E78:E83) -> 4466.5673 | F84: =SUM(F78:F83) -> 4661.3521 | G84: =SUM(G78:G83) -> 4874.7992 | H84: =SUM(H78:H83) -> 5112.4056 | I84: =SUM(I78:I83) -> 5392.5459 | ... R84: =SUM(R78:R83) -> 7719.4272

Sheet _Data_Sectoral
A1: geo_code | B1: geo_name | C1: sector | D1: sub_segment | E1: year | F1: demand_twh | G1: scenario
A2: CA | B2: Canada | C2: buildings | D2: Electric_Boiler | E2: 2024 | F2: 0 | G2: FEL 2026 | Base FEL | Base
A3: CA | B3: Canada | C3: buildings | D3: Electric_Boiler | E3: 2025 | F3: 0 | G3: FEL 2026 | Base FEL | Base
A4: CA | B4: Canada | C4: buildings | D4: Electric_Boiler | E4: 2026 | F4: 0 | G4: FEL 2026 | Base FEL | Base
A5: CA | B5: Canada | C5: buildings | D5: Electric_Boiler | E5: 2027 | F5: 0 | G5: FEL 2026 | Base FEL | Base
A6: CA | B6: Canada | C6: buildings | D6: Electric_Boiler | E6: 2028 | F6: 0 | G6: FEL 2026 | Base FEL | Base
A7: CA | B7: Canada | C7: buildings | D7: Electric_Boiler | E7: 2029 | F7: 0 | G7: FEL 2026 | Base FEL | Base
A8: CA | B8: Canada | C8: buildings | D8: Electric_Boiler | E8: 2030 | F8: 0 | G8: FEL 2026 | Base FEL | Base
A9: CA | B9: Canada | C9: buildings | D9: Electric_Boiler | E9: 2031 | F9: 0 | G9: FEL 2026 | Base FEL | Base
A10: CA | B10: Canada | C10: buildings | D10: Electric_Boiler | E10: 2032 | F10: 0 | G10: FEL 2026 | Base FEL | Base
A11: CA | B11: Canada | C11: buildings | D11: Electric_Boiler | E11: 2033 | F11: 0 | G11: FEL 2026 | Base FEL | Base
A12: CA | B12: Canada | C12: buildings | D12: Electric_Boiler | E12: 2034 | F12: 0 | G12: FEL 2026 | Base FEL | Base
A13: CA | B13: Canada | C13: buildings | D13: Electric_Boiler | E13: 2035 | F13: 0 | G13: FEL 2026 | Base FEL | Base
... A9368: US_R_WECC | B9368: WECC (ex-California) | C9368: transport | D9368: TOTAL | E9368: 2040 | F9368: 95.884405 | G9368: FEL 2026 | Base FEL | Base

Sheet _Data_Macro
A1: geo_code | B1: geo_name | C1: sector | D1: year | E1: raw_demand_twh | F1: gdp_adj_twh | G1: efficiency_adj_twh | H1: price_adj_twh | I1: adjusted_demand_twh | J1: scenario
A2: CA | B2: Canada | C2: buildings | D2: 2024 | E2: 311.46606 | F2: 0 | G2: 0 | H2: 0 | I2: 311.46606 | J2: FEL 2026 | Base FEL | Base
A3: CA | B3: Canada | C3: buildings | D3: 2025 | E3: 311.55721 | F3: 0 | G3: 0 | H3: 0 | I3: 311.55721 | J3: FEL 2026 | Base FEL | Base
A4: CA | B4: Canada | C4: buildings | D4: 2026 | E4: 312.13995 | F4: 0 | G4: 0 | H4: 0 | I4: 312.13995 | J4: FEL 2026 | Base FEL | Base
A5: CA | B5: Canada | C5: buildings | D5: 2027 | E5: 312.9459 | F5: 0 | G5: 0 | H5: 0 | I5: 312.9459 | J5: FEL 2026 | Base FEL | Base
A6: CA | B6: Canada | C6: buildings | D6: 2028 | E6: 313.55515 | F6: 0 | G6: 0 | H6: 0 | I6: 313.55515 | J6: FEL 2026 | Base FEL | Base
A7: CA | B7: Canada | C7: buildings | D7: 2029 | E7: 314.70366 | F7: 0 | G7: 0 | H7: 0 | I7: 314.70366 | J7: FEL 2026 | Base FEL | Base
A8: CA | B8: Canada | C8: buildings | D8: 2030 | E8: 315.40032 | F8: 0 | G8: 0 | H8: 0 | I8: 315.40032 | J8: FEL 2026 | Base FEL | Base
A9: CA | B9: Canada | C9: buildings | D9: 2031 | E9: 316.06496 | F9: 0 | G9: 0 | H9: 0 | I9: 316.06496 | J9: FEL 2026 | Base FEL | Base
A10: CA | B10: Canada | C10: buildings | D10: 2032 | E10: 316.61852 | F10: 0 | G10: 0 | H10: 0 | I10: 316.61852 | J10: FEL 2026 | Base FEL | Base
A11: CA | B11: Canada | C11: buildings | D11: 2033 | E11: 317.22558 | F11: 0 | G11: 0 | H11: 0 | I11: 317.22558 | J11: FEL 2026 | Base FEL | Base
A12: CA | B12: Canada | C12: buildings | D12: 2034 | E12: 317.90271 | F12: 0 | G12: 0 | H12: 0 | I12: 317.90271 | J12: FEL 2026 | Base FEL | Base
A13: CA | B13: Canada | C13: buildings | D13: 2035 | E13: 318.93913 | F13: 0 | G13: 0 | H13: 0 | I13: 318.93913 | J13: FEL 2026 | Base FEL | Base
... A1718: US_R_WECC | B1718: WECC (ex-California) | C1718: transport | D1718: 2040 | E1718: 95.884405 | F1718: 0 | G1718: 0 | H1718: 0 | I1718: 95.884405 | J1718: FEL 2026 | Base FEL | Base

Sheet _Data_Intermediates
A1: geo_code | B1: geo_name | C1: sector | D1: name | E1: year | F1: value | G1: unit
A2: US | B2: United States | C2: transport | D2: bev_total_twh | E2: 2024 | F2: 6.2488615 | G2: TWh
A3: US | B3: United States | C3: transport | D3: other_transport_twh | E3: 2024 | F3: 17.286036 | G3: TWh
A4: US | B4: United States | C4: transport | D4: gdp_correction_factor | E4: 2024 | F4: 1 | G4: ratio
A5: US | B5: United States | C5: transport | D5: bev_total_twh | E5: 2025 | F5: 24.128885 | G5: TWh
A6: US | B6: United States | C6: transport | D6: other_transport_twh | E6: 2025 | F6: 20.219895 | G6: TWh
A7: US | B7: United States | C7: transport | D7: gdp_correction_factor | E7: 2025 | F7: 0.99707887 | G7: ratio
A8: US | B8: United States | C8: transport | D8: bev_total_twh | E8: 2026 | F8: 28.469004 | G8: TWh
A9: US | B9: United States | C9: transport | D9: other_transport_twh | E9: 2026 | F9: 23.854658 | G9: TWh
A10: US | B10: United States | C10: transport | D10: gdp_correction_factor | E10: 2026 | F10: 0.99853944 | G10: ratio
A11: US | B11: United States | C11: transport | D11: bev_total_twh | E11: 2027 | F11: 34.925689 | G11: TWh
A12: US | B12: United States | C12: transport | D12: other_transport_twh | E12: 2027 | F12: 27.808953 | G12: TWh
A13: US | B13: United States | C13: transport | D13: gdp_correction_factor | E13: 2027 | F13: 0.99853944 | G13: ratio
... A10143: US | B10143: United States | C10143: cooling | D10143: share_heat_other | E10143: 2040 | F10143: 0.10154132 | G10143: share

Sheet _Data_BTM
A1: geo_code | B1: geo_name | C1: sector | D1: segment | E1: year | F1: total_twh | G1: btm_rate | H1: btm_twh | I1: grid_twh
A2: CA | B2: Canada | C2: buildings | D2: commercial | E2: 2024 | F2: 0 | G2: 0.01 | H2: 0 | I2: 0
A3: CA | B3: Canada | C3: buildings | D3: commercial | E3: 2024 | F3: 0 | G3: 0.01 | H3: 0 | I3: 0
A4: CA | B4: Canada | C4: buildings | D4: commercial | E4: 2024 | F4: 148.87132 | G4: 0.01 | H4: 1.4887132 | I4: 147.3826
A5: CA | B5: Canada | C5: buildings | D5: commercial | E5: 2025 | F5: 0 | G5: 0.01 | H5: 0 | I5: 0
A6: CA | B6: Canada | C6: buildings | D6: commercial | E6: 2025 | F6: 0 | G6: 0.01 | H6: 0 | I6: 0
A7: CA | B7: Canada | C7: buildings | D7: commercial | E7: 2025 | F7: 148.55095 | G7: 0.01 | H7: 1.4855095 | I7: 147.06544
A8: CA | B8: Canada | C8: buildings | D8: commercial | E8: 2026 | F8: 0 | G8: 0.012 | H8: 0 | I8: 0
A9: CA | B9: Canada | C9: buildings | D9: commercial | E9: 2026 | F9: 0 | G9: 0.012 | H9: 0 | I9: 0
A10: CA | B10: Canada | C10: buildings | D10: commercial | E10: 2026 | F10: 148.22113 | G10: 0.012 | H10: 1.7786535 | I10: 146.44247
A11: CA | B11: Canada | C11: buildings | D11: commercial | E11: 2027 | F11: 0 | G11: 0.014 | H11: 0 | I11: 0
A12: CA | B12: Canada | C12: buildings | D12: commercial | E12: 2027 | F12: 0 | G12: 0.014 | H12: 0 | I12: 0
A13: CA | B13: Canada | C13: buildings | D13: commercial | E13: 2027 | F13: 148.09726 | G13: 0.014 | H13: 2.0733617 | I13: 146.0239
... A7592: US_R_WECC | B7592: WECC (ex-California) | C7592: transport | D7592: road_nonbev | E7592: 2040 | F7592: 1.1999832 | G7592: 0 | H7592: 0 | I7592: 1.1999832
A7594: SECTOR SUMMARY
A7595: geo_code | B7595: geo_name | C7595: sector | E7595: year | F7595: total_twh | G7595: btm_pct | H7595: btm_twh | I7595: grid_twh
A7596: CA | B7596: Canada | C7596: buildings | E7596: 2024 | F7596: 311.46606 | G7596: 0.0090126839 | H7596: 2.8071451 | I7596: 308.65891
A7597: CA | B7597: Canada | C7597: buildings | E7597: 2025 | F7597: 311.55721 | G7597: 0.0090278118 | H7597: 2.8126799 | I7597: 308.74453
A7598: CA | B7598: Canada | C7598: buildings | E7598: 2026 | F7598: 312.13995 | G7598: 0.011377078 | H7598: 3.5512405 | I7598: 308.58871
A7599: CA | B7599: Canada | C7599: buildings | E7599: 2027 | F7599: 312.9459 | G7599: 0.013738147 | H7599: 4.2992969 | I7599: 308.64661
A7600: CA | B7600: Canada | C7600: buildings | E7600: 2028 | F7600: 313.55515 | G7600: 0.016114099 | H7600: 5.0526587 | I7600: 308.50249
A7601: CA | B7601: Canada | C7601: buildings | E7601: 2029 | F7601: 314.70366 | G7601: 0.018503603 | H7601: 5.8231515 | I7601: 308.88051
A7602: CA | B7602: Canada | C7602: buildings | E7602: 2030 | F7602: 315.40032 | G7602: 0.020909797 | H7602: 6.5949567 | I7602: 308.80536
A7603: CA | B7603: Canada | C7603: buildings | E7603: 2031 | F7603: 316.06496 | G7603: 0.024258617 | H7603: 7.667299 | I7603: 308.39766
A7604: CA | B7604: Canada | C7604: buildings | E7604: 2032 | F7604: 316.61852 | G7604: 0.027612157 | H7604: 8.7425204 | I7604: 307.876
A7605: CA | B7605: Canada | C7605: buildings | E7605: 2033 | F7605: 317.22558 | G7605: 0.030970293 | H7605: 9.8245691 | I7605: 307.40101
A7606: CA | B7606: Canada | C7606: buildings | E7606: 2034 | F7606: 317.90271 | G7606: 0.034335039 | H7606: 10.915202 | I7606: 306.98751
A7607: CA | B7607: Canada | C7607: buildings | E7607: 2035 | F7607: 318.93913 | G7607: 0.037705065 | H7607: 12.025621 | I7607: 306.91351
... A9482: US_R_WECC | B9482: WECC (ex-California) | C9482: transport | E9482: 2040 | F9482: 95.884405 | G9482: 0.13504954 | H9482: 12.949145 | I9482: 82.93526

Sheet _Data_Grid
A1: geo_code | B1: geo_name | C1: sector | D1: year | E1: total_twh | F1: btm_twh | G1: at_meter_twh | H1: td_loss_rate | I1: td_loss_twh | J1: busbar_twh
A2: CA | B2: Canada | C2: buildings | D2: 2024 | E2: 311.46606 | F2: 2.8071451 | G2: 308.65891 | H2: 0.05 | I2: 15.432946 | J2: 324.09186
A3: CA | B3: Canada | C3: buildings | D3: 2025 | E3: 311.55721 | F3: 2.8126799 | G3: 308.74453 | H3: 0.05 | I3: 15.437227 | J3: 324.18176
A4: CA | B4: Canada | C4: buildings | D4: 2026 | E4: 312.13995 | F4: 3.5512405 | G4: 308.58871 | H4: 0.05 | I4: 15.429436 | J4: 324.01815
A5: CA | B5: Canada | C5: buildings | D5: 2027 | E5: 312.9459 | F5: 4.2992969 | G5: 308.64661 | H5: 0.05 | I5: 15.43233 | J5: 324.07894
A6: CA | B6: Canada | C6: buildings | D6: 2028 | E6: 313.55515 | F6: 5.0526587 | G6: 308.50249 | H6: 0.05 | I6: 15.425124 | J6: 323.92761
A7: CA | B7: Canada | C7: buildings | D7: 2029 | E7: 314.70366 | F7: 5.8231515 | G7: 308.88051 | H7: 0.05 | I7: 15.444025 | J7: 324.32453
A8: CA | B8: Canada | C8: buildings | D8: 2030 | E8: 315.40032 | F8: 6.5949567 | G8: 308.80536 | H8: 0.05 | I8: 15.440268 | J8: 324.24563
A9: CA | B9: Canada | C9: buildings | D9: 2031 | E9: 316.06496 | F9: 7.667299 | G9: 308.39766 | H9: 0.05 | I9: 15.419883 | J9: 323.81755
A10: CA | B10: Canada | C10: buildings | D10: 2032 | E10: 316.61852 | F10: 8.7425204 | G10: 307.876 | H10: 0.05 | I10: 15.3938 | J10: 323.2698
A11: CA | B11: Canada | C11: buildings | D11: 2033 | E11: 317.22558 | F11: 9.8245691 | G11: 307.40101 | H11: 0.05 | I11: 15.37005 | J11: 322.77106
A12: CA | B12: Canada | C12: buildings | D12: 2034 | E12: 317.90271 | F12: 10.915202 | G12: 306.98751 | H12: 0.05 | I12: 15.349376 | J12: 322.33689
A13: CA | B13: Canada | C13: buildings | D13: 2035 | E13: 318.93913 | F13: 12.025621 | G13: 306.91351 | H13: 0.05 | I13: 15.345675 | J13: 322.25918
... A1701: US_R_WECC | B1701: WECC (ex-California) | C1701: transport | D1701: 2040 | E1701: 95.884405 | F1701: 12.949145 | G1701: 82.93526 | H1701: 0.05 | I1701: 4.146763 | J1701: 87.082023

Sheet _Scenario_Params
A1: param_id | B1: display_name | C1: sector | D1: chosen_preset | E1: scaling | F1: description | G1: scope
A2: bev_share | B2: BEV share of vehicle sales | C2: transport | D2: base_fel | E2: 1 | F2: Base FEL (Fusion Energy Landscape) | G2: country
A3: buildings_scenario | B3: Buildings scenario | C3: buildings | D3: base_fel | F3: FEL base: Policy (EU+CA), BAU (US) | G3: country
A4: industry_scenario | B4: Industry scenario | C4: industry | D4: base_fel | E4: 1 | F4: Continuation: vintage-corrected (US/CA), BAU relocation (EU) | G4: country
A5: industry_electrification_iron_steel | B5: Industry electrification — Iron & Steel | C5: industry | D5: base_fel | E5: 1 | F5: Base electrification of Iron & Steel | G5: country
A6: industry_electrification_chemicals | B6: Industry electrification — Chemicals | C6: industry | D6: base_fel | E6: 1 | F6: Base electrification of chemicals | G6: country
A7: industry_electrification_other | B7: Industry electrification — Other | C7: industry | D7: base_fel | E7: 1 | F7: Base electrification of other industry | G7: country
A8: dc_scenario | B8: Data center scenario | C8: data_centers | D8: base_fel | F8: Base DC capacity trajectory | G8: region
A9: dc_btm_sensitivity | B9: DC BTM/FTM sensitivity | C9: data_centers | D9: base_fel | F9: Base BTM/FTM split | G9: region
A10: hydrogen_scenario | B10: Hydrogen scenario | C10: hydrogen | D10: base_fel | F10: Base — Continued Momentum, partial RED III | G10: region
A11: energy_efficiency | B11: Energy efficiency improvements | C11: cross_cutting | D11: base_fel | E11: 1 | F11: Base efficiency improvements | G11: region
A12: gdp_growth | B12: GDP growth | C12: cross_cutting | D12: base_fel | E12: 1 | F12: McKinsey base GDP projection | G12: country
A13: power_prices | B13: Power prices | C13: cross_cutting | D13: base_fel | E13: 1 | F13: Base power price trajectory | G13: country
A14: transport_scenario | B14: Transport scenario | C14: transport | D14: base_fel | F14: Base case — EU fleet emission standards (policy) | G14: country
A15: transport_us_scenario | B15: US transport BEV scenario | C15: transport | D15: base_fel | F15: US base — IEA STEPS 2030, EIA AEO 2025 Reference 2040 | G15: country
A16: cooling_split | B16: Cooling split (own sector) | C16: cooling | D16: pdm_2026-09-23 | F16: Cooling share of buildings from Power Demand Model 2026-09-23 (climate removed), applied to v2 buildings level; carved out of Other_Buildings | G16: region
A17: climate_physical | B17: Physical climate pathway (cooling/heating) | C17: cooling | D17: ssp245 | F17: SSP2-4.5 CDD/HDD indices (2024=1) from PDM 2026-09-23, plus temperature-dependent COP for AC and heat pumps (colleagues SSP2-4.5 hourly series, US ISOs; Canada proxy) | G17: region
A18: cooling_ac_adoption | B18: AC adoption from warmer summers | C18: cooling | D18: mcneil_gap_closure | E18: 1 | F18: Climate-driven AC ownership, McNeil and Letschert saturation curve as gap closure; residential only; scaling = marginal adopter intensity | G18: region

Sheet _Provenance
A1: source_id | B1: name | C1: provider | D1: dataset_id | E1: version | F1: variables | G1: geographies | H1: time_range | I1: unit | J1: excel_sheet
A2: mckinsey_fusion_vehicle_sales | B2: McKinsey Fusion — Vehicle Sales | C2: McKinsey | D2: 19 | E2: 2025-04-11 | F2: vehicle_sales | G2: DE, FR, IT, ES, UK, US, US_R_CALIFORNIA, US_R_ERCOT, US_R_PJM | H2: 2022-2040 | I2: # | J2: Vehicle sales
A3: mckinsey_fusion_vehicle_parc | B3: McKinsey Fusion — Vehicle Parc | C3: McKinsey | D3: 1519 | E3: 2025-04-11 | F3: vehicle_parc | G3: DE, FR, IT, ES, UK, US, US_R_CALIFORNIA, US_R_ERCOT, US_R_PJM | H3: 2022-2040 | I3: # | J3: Vehicle parc
A4: mckinsey_fusion_bev_power_demand | B4: McKinsey Fusion — BEV Power Demand | C4: McKinsey | D4: 48,92,162 | E4: 2025-04-11 | F4: bev_power_demand | G4: DE, FR, IT, ES, UK, US, US_R_CALIFORNIA, US_R_ERCOT, US_R_PJM | H4: 2022-2040 | I4: TWh | J4: BEV power demand
A5: mckinsey_derived_bev_consumption | B5: BEV Power Consumption per Vehicle (Derived) | C5: McKinsey | D5: derived | E5: 2025-04-11 | F5: bev_power_consumption_per_vehicle | G5: DE, FR, IT, ES, UK, US | H5: 2022-2040 | I5: MWh/# | J5: BEV power consumption
A6: mckinsey_fusion_transport_power | B6: McKinsey Fusion — Transport Power Consumption | C6: McKinsey | D6: 627 | E6: 2025-04-11 | F6: transport_power_consumption | G6: DE, FR, IT, ES, UK, US | H6: 2022-2040 | I6: TWh | J6: Transport power consumption
A7: mckinsey_fusion_heat_pump_stock | B7: McKinsey Fusion — Heat Pump Stock | C7: McKinsey | D7: 3144 | E7: 2025-04-11 | F7: heat_pump_stock | G7: DE, FR, IT, ES, UK, US | H7: 2022-2040 | I7: # | J7: Heat pump stock
A8: mckinsey_fusion_heat_pump_consumption | B8: McKinsey Fusion — Heat Pump Power Consumption | C8: McKinsey | D8: 3179 | E8: 2025-04-11 | F8: heat_pump_power_consumption | G8: DE, FR, IT, ES, UK, US | H8: 2022-2040 | I8: TWh | J8: Heat pump power consumption
A9: mckinsey_fusion_electric_boiler | B9: McKinsey Fusion — Electric Boiler Consumption | C9: McKinsey | D9: 3179 | E9: 2025-04-11 | F9: electric_boiler_consumption | G9: DE, FR, IT, ES, UK, US | H9: 2022-2040 | I9: TWh | J9: Electric boilers power consumpt
A10: mckinsey_derived_hp_boiler_iso | B10: HP and Electric Boiler ISO Back-calculation | C10: McKinsey | D10: derived | E10: 2025-04-11 | F10: hp_boiler_iso | G10: US | H10: 2022-2040 | I10: TWh | J10: HP and Electric Boiler ISO
A11: mckinsey_fusion_building_consumption | B11: McKinsey Fusion — Additional Building Power Consumption | C11: McKinsey | D11: 627 | E11: 2025-04-11 | F11: building_additional_consumption | G11: DE, FR, IT, ES, UK, US | H11: 2022-2040 | I11: TWh | J11: Add. building power consumption
A12: mckinsey_fusion_industry_total | B12: McKinsey Fusion — Industry Total Final Consumption | C12: McKinsey | D12: 627 | E12: 2025-04-11 | F12: industry_total_final_consumption | G12: DE, FR, IT, ES, UK, US | H12: 2022-2040 | I12: TWh | J12: Industry total final consumptio
... A18: mckinsey_dc_capacity_iso | B18: Data Center Capacity per ISO Zone | C18: McKinsey | D18: derived | E18: 2025-06-11 | F18: data_center_capacity_iso | G18: US_R_CALIFORNIA, US_R_ERCOT, US_R_PJM | H18: 2024-2040 | I18: MW | J18: Data Centers capacity_ISO zones
A19: bnef_dcbyte_2025q4 | B19: BNEF DCByte — Data Center Live IT Capacity | C19: BloombergNEF | D19: dcbyte | E19: 2025-04-01 | F19: data_center_facility_capacity | G19: DE, FR, IT, ES, UK, PL, CA, US_R_CALIFORNIA, US_R_ERCOT, US_R_PJM, US_R_OTHER | H19: 1990-2025 | I19: GW
A20: us_esa_large_load | B20: US ESA Large Load Forecast | C20: ESA/Utilities | D20: esa_2026 | E20: 2026-04-01 | F20: data_center_capacity | G20: US_R_CALIFORNIA, US_R_ERCOT, US_R_PJM, US_R_OTHER | H20: 2025-2035 | I20: TWh | J20: US_ESA_Forecast
A21: pmk_q1_2026_pipeline | B21: PMK Quarterly Demand Update — Pipeline Adder | C21: PMK | D21: pmk_q1_2026 | E21: 2026-03-01 | F21: data_center_capacity_adder | G21: US_R_CALIFORNIA, US_R_ERCOT, US_R_PJM, US_R_OTHER | H21: 2025-2035 | I21: TWh | J21: US_ESA_Pipeline_Adder
A22: eudca_2026 | B22: EUDCA 2026 — EU Data Centre IT Power | C22: EUDCA/Pb7 | D22: pb7_feb_2026 | E22: 2026-02-01 | F22: data_center_capacity | G22: DE, FR, IT, ES, UK, PL, EU_OTHER | H22: 2024-2031 | I22: GW | J22: EU_EUDCA_2026
A23: us_pools_260522 | B23: US Pools — Data Center Demand (Capacity MW) | C23: US Pools supplier | D23: us_pools_260522 | E23: 2026-05-22 | F23: data_center_us_capacity_mw | G23: US_R_CALIFORNIA, US_R_WECC, US_R_SPP, US_R_MISO, US_R_ERCOT, US_R_SERC, US_R_PJM, US_R_NYISO, US_R_ISONE | H23: 2025-2035 | I23: GW | J23: Demand Modifier
A24: us_pools_active_gw_260522 | B24: US Pools — Active Pipeline GW | C24: US Pools supplier | D24: us_pools_260522 | E24: 2026-05-22 | F24: data_center_us_active_gw | G24: US_R_CALIFORNIA, US_R_WECC, US_R_SPP, US_R_MISO, US_R_ERCOT, US_R_SERC, US_R_PJM, US_R_NYISO, US_R_ISONE | H24: 2025-2035 | I24: GW | J24: Upside GW
A25: us_btm_gw_snapshot | B25: US DC BTM GW — Fixed Trajectory | C25: Analyst (seeded from prior model snapshot) | D25: us_btm_snapshot | E25: 2026-05-22 | F25: data_center_us_btm_gw | G25: US_R_CALIFORNIA, US_R_WECC, US_R_SPP, US_R_MISO, US_R_ERCOT, US_R_SERC, US_R_PJM, US_R_NYISO, US_R_ISONE | H25: 2025-2040 | I25: GW | J25: BTM_GW_Trajectory
A26: us_bnef_live_anchor_2025 | B26: US DC BNEF Live — 2025 Anchor | C26: BNEF DCByte (per-sub-region snapshot) | D26: us_bnef_live_2025 | E26: 2026-05-22 | F26: data_center_us_bnef_live | G26: US_R_CALIFORNIA, US_R_WECC, US_R_SPP, US_R_MISO, US_R_ERCOT, US_R_SERC, US_R_PJM, US_R_NYISO, US_R_ISONE | H26: 2025-2025 | I26: GW | J26: BNEF_Live_2025
A27: canada_logistic_v1 | B27: Canada DC Forecast — Provincial Logistic Curves | C27: IESO/AESO/HQ/Cushman | D27: canada_dc_v1 | E27: 2026-04-01 | F27: data_center_capacity | G27: CA | H27: 2024-2040 | I27: GW | J27: CA_Province_Curves
A28: bnef_dcbyte_facilities_enriched | B28: BNEF DCByte — Enriched Facility Database | C28: BloombergNEF | D28: dcbyte_enriched | E28: 2025-04-01 | F28: data_center_facility_reference | G28: DE, FR, IT, ES, UK, PL, CA, US_R_CALIFORNIA, US_R_ERCOT, US_R_PJM, US_R_OTHER | H28: 2025-2025 | I28: MW
A29: dc_assumptions_v1 | B29: DC Assumptions Workbook v1 | C29: FEL/Internal | D29: dc_assumptions | E29: 2026-04-01 | F29: dc_assumptions | G29: US_R_CALIFORNIA, US_R_ERCOT, US_R_PJM, US_R_OTHER, DE, FR, IT, ES, UK, PL, EU_OTHER, CA | H29: 2024-2040 | I29: various
A30: mckinsey_fusion_h2_power | B30: McKinsey Fusion — Hydrogen Power Intensity | C30: McKinsey | D30: 2570 | E30: 2025-04-11 | F30: hydrogen_power_intensity | G30: EU5, US | H30: 2022-2040 | I30: TWh/mtpa | J30: Power demand for hydrogen
A31: mckinsey_h2_production | B31: McKinsey — Green H2 Production (FEL aligned) | C31: McKinsey | D31: continued_momentum | E31: 2025-04-11 | F31: hydrogen_production | G31: EU5, US | H31: 2022-2040 | I31: mtpa | J31: H2 production
A32: gh2_scenarios_2026 | B32: GH2 Europe Scenarios v5 — Green Hydrogen TWh | C32: GH2 Europe / FEL | D32: gh2_v5 | E32: 2026-03 | F32: hydrogen_power_demand | G32: DE, FR, IT, ES, UK, PL, EU_OTHER, US, CA | H32: 2024-2040 | I32: TWh
A33: h2_btm_generation_mix_2026 | B33: Hydrogen BTM Generation Mix — RE Technology Shares | C33: FEL / analyst | D33: h2_btm_mix | E33: 2026-03 | F33: hydrogen_btm_generation_mix | G33: DE, FR, IT, ES, UK, PL, EU_OTHER, US, CA | H33: 2024-2040 | I33: share
A34: mckinsey_gdp | B34: McKinsey — GDP Projections | C34: McKinsey | D34: mck_gdp | E34: 2025-04-11 | F34: gdp_mck | G34: DE, FR, IT, ES, UK, US | H34: 2022-2040 | I34: million USD | J34: GDP McK
A35: discord_gdp | B35: Discord — GDP (S&P Energy Outlook to 2050) | C35: Discord/S&P | D35: discord_energy_2024 | E35: 2024-07 | F35: gdp_discord | G35: DE, FR, IT, ES, UK, US | H35: 1990-2050 | I35: billion 2023 USD | J35: GDP SP Discord
A36: eia_retail_sales | B36: EIA Retail Sales of Electricity | C36: EIA | D36: electricity_data_browser | E36: 2026-04-01 | F36: retail_electricity_sales | G36: US | H36: 2001-2025 | I36: TWh
A37: us_industry_scope_adjustment | B37: US Industry Scope Adjustment Wedge | C37: EIA AEO 2025 + analyst-derived | D37: scope_gap | E37: 2026-04-08 | F37: scope_adjustment_power_twh | G37: US | H37: 2022-2040 | I37: TWh
A38: buildings_trajectory_adjustment | B38: Buildings Trajectory Adjustment Wedge | C38: EIA STEO + European Climate Observatory + IEA + analyst-derived | D38: trajectory_wedge | E38: 2026-04-08 | F38: wedge_twh | G38: US, DE, FR, IT, ES, UK | H38: 2022-2040 | I38: TWh
A39: mckinsey_derived_td_losses | B39: T&D Losses | C39: McKinsey | D39: derived | E39: 2025-04-11 | F39: td_losses | G39: DE, FR, IT, ES, UK, US | H39: 2022-2040 | I39: TWh | J39: T&D losses
A40: mckinsey_fusion_additional_demand | B40: McKinsey Fusion — Additional Power Demand | C40: McKinsey | D40: 2572 | E40: 2025-04-11 | F40: additional_power_demand | G40: DE, FR, IT, ES, UK, US | H40: 2022-2040 | I40: TWh | J40: Additional power demand
A41: mckinsey_energy_efficiency | B41: McKinsey — Energy Efficiency Assumptions | C41: McKinsey | D41: pttx | E41: 2025-04-11 | F41: energy_efficiency | G41: EU5, US | H41: 2040-2040 | I41: ratio | J41: Energy efficiency
A42: mckinsey_elasticities | B42: McKinsey — Income/GDP Elasticities | C42: McKinsey | D42: regression | E42: 2025-04-11 | F42: elasticities | G42: DE, FR, IT, ES, UK, US | H42: 2024-2040 | I42: ratio | J42: Elasticities
A43: mckinsey_fusion_total_fuel | B43: McKinsey Fusion — Total Fuel Consumption | C43: McKinsey | D43: 627 | E43: 2025-04-11 | F43: total_fuel_consumption | G43: DE, FR, IT, ES, UK, US | H43: 2022-2040 | I43: TWh | J43: Total fuel consumption
A44: other_data | B44: Other Data (FX rates, emission factors) | C44: Various | D44: other | E44: 2025-04-11 | F44: other_data | H44: 2023-2023 | I44: various | J44: Other data
A45: mckinsey_us_iso_demand | B45: US ISO Power Demand by Segment | C45: McKinsey | D45: derived | E45: 2025-04-11 | F45: us_iso_power_demand | G45: US_R_CALIFORNIA, US_R_ERCOT, US_R_PJM | H45: 2022-2040 | I45: TWh | J45: US ISO power demand
A46: mckinsey_legacy_other_transport | B46: McKinsey Legacy — Other Transport (Rail, Maritime, Road_NonBEV) | C46: McKinsey | D46: derived | E46: 2025-04-11 | F46: transport_power_consumption_other | G46: DE, FR, IT, ES, UK, US, US_R_CALIFORNIA, US_R_ERCOT, US_R_PJM | H46: 2022-2040 | I46: TWh
A47: sp_scaled_industry_canada | B47: S&P Scaled Industry — Canada | C47: S&P Global | D47: derived | E47: 2026-03 | F47: industry_power_consumption, industry_total_final_consumption | G47: CA | H47: 2022-2040 | I47: TWh
A48: eurostat_scaled_industry_poland | B48: Eurostat Scaled Industry — Poland | C48: Eurostat | D48: derived | E48: 2026-03 | F48: industry_power_consumption, industry_total_final_consumption | G48: PL | H48: 2022-2040 | I48: TWh
A49: eurostat_residual_industry_eu_other | B49: Eurostat Residual Industry — EU_Other | C49: Eurostat | D49: derived | E49: 2026-03 | F49: industry_power_consumption, industry_total_final_consumption | G49: EU_OTHER | H49: 2022-2040 | I49: TWh
A50: industry_btm_eurostat_v2 | B50: Industry BTM Rates — Eurostat Autoproduction | C50: Eurostat | D50: nrg_ind_pehap | E50: 2026-03 | F50: btm_rate, btm_component | G50: DE, FR, IT, ES, UK, PL, EU_OTHER, US, US_R_CALIFORNIA, US_R_ERCOT, US_R_PJM, US_R_OTHER, CA | H50: 2024-2040 | I50: ratio
A51: pdm_2026_09_23_buildings_split | B51: Power Demand Model 2026-09-23 buildings sub-segments (Cooling, Heating_HP, Heating_Other, Appliances_MEL, PV self-consumption, NonSpecified services) | C51: Internal | D51: base_fel.xlsx | E51: 2026-09-23 | F51: buildings split, cdd_index, hdd_index | G51: CA, US_R_* | H51: 2024-2040 | I51: TWh
A52: ssp245_hourly_temperature_us | B52: Climate projections SSP2-45 for US, hourly region temperatures 2030/2035 | C52: Internal (colleagues) | D52: 2026-10-14 | E52: 2026-10-14 | F52: hourly temperature | G52: US_R_* (9 ISOs) | H52: 2030, 2035 | I52: C
A53: temp_2018_weather_year | B53: 2018 hourly weather year, North America (via US ISO Temperature Outlook) | C53: Internal | D53: 2018_temperature_northamerica | E53: 2026-10-19 | F53: hourly temperature | G53: US_R_* (9 ISOs) | H53: 2018 | I53: C
A54: staffell_2012_hp_cop | B54: Staffell et al. 2012, A review of domestic heat pumps, Energy Environ. Sci. 5, 9291: ASHP COP fit | C54: Literature | D54: doi:10.1039/c2ee22653g | E54: 2012 | F54: heat pump COP | G54: ALL | H54: n/a | I54: ratio
A55: mcneil_letschert_ac_saturation | B55: McNeil and Letschert, climate maximum AC saturation curve | C55: Literature (LBNL) | D55: LBNL | E55: 2008/2010 | F55: AC saturation vs CDD | G55: ALL | H55: n/a | I55: share
A56: eia_recs_2020_ac | B56: EIA RECS 2020: households using air conditioning by census region | C56: EIA | D56: RECS 2020 | E56: 2022 | F56: AC ownership | G56: US | H56: 2020 | I56: share
A57: statcan_2025_ac | B57: Statistics Canada 2025: households with air conditioning | C57: Statistics Canada | D57: The Daily 2025-07-08 | E57: 2025 | F57: AC ownership | G57: CA | H57: 2025 | I57: share
